Workbook

Sheet Dashboard
B1: Total | D1: Differential | F1: Flux | H1: Spending | J1: Net Worth | W1: Current Paid | Y1: Total Paid | AA1: Interest | AE1: Gas Data (Averages)
A2: This Month | B2: ='Data Analysis'!K58 -> 3160.6221 | D2: ='Data Analysis'!AJ58 -> 88.939127 | F2: ='Data Analysis'!AG58 -> 17.76 | H2: ='Data Analysis'!R58 -> 3347.6809 | V2: Original | W2: ='Student Loans'!X3 -> 23664.19 | Y2: ='Student Loans'!D16 -> 51631.54 | AA2: ='Student Loans'!E16 -> 8994 | AC2: CPG | AD2: MPG | AE2: MPD | AF2: CPM
A3: Last Month | B3: ='Data Analysis'!K57 -> 3071.6829 | D3: ='Data Analysis'!AJ57 -> 84.860791 | F3: ='Data Analysis'!AG57 -> -123.11 | H3: ='Data Analysis'!R57 -> 2825.5992 | V3: Saved | W3: =Y3-Y2 -> -4055.0151 | Y3: ='Student Loans'!D17 -> 47576.525 | AA3: ='Student Loans'!E17 -> 4938.9849 | AC3: =Gas!N3 -> 4.4404006 | AD3: =Gas!O3 -> 25.461285 | AE3: =Gas!P3 -> 6.0694424 | AF3: =Gas!Q3 -> 0.1752112

Sheet Data
A2: 2020 | C2: èè INFLOW èè | F2: èèèè OUTFLOW èèèè
A3: êêê | B3: 43952 | F3: Necessary | I3: Unnecessary | L3: Savings B | M3: Savings A | N3: Stocks
F5: 240 | G5: Food | I5: 205 | J5: Green | O5: Flux | P5: Net | Q5: Estimated | U5: Actual | W5: Net | X5: Flux | Z5: Cash | AB5: Bank
B6: 43959 | C6: 505.71 | D6: Work | F6: 120 | G6: Gas | I6: 9.99 | J6: Spotify | Q6: =U6 -> 104.64 | R6: Balance | U6: =AB6+Z6 -> 104.64 | Y6: Wallet | Z6: 21 | AA6: Checking | AB6: 83.64
B7: 43973 | C7: 308.46 | D7: Work | F7: 712.86 | G7: UCO | I7: 6.99 | J7: Disney Plus | Q7: =U7 -> 645.96 | R7: Savings | U7: =AB7+Z7+Z8 -> 645.96 | Y7: Drawer | Z7: 144 | AA7: Savings | AB7: 401.96
Q8: =U8 -> 750.6 | R8: Total | U8: =AB6+AB7+Z6+Z7+Z8 -> 750.6 | Y8: Coins | Z8: 100
A9: êêê | B9: 43983
F10: =9+34.9+9.27+8.87+9.27+9+10.57+9.27+7+7+32.55+8+10+9+8+7+41.06+9+9 -> 247.76 | G10: Food | I10: =50+120+90+115 -> 375 | J10: Green
C11: =50+70+60 -> 180 | F11: =21.19+22 -> 43.19 | G11: Gas | I11: 9.99 | J11: Spotify | Z11: Cash | AB11: Bank
C12: 500 | D12: Mom | F12: 10 | G12: Haircut | I12: 6.99 | J12: Disney Plus | Q12: =Q6+P14 -> 8.65 | R12: Balance | U12: =AB12+Z12 -> 85.92 | W12: =U12-U6 -> -18.72 | X12: =W12/30 -> -0.624 | Y12: Wallet | Z12: 31 | AA12: Checking | AB12: 54.92
B13: 44001 | C13: 645.2 | D13: UCO | F13: 712.86 | G13: UCO | I13: 15.4 | J13: EVE Online | Q13: =Q7+SUM(L10:L13) -> 645.96 | R13: Savings | U13: =AB13+Z13+Z14 -> 497.96 | W13: =U13-U7 -> -148 | X13: =W13/30 -> -4.9333333 | Y13: Drawer | Z13: =140+144 -> 284 | AA13: Savings | AB13: 101.96
O14: =P14/30 -> -3.1996667 | P14: =SUM(C9:C14)-SUM(F9:F14)-SUM(I9:I14) -> -95.99 | Q14: =Q12+Q13 -> 654.61 | R14: Total | U14: =AB12+AB13+Z12+Z13+Z14 -> 583.88 | W14: =U14-U8 -> -166.72 | X14: =W14/30 -> -5.5573333 | Y14: Coins | Z14: 112
A15: êêê | B15: 44013
C16: =75+60 -> 135 | F16: =9+10+9+7+10+15+9+9+10+9+10+6+8.47+21.7+10+8+10+6+10+10+11+38.71+6+9.48+10.79+7 -> 280.15 | G16: Food | I16: =240+75+90+90+110 -> 605 | J16: Green | L16: -240
C17: 200 | D17: Mom | F17: =26.02+26.14 -> 52.16 | G17: Gas | I17: 9.99 | J17: Spotify | L17: 170 | Z17: Cash | AB17: Bank
B18: 44014 | C18: 645.2 | D18: UCO | F18: 300 | G18: Mom | I18: 6.99 | J18: Disney Plus | L18: -100 | O18: =P18/31 -> 10.449032 | P18: =SUM(C16:C19)-SUM(F16:F19)-SUM(I16:I19)-SUM(L16:L19) -> 323.92 | Q18: =Q12+P18 -> 332.57 | R18: Balance | U18: =AB18+Z18 -> 367.95 | W18: =U18-U12 -> 282.03 | X18: =W18/31 -> 9.0977419 | Y18: Wallet | Z18: 216 | AA18: Checking | AB18: 151.95
B19: 44043 | C19: 629.01 | D19: UCO | I19: 1 | J19: Xbox Live | L19: 200 | O19: =P19/31 -> 0.96774194 | P19: =SUM(L15:L20) -> 30 | Q19: =Q13+SUM(L16:L19) -> 675.96 | R19: Savings | U19: =AB19+Z19+Z20 -> 562.96 | W19: =U19-U13 -> 65 | X19: =W19/31 -> 2.0967742 | Y19: Drawer | Z19: =344 -> 344 | AA19: Savings | AB19: 101.96
O20: =P20/31 -> 11.416774 | P20: =SUM(C15:C20)-SUM(F15:F20)-SUM(I15:I20) -> 353.92 | Q20: =Q14+P20 -> 1008.53 | R20: Total | U20: =AB18+AB19+Z18+Z19+Z20 -> 930.91 | W20: =U20-U14 -> 347.03 | X20: =W20/31 -> 11.194516 | Y20: Coins | Z20: 117
A21: êêê | B21: August
F22: =8+32.55+7.8+6+9.48+9+6+7+20+40+4.55+10+5+12+8.47+5+10+5+10+8+21.7+5+5+10+8.47+5+9+6+22+9+10 -> 335.02 | G22: Food | I22: =90+90+35+80+200 -> 495 | J22: Green | L22: -100
F23: =24.95+8.06+26.8 -> 59.81 | G23: Gas | I23: 19.99 | J23: Call of Duty | L23: -100
F24: 10 | G24: Haircut | I24: 9.99 | J24: Spotify
F25: 50 | G25: Caitlin's Birthday | I25: 19.99 | J25: Fall Guys | Z25: Cash | AB25: Bank
C26: =60+60 -> 120 | F26: 19.99 | G26: Adobe Creative | I26: 14.99 | J26: Xbox Live | O26: =P26/31 -> -10.221613 | P26: =SUM(C24:C27)-SUM(F22:F27)-SUM(I22:I27)-SUM(L22:L27) -> -316.87 | Q26: =Q18+P26 -> 15.7 | R26: Balance | U26: =Z26+AB26 -> 51.08 | W26: =U26-U18 -> -316.87 | X26: =W26/31 -> -10.221613 | Y26: Wallet | Z26: 39 | AA26: Checking | AB26: 12.08
B27: 44057 | C27: 404.9 | D27: UCO | I27: 6.99 | J27: Disney Plus | O27: =P27/31 -> -6.4516129 | P27: =SUM(L22:L27) -> -200 | Q27: =Q19+SUM(L22:L27) -> 475.96 | R27: Savings | U27: =Z27+Z28+AB27 -> 370.96 | W27: =U27-U19 -> -192 | X27: =W27/31 -> -6.1935484 | Y27: Drawer | Z27: 144 | AA27: Savings | AB27: 101.96
O28: =P28/31 -> -16.673226 | P28: =SUM(C24:C27)-SUM(F22:F27)-SUM(I22:I27) -> -516.87 | Q28: =Q20+P28 -> 491.66 | R28: Total | U28: =U26+U27 -> 422.04 | W28: =U28-U20 -> -508.87 | X28: =W28/31 -> -16.415161 | Y28: Coins | Z28: 125
A29: êêê | B29: September
F30: =5+9+5+8.57+9+9+6+10+6+9.47+7.47+10+9+6+2+9+21.7+7+9+9+11+9+9+9+9+6+9+17+6+9+8.9+8+36.95+8.9+9+7.81+10 -> 350.77 | G30: Food | I30: =40+115+95+60+200+25 -> 535 | J30: Green | L30: -70
F31: =26.49+9.97+26.54+25.49 -> 88.49 | G31: Gas | I31: 9.99 | J31: Spotify | L31: -40
C32: =30+60+60 -> 150 | F32: 10 | G32: Haircut | I32: 0.99 | J32: KRON App | L32: 15
C33: 100 | D33: Mom | F33: 1463.51 | G33: UCO | I33: 6.99 | J33: Disney Plus | L33: 2980
B34: 44085 | C34: 113.8 | D34: UCO | F34: 300 | G34: Mom | I34: 93.82 | J34: External HDD
B35: 44088 | C35: 8410 | D35: FAFSA Loan | F35: 2400 | G35: VW | I35: 19.99 | J35: Masks | Z35: Cash | AB35: Bank
B36: 44092 | C36: 180 | D36: Papa | F36: 290 | G36: VW | I36: 19.99 | J36: Adobe Creative | O36: =P36/30 -> 19.635333 | P36: =SUM(C30:C37)-SUM(F30:F37)-SUM(I30:I37)-SUM(L30:L37) -> 589.06 | Q36: =Q26+P38-SUM(L30:L37) -> 604.76 | R36: Balance | U36: =Z36+AB36 -> 629.59 | W36: =U36-U26 -> 578.51 | X36: =W36/30 -> 19.283667 | Y36: Wallet | Z36: 297 | AA36: Checking | AB36: 332.59
B37: 44099 | C37: 113.8 | D37: UCO | F37: 4 | G37: Notebook | O37: =P37/30 -> 96.166667 | P37: =SUM(L30:L37) -> 2885 | Q37: =Q27+SUM(L30:L37) -> 3360.96 | R37: Savings | U37: =Z37+Z38+AB37 -> 3260.99 | W37: =U37-U27 -> 2890.03 | X37: =W37/30 -> 96.334333 | Y37: Drawer | Z37: 124 | AA37: Savings | AB37: 3001.99
O38: =P38/30 -> 115.802 | P38: =SUM(C30:C37)-SUM(F30:F37)-SUM(I29:I38) -> 3474.06 | Q38: =Q36+Q37 -> 3965.72 | R38: Total | U38: =U36+U37 -> 3890.58 | W38: =U38-U28 -> 3468.54 | X38: =W38/30 -> 115.618 | Y38: Coins | Z38: 135
A39: êêê | B39: October
F40: =9+2+9+15+7.81+9+10+12+5+9+27+6+9+9+9+10+7.81+10+36.66+8+11+9+8+6+7+5+9+9+5 -> 289.28 | G40: Food | I40: =65+80+220 -> 365 | J40: Green
F41: =22.05+23.51 -> 45.56 | G41: Gas | I41: 39.99 | J41: SW Squadrons
F42: 24 | G42: AIP | I42: 9.99 | J42: Spotify
F43: 20 | G43: Haircut | I43: 0.99 | J43: KRON App
C44: =60+70 -> 130 | F44: 22 | G44: Walmart | I44: 6.99 | J44: Disney Plus
B45: 44112 | C45: 165 | D45: Papa | F45: 87.5 | G45: OTC | I45: 19.99 | J45: Adobe Creative | Z45: Cash | AB45: Bank
B46: 44113 | C46: 481.28 | D46: UCO | F46: 15 | G46: OAS | O46: =P46/31 -> -3.0822581 | P46: =SUM(C40:C47)-SUM(F40:F47)-SUM(I40:I47)-SUM(L40:L47) -> -95.55 | Q46: =Q36+P48-SUM(L40:L47) -> 509.21 | R46: Balance | U46: =AB46+Z46 -> 533.54 | W46: =U46-U36 -> -96.05 | X46: =W46/31 -> -3.0983871 | Y46: Wallet | Z46: 110 | AA46: Checking | AB46: 423.54
B47: 44127 | C47: 219.46 | D47: UCO | F47: 145 | G47: VW | O47: =P47/31 -> 0 | P47: =SUM(L40:L47) -> 0 | Q47: =Q37+SUM(L44:L47) -> 3360.96 | R47: Savings | U47: =AB47+Z47+Z48 -> 3267.04 | W47: =U47-U37 -> 6.05 | X47: =W47/31 -> 0.19516129 | Y47: Drawer | Z47: 124 | AA47: Savings | AB47: 3002.04
O48: =P48/31 -> -3.0822581 | P48: =SUM(C44:C47)-SUM(F40:F47)-SUM(I40:I47) -> -95.55 | Q48: =Q46+Q47 -> 3870.17 | R48: Total | U48: =U47+U46 -> 3800.58 | W48: =U48-U38 -> -90 | X48: =W48/31 -> -2.9032258 | Y48: Coins | Z48: 141
A49: êêê | B49: November
F50: =9+36.89+7+9+6+10+6+9+9+8+9+7+10+22+6+9+8+11.82+4.33+8.47+6.15+9+8+9+6+36.89 -> 280.55 | G50: Food | I50: =200+160 -> 360 | J50: Green | L50: -400
F51: =24.25+24.22 -> 48.47 | G51: Gas | I51: 9.99 | J51: Spotify
C52: 20 | F52: 20 | G52: Haircut | I52: 0.99 | J52: KRON App | Z52: Cash | AB52: Bank
B53: 44141 | C53: 219.46 | F53: 145 | G53: VW | I53: 6.99 | J53: Disney Plus | O53: =P53/30 -> -1.102 | P53: =SUM(C51:C54)-SUM(F50:F54)-SUM(I50:I54)-SUM(L50:L54) -> -33.06 | Q53: =Q46+P53 -> 476.15 | R53: Balance | U53: =Z53+AB53 -> 500.48 | W53: =U53-U46 -> -33.06 | X53: =W53/30 -> -1.102 | Y53: Wallet | Z53: 234 | AA53: Checking | AB53: 266.48
B54: 44155 | C54: 219.46 | I54: 19.99 | J54: Adobe Creative | O54: =P54/30 -> -13.333333 | P54: =SUM(L50:L54) -> -400 | Q54: =Q47+P54 -> 2960.96 | R54: Savings | U54: =Z55+Z54+AB54 -> 2873.09 | W54: =U54-U47 -> -393.95 | X54: =W54/30 -> -13.131667 | Y54: Drawer | Z54: 124 | AA54: Savings | AB54: 2602.09
O55: =P55/30 -> -14.435333 | P55: =SUM(C51:C54)-SUM(F50:F54)-SUM(I49:I55) -> -433.06 | Q55: =Q53+Q54 -> 3437.11 | R55: Total | U55: =U54+U53 -> 3373.57 | W55: =U55-U48 -> -427.01 | X55: =W55/30 -> -14.233667 | Y55: Coins | Z55: 147
A56: êêê | B56: December
F57: =9+8+9+9+13.65+10+8+9+9+10+22+8+7.59+9+9+10+36.89+22.62+9+8+8.47+9+6+8.78 -> 269 | G57: Food | I57: =160+70+300+100 -> 630 | J57: Green | L57: -920
F58: =24.71+28.03+29.92 -> 82.66 | G58: Gas | I58: 9.99 | J58: Spotify | L58: 100
F59: 99.55 | G59: Heavy Paper | I59: 6.99 | J59: Disney Plus
F60: 48 | G60: Thesis Binding | I60: 19.99 | J60: Adobe Creative
C61: 125 | F61: 124.27 | G61: Kinko's
C62: 40 | F62: =84.44+33 -> 117.44 | G62: Graduation Stuff
C63: 100 | F63: =59.51+21.57+20+38+40+20 -> 199.08 | G63: Christmas | Z63: Cash | AB63: Bank
B64: 44169 | C64: 219.46 | F64: 30 | G64: Haircut | O64: =P64/31 -> -8.3241935 | P64: =SUM(C61:C65)-SUM(F57:F65)-SUM(I57:I65)-SUM(L57:L65) -> -258.05 | Q64: =Q53+P64 -> 218.1 | R64: Balance | U64: =Z64+AB64 -> 244.43 | W64: =U64-U53 -> -256.05 | X64: =W64/31 -> -8.2596774 | Y64: Wallet | Z64: =6 -> 6 | AA64: Checking | AB64: =383.43-145 -> 238.43
B65: 44183 | C65: 219.46 | F65: 145 | G65: VW | O65: =P65/31 -> -26.451613 | P65: =SUM(L57:L65) -> -820 | Q65: =Q54+P65 -> 2140.96 | R65: Savings | U65: =Z66+Z65+AB65 -> 2059.13 | W65: =U65-U54 -> -813.96 | X65: =W65/31 -> -26.256774 | Y65: Drawer | Z65: 224 | AA65: Savings | AB65: 1702.13
A66: 2021 | O66: =P66/31 -> -34.775806 | P66: =SUM(C61:C65)-SUM(F57:F65)-SUM(I56:I66) -> -1078.05 | Q66: =Q64+Q65 -> 2359.06 | R66: Total | U66: =U65+U64 -> 2303.56 | W66: =U66-U55 -> -1070.01 | X66: =W66/31 -> -34.516452 | Y66: Coins | Z66: 133
A67: êêê | B67: 44197
F68: =9.65+8.46+7.47+11.76+6.51+7+9+9+9.65+6.51+8.9+9+9+10+9.33+9+7.04+8.9+16+7+8.9+8.46+8+9.65+8.41+10.19+8.9+7.58 -> 249.27 | G68: Food | I68: =300+180+120+175 -> 775 | J68: Green | L68: -500
F69: 29 | G69: Walmart | I69: 9.99 | J69: Spotify | L69: -100
F70: 70 | G70: UCO | I70: 67.28 | J70: Barnes & Noble
F71: 28.43 | G71: Gas | I71: 0.99 | J71: Blackwake | Z71: Cash | AB71: Bank
C72: 120 | F72: 10 | G72: Haircut | I72: 6.99 | J72: Disney Plus | O72: =P72/31 -> -2.9658065 | P72: =SUM(C70:C73)-SUM(F68:F73)-SUM(I68:I73)-SUM(L68:L73) -> -91.94 | Q72: =Q64+P72 -> 126.16 | R72: Balance | U72: =Z72+AB72 -> 127.49 | W72: =U72-U64 -> -116.94 | X72: =W72/31 -> -3.7722581 | Y72: Wallet | Z72: 44 | AA72: Checking | AB72: 83.49
B73: 44197 | C73: 600 | D73: USA | F73: 145 | G73: VW | I73: 19.99 | J73: Adobe Creative | O73: =P73/31 -> -19.354839 | P73: =SUM(L68:L73) -> -600 | Q73: =Q65+P73 -> 1540.96 | R73: Savings | U73: =Z73+Z74+AB73 -> 1477.16 | W73: =U73-U65 -> -581.97 | X73: =W73/31 -> -18.773226 | Y73: Drawer | Z73: 224 | AA73: Savings | AB73: 1102.16
O74: =P74/31 -> -22.320645 | P74: =SUM(C70:C73)-SUM(F68:F73)-SUM(I67:I74) -> -691.94 | Q74: =Q72+Q73 -> 1667.12 | R74: Total | U74: =U73+U72 -> 1604.65 | W74: =U74-U66 -> -698.91 | X74: =W74/31 -> -22.545484 | Y74: Coins | Z74: 151
A75: êêê | B75: February
F76: =16+27+9+6.75+4+9.65+10+9+11+9.65+9+10+8+21.51+8.08+8+9+8+7.38+9+8 -> 218.02 | G76: Food | I76: =60+120+120+180+120 -> 600 | J76: Green | L76: -500
F77: =30.44+25.54 -> 55.98 | G77: Gas | I77: 9.99 | J77: Fitbod App | L77: -400
F78: 7.95 | G78: Service Fee | I78: 9.99 | J78: Spotify
F79: 10 | G79: Haircut | I79: 6.99 | J79: Disney Plus | Z79: Cash | AB79: Bank
F80: 145 | G80: VW | I80: 5.15 | J80: ProtonMail | O80: =P80/28 -> -2.4664286 | P80: =SUM(C78:C82)-SUM(F76:F81)-SUM(I76:I81)-SUM(L76:L81) -> -69.06 | Q80: =Q72+P80 -> 57.1 | R80: Balance | U80: =Z80+AB80 -> 64.23 | W80: =U80-U72 -> -63.26 | X80: =W80/28 -> -2.2592857 | Y80: Wallet | Z80: 6 | AA80: Checking | AB80: 58.23
C81: 120 | I81: 19.99 | J81: Adobe Creative | O81: =P81/28 -> -32.142857 | P81: =SUM(L76:L81) -> -900 | Q81: =Q73+P81 -> 640.96 | R81: Savings | U81: =Z81+AB81+Z82 -> 585.17 | W81: =U81-U73 -> -891.99 | X81: =W81/28 -> -31.856786 | Y81: Drawer | Z81: 224 | AA81: Savings | AB81: 202.17
O82: =P82/28 -> -34.609286 | P82: =SUM(C78:C81)-SUM(F76:F81)-SUM(I75:I82) -> -969.06 | Q82: =Q80+Q81 -> 698.06 | R82: Total | U82: =U81+U80 -> 649.4 | W82: =U82-U74 -> -955.25 | X82: =W82/28 -> -34.116071 | Y82: Coins | Z82: 159
A83: êêê | B83: March
F84: =15.08+43.41+8.68+9.65+5.96+9+9+8.78+8+7.59+9+9+10+10+7+6+10+9 -> 195.15 | G84: Food | I84: 6.87 | J84: Barnes & Noble | L84: -100
F85: =35.63+17.95 -> 53.58 | G85: Gas | I85: =120+180 -> 300 | J85: Green | L85: -100
F86: 10 | G86: Haircut | I86: 9.99 | J86: Spotify | L86: 50
F87: 145 | G87: VW | I87: 9.99 | J87: Fitbod App | L87: 100
C88: 1400 | D88: USA | I88: 5.15 | J88: ProtonMail | Z88: Cash | AB88: Bank
C89: 7.95 | D89: Refund | I89: 401.77 | J89: Creality E5 Pro | O89: =P89/31 -> 12.918065 | P89: =SUM(C87:C90)-SUM(F84:F90)-SUM(I84:I90)-SUM(L84:L90) -> 400.46 | Q89: =Q80+P89 -> 457.56 | R89: Balance | U89: =Z89+AB89 -> 459.71 | W89: =U89-U80 -> 395.48 | X89: =W89/31 -> 12.757419 | Y89: Wallet | Z89: 256 | AA89: Checking | AB89: 203.71
C90: 100 | D90: Papa | I90: 19.99 | J90: Adobe Creative | O90: =P90/31 -> -1.6129032 | P90: =SUM(L84:L90) -> -50 | Q90: =Q81+P90 -> 590.96 | R90: Savings | U90: =Z91+Z90+AB90 -> 539.17 | W90: =U90-U81 -> -46 | X90: =W90/31 -> -1.483871 | Y90: Drawer | Z90: 174 | AA90: Savings | AB90: 202.17
O91: =P91/31 -> 11.305161 | P91: =SUM(C87:C90)-SUM(F84:F90)-SUM(I83:I91) -> 350.46 | Q91: =Q89+Q90 -> 1048.52 | R91: Total | U91: =U90+U89 -> 998.88 | W91: =U91-U82 -> 349.48 | X91: =W91/31 -> 11.273548 | Y91: Coins | Z91: 163
A92: êêê | B92: April
F93: =8+8.78+32.55+9+9+8.32+10+9+10+8.41+10+10+8.68+10+9.82+8.68+9+9+7.89+8.9+9.65+9+8.68+8.28+9.65 -> 250.29 | G93: Food | I93: 305 | J93: Green | L93: -50
F94: =34.78+36.15 -> 70.93 | G94: Gas | I94: 9.99 | J94: Fitbod App | L94: -100
F95: 42 | G95: Mom's Birthday | I95: 9.99 | J95: Spotify | L95: -171
C96: 20 | D96: Dad | F96: 6 | G96: Dad's Birthday | I96: 39.98 | J96: Cancelled Adobe
C97: 20 | D97: Andrew | F97: 10 | G97: Haircut | I97: 6 | J97: UCO Outtakes | Z97: Cash | AB97: Bank | AD97: Crypto
C98: 70 | D98: Papa | F98: 145 | G98: VW | I98: =19.12+0.5+2 -> 21.62 | J98: BitCoin | O98: =P98/30 -> -10.031667 | P98: =SUM(C96:C99)-SUM(F93:F99)-SUM(I93:I99)-SUM(L93:L99) -> -300.95 | Q98: =Q89+P100-SUM(L93:L99) -> 156.61 | R98: Balance | U98: =Z98+AB98+AD98+AD99 -> 174.23 | W98: =U98-U89 -> -285.48 | X98: =W98/30 -> -9.516 | Y98: Wallet | Z98: 101 | AA98: Checking | AB98: 41.88 | AC98: Wallet | AD98: 13.35
C99: 190 | D99: UCO Refund | I99: 5.15 | J99: ProtonMail | O99: =P99/30 -> -10.7 | P99: =SUM(L93:L99) -> -321 | Q99: =Q90+SUM(L93:L99) -> 269.96 | R99: Savings | U99: =Z99+Z100+AB99 -> 226.17 | W99: =U99-U90 -> -313 | X99: =W99/30 -> -10.433333 | Y99: Drawer | Z99: 124 | AA99: Savings | AB99: 102.17 | AC99: BitCoin | AD99: 18
O100: =P100/30 -> -20.731667 | P100: =SUM(C96:C99)-SUM(F93:F99)-SUM(I92:I100) -> -621.95 | Q100: =Q98+Q99 -> 426.57 | R100: Total | U100: =U99+U98 -> 400.4 | W100: =U100-U91 -> -598.48 | X100: =W100/30 -> -19.949333 | Y100: Coins | Z100: 0
A101: êêê | B101: May
B102: 44319 | C102: 70 | D102: Papa | F102: =9.65+21.7+10+9+9.65+9+9+9+10+8.9+9+33+8.71+8.9+9+15.78+9+10+9+9+9+9+9+9 -> 263.29 | G102: Food | I102: =70+40+160+50 -> 320 | J102: Green | L102: -50
...

Sheet Data Analysis
D2: Economy | S2: Parameters | AG2: Signal Dynamics | AR2: Accuracy, Precision, Errors, and Differences | AZ2: Exercise Days per Month
D3: Model | K3: Actual | S3: Predictive | Z3: Model | AG3: Velocity (Δ$/Mo) | AM3: Acceleration (ΔVelocity/Mo) | AR3: Model Deviation from Actual | AU3: Percent Error (Accuracy) | AW3: Percent Diff (Precision) | BP3: Meaningless signal?
B4: Month | C4: Income | D4: Total | E4: Balance | F4: Savings | G4: Savings 2 | H4: Market | I4: Bitcoin | J4: Stocks | K4: Total | L4: Balance | M4: Savings A | N4: Savings B | O4: Bitcoin | P4: Stocks | Q4: Market | R4: Spending | S4: Gas | T4: Grub | U4: Green | V4: Other | W4: Necessary | X4: Unnecessary | Y4: Total | Z4: Gas | AA4: Grub | AB4: Green | AC4: Other | AD4: Necessary | AE4: Unnecessary | AF4: Spending | AG4: Model 1 | AH4: Model 2 | AI4: Actual 1 | AJ4: Actual 2 | AK4: Model Dev | AL4: Actual Dev | AM4: Model 1 | AN4: Model 2 | AO4: Actual | AP4: Model Dev | AQ4: Net Dev | AR4: of $ | AS4: of Δ$1 | AT4: of Δ$2 | AU4: % Error of $ | AV4: % Error of Δ$ | AW4: % Diff of $ | AX4: % Diff of Δ$
B5: 43952 | C5: =SUM(Data!C4:C7) -> 814.17 | D5: =Data!Q8 -> 750.6 | E5: =Data!Q6 -> 104.64 | F5: =Data!Q7 -> 645.96 | K5: =Data!U8 -> 750.6 | L5: =Data!U6 -> 104.64 | N5: =Data!U7 -> 645.96 | S5: 50 | T5: 250 | U5: 240 | V5: 50 | Z5: =Data!F6 -> 120 | AA5: =Data!F5 -> 240 | AB5: =Data!I5 -> 205 | AC5: =SUM(Data!I6:I7) -> 16.98 | AD5: =SUM(Data!F5:F7) -> 1072.86 | AE5: =SUM(Data!I5:I7) -> 221.98 | AF5: =SUM(AD5:AE5) -> 1294.84 | AG5: =C5-AF5 -> -480.67 | AR5: =K5-D5 -> 0 | AU5: =ABS(AR5/K5) -> 0 | AW5: =ABS(AR5/AVERAGE(K5,D5)) -> 0 | BP5: =ABS((AR6-AS6)/((ABS(AR6)+ABS(AS6))/2))/10 -> 1.6073355e-16
B6: 43983 | C6: =SUM(Data!C10:C13) -> 1325.2 | D6: =Data!Q14 -> 654.61 | E6: =Data!Q12 -> 8.65 | F6: =Data!Q13 -> 645.96 | K6: =Data!U14 -> 583.88 | L6: =Data!U12 -> 85.92 | N6: =Data!U13 -> 497.96 | R6: =K5-K6+C6 -> 1491.92 | S6: 50 | T6: 250 | U6: 240 | V6: 50 | Z6: =Data!F11 -> 43.19 | AA6: =Data!F10 -> 247.76 | AB6: =Data!I10-Data!C11 -> 195 | AC6: =SUM(Data!I11:I13) -> 32.38 | AD6: =SUM(Data!F10:F13) -> 1013.81 | AE6: =SUM(Data!I10:I13) -> 407.38 | AF6: =SUM(AD6:AE6) -> 1421.19 | AG6: =C6-AF6 -> -95.99 | AH6: =D6-D5 -> -95.99 | AI6: =C6-R6 -> -166.72 | AJ6: =K6-K5 -> -166.72 | AK6: =AG6-AH6 -> -2.2737368e-13 | AL6: =AI6-AJ6 -> 0 | AR6: =K6-D6 -> -70.73 | AS6: =AI6-AG6 -> -70.73 | AT6: =AJ6-AH6 -> -70.73 | AU6: =ABS(AR6/K6) -> 0.12113791 | AV6: =ABS(AS6/AI6) -> 0.42424424 | AW6: =ABS(AR6/AVERAGE(K6,D6)) -> 0.11421974 | AX6: =ABS((AG6-AH6)/AVERAGE(AG6,AH6)) -> 2.3687225e-15 | BP6: =ABS((AR7-AS7)/((ABS(AR7)+ABS(AS7))/2))/10 -> 0.16738847
B7: 44013 | C7: =SUM(Data!C16:C19) -> 1609.21 | D7: =Data!Q20 -> 1008.53 | E7: =Data!Q18 -> 332.57 | F7: =Data!Q19 -> 675.96 | K7: =Data!U20 -> 930.91 | L7: =Data!U18 -> 367.95 | N7: =Data!U19 -> 562.96 | R7: =K6-K7+C7 -> 1262.18 | S7: 50 | T7: 250 | U7: 250 | V7: 50 | Z7: =Data!F17 -> 52.16 | AA7: =Data!F16 -> 280.15 | AB7: =Data!I16-Data!C16 -> 470 | AC7: =SUM(Data!I17:I19) -> 17.98 | AD7: =SUM(Data!F16:F18) -> 632.31 | AE7: =SUM(Data!I16:I19) -> 622.98 | AF7: =SUM(AD7:AE7) -> 1255.29 | AG7: =C7-AF7 -> 353.92 | AH7: =D7-D6 -> 353.92 | AI7: =C7-R7 -> 347.03 | AJ7: =K7-K6 -> 347.03 | AK7: =AG7-AH7 -> 0 | AL7: =AI7-AJ7 -> 0 | AM7: =AG7-AG6 -> 449.91 | AN7: =AH7-AH6 -> 449.91 | AO7: =AJ7-AJ6 -> 513.75 | AP7: =AN7-AM7 -> 0 | AQ7: =AO7-AN7 -> 63.84 | AR7: =K7-D7 -> -77.62 | AS7: =AI7-AG7 -> -6.89 | AT7: =AJ7-AH7 -> -6.89 | AU7: =ABS(AR7/K7) -> 0.083380778 | AV7: =ABS(AS7/AI7) -> 0.019854191 | AW7: =ABS(AR7/AVERAGE(K7,D7)) -> 0.080043724 | AX7: =ABS((AG7-AH7)/AVERAGE(AG7,AH7)) -> 3.2122185e-16 | BP7: =ABS((AR8-AS8)/((ABS(AR8)+ABS(AS8))/2))/10 -> 0.2
B8: 44044 | C8: =SUM(Data!C22:C27) -> 524.9 | D8: =Data!Q28 -> 491.66 | E8: =Data!Q26 -> 15.7 | F8: =Data!Q27 -> 475.96 | K8: =Data!U28 -> 422.04 | L8: =Data!U26 -> 51.08 | N8: =Data!U27 -> 370.96 | R8: =K7-K8+C8 -> 1033.77 | S8: 60 | T8: 300 | U8: 300 | V8: 50 | Z8: =Data!F23 -> 59.81 | AA8: =Data!F22 -> 335.02 | AB8: =Data!I22-Data!C26 -> 375 | AC8: =SUM(Data!I23:I27) -> 71.95 | AD8: =SUM(Data!F22:F26) -> 474.82 | AE8: =SUM(Data!I22:I27) -> 566.95 | AF8: =SUM(AD8:AE8) -> 1041.77 | AG8: =C8-AF8 -> -516.87 | AH8: =D8-D7 -> -516.87 | AI8: =C8-R8 -> -508.87 | AJ8: =K8-K7 -> -508.87 | AK8: =AG8-AH8 -> 0 | AL8: =AI8-AJ8 -> 0 | AM8: =AG8-AG7 -> -870.79 | AN8: =AH8-AH7 -> -870.79 | AO8: =AJ8-AJ7 -> -855.9 | AP8: =AN8-AM8 -> 0 | AQ8: =AO8-AN8 -> 14.89 | AR8: =K8-D8 -> -69.62 | AS8: =AI8-AG8 -> 8 | AT8: =AJ8-AH8 -> 8 | AU8: =ABS(AR8/K8) -> 0.16496067 | AV8: =ABS(AS8/AI8) -> 0.015721108 | AW8: =ABS(AR8/AVERAGE(K8,D8)) -> 0.15239138 | AX8: =ABS((AG8-AH8)/AVERAGE(AG8,AH8)) -> 2.1995248e-16 | BP8: =ABS((AR9-AS9)/((ABS(AR9)+ABS(AS9))/2))/10 -> 0.17262584
B9: 44075 | C9: =SUM(Data!C32:C37) -> 9067.6 | D9: =Data!Q38 -> 3965.72 | E9: =Data!Q36 -> 604.76 | F9: =Data!Q37 -> 3360.96 | K9: =Data!U38 -> 3890.58 | L9: =Data!U36 -> 629.59 | N9: =Data!U37 -> 3260.99 | R9: =K8-K9+C9 -> 5599.06 | S9: 60 | T9: 300 | U9: 300 | V9: 50 | Z9: =Data!F31 -> 88.49 | AA9: =Data!F30 -> 350.77 | AB9: =Data!I30-Data!C32 -> 385 | AC9: =SUM(Data!I31:I36) -> 151.77 | AD9: =SUM(Data!F30:F37) -> 4906.77 | AE9: =SUM(Data!I30:I36) -> 686.77 | AF9: =SUM(AD9:AE9) -> 5593.54 | AG9: =C9-AF9 -> 3474.06 | AH9: =D9-D8 -> 3474.06 | AI9: =C9-R9 -> 3468.54 | AJ9: =K9-K8 -> 3468.54 | AK9: =AG9-AH9 -> 0 | AL9: =AI9-AJ9 -> 0 | AM9: =AG9-AG8 -> 3990.93 | AN9: =AH9-AH8 -> 3990.93 | AO9: =AJ9-AJ8 -> 3977.41 | AP9: =AN9-AM9 -> 0 | AQ9: =AO9-AN9 -> -13.52 | AR9: =K9-D9 -> -75.14 | AS9: =AI9-AG9 -> -5.52 | AT9: =AJ9-AH9 -> -5.52 | AU9: =ABS(AR9/K9) -> 0.019313316 | AV9: =ABS(AS9/AI9) -> 0.0015914477 | AW9: =ABS(AR9/AVERAGE(K9,D9)) -> 0.019128597 | AX9: =ABS((AG9-AH9)/AVERAGE(AG9,AH9)) -> 1.3089796e-16 | BP9: =ABS((AR10-AS10)/((ABS(AR10)+ABS(AS10))/2))/10 -> 0.2
B10: 44105 | C10: =SUM(Data!C40:C47) -> 995.74 | D10: =Data!Q48 -> 3870.17 | E10: =Data!Q46 -> 509.21 | F10: =Data!Q47 -> 3360.96 | K10: =Data!U48 -> 3800.58 | L10: =Data!U46 -> 533.54 | N10: =Data!U47 -> 3267.04 | R10: =K9-K10+C10 -> 1085.74 | S10: 60 | T10: 350 | U10: 300 | V10: 50 | Z10: =Data!F41 -> 45.56 | AA10: =Data!F40 -> 289.28 | AB10: =Data!I40-Data!C44 -> 235 | AC10: =SUM(Data!I41:I45) -> 77.95 | AD10: =SUM(Data!F40:F47) -> 648.34 | AE10: =SUM(Data!I40:I45) -> 442.95 | AF10: =SUM(AD10:AE10) -> 1091.29 | AG10: =C10-AF10 -> -95.55 | AH10: =D10-D9 -> -95.55 | AI10: =C10-R10 -> -90 | AJ10: =K10-K9 -> -90 | AK10: =AG10-AH10 -> -2.2737368e-13 | AL10: =AI10-AJ10 -> 0 | AM10: =AG10-AG9 -> -3569.61 | AN10: =AH10-AH9 -> -3569.61 | AO10: =AJ10-AJ9 -> -3558.54 | AP10: =AN10-AM10 -> 0 | AQ10: =AO10-AN10 -> 11.07 | AR10: =K10-D10 -> -69.59 | AS10: =AI10-AG10 -> 5.55 | AT10: =AJ10-AH10 -> 5.55 | AU10: =ABS(AR10/K10) -> 0.018310363 | AV10: =ABS(AS10/AI10) -> 0.061666667 | AW10: =ABS(AR10/AVERAGE(K10,D10)) -> 0.018144249 | AX10: =ABS((AG10-AH10)/AVERAGE(AG10,AH10)) -> 2.3796303e-15 | BP10: =ABS((AR11-AS11)/((ABS(AR11)+ABS(AS11))/2))/10 -> 0.2
B11: 44136 | C11: =SUM(Data!C50:C54) -> 458.92 | D11: =Data!Q55 -> 3437.11 | E11: =Data!Q53 -> 476.15 | F11: =Data!Q54 -> 2960.96 | K11: =Data!U55 -> 3373.57 | L11: =Data!U53 -> 500.48 | N11: =Data!U54 -> 2873.09 | R11: =K10-K11+C11 -> 885.93 | S11: 60 | T11: 350 | U11: 300 | V11: 50 | Z11: =Data!F51 -> 48.47 | AA11: =Data!F50 -> 280.55 | AB11: =Data!I50-Data!C52 -> 340 | AC11: =SUM(Data!I51:I54) -> 37.96 | AD11: =SUM(Data!F50:F53) -> 494.02 | AE11: =SUM(Data!I50:I54) -> 397.96 | AF11: =SUM(AD11:AE11) -> 891.98 | AG11: =C11-AF11 -> -433.06 | AH11: =D11-D10 -> -433.06 | AI11: =C11-R11 -> -427.01 | AJ11: =K11-K10 -> -427.01 | AK11: =AG11-AH11 -> 0 | AL11: =AI11-AJ11 -> 0 | AM11: =AG11-AG10 -> -337.51 | AN11: =AH11-AH10 -> -337.51 | AO11: =AJ11-AJ10 -> -337.01 | AP11: =AN11-AM11 -> -6.2527761e-13 | AQ11: =AO11-AN11 -> 0.5 | AR11: =K11-D11 -> -63.54 | AS11: =AI11-AG11 -> 6.05 | AT11: =AJ11-AH11 -> 6.05 | AU11: =ABS(AR11/K11) -> 0.018834647 | AV11: =ABS(AS11/AI11) -> 0.014168286 | AW11: =ABS(AR11/AVERAGE(K11,D11)) -> 0.01865893 | AX11: =ABS((AG11-AH11)/AVERAGE(AG11,AH11)) -> 9.1881941e-16 | BP11: =ABS((AR12-AS12)/((ABS(AR12)+ABS(AS12))/2))/10 -> 0.2
B12: 44166 | C12: =SUM(Data!C57:C65) -> 703.92 | D12: =Data!Q66 -> 2359.06 | E12: =Data!Q64 -> 218.1 | F12: =Data!Q65 -> 2140.96 | K12: =Data!U66 -> 2303.56 | L12: =Data!U64 -> 244.43 | N12: =Data!U65 -> 2059.13 | R12: =K11-K12+C12 -> 1773.93 | S12: 60 | T12: 350 | U12: 300 | V12: 100 | Z12: =Data!F58 -> 82.66 | AA12: =Data!F57 -> 269 | AB12: =Data!I57-Data!C62 -> 590 | AC12: =SUM(Data!I58:I60) -> 36.97 | AD12: =SUM(Data!F57:F65) -> 1115 | AE12: =SUM(Data!I57:I60) -> 666.97 | AF12: =SUM(AD12:AE12) -> 1781.97 | AG12: =C12-AF12 -> -1078.05 | AH12: =D12-D11 -> -1078.05 | AI12: =C12-R12 -> -1070.01 | AJ12: =K12-K11 -> -1070.01 | AK12: =AG12-AH12 -> 0 | AL12: =AI12-AJ12 -> 0 | AM12: =AG12-AG11 -> -644.99 | AN12: =AH12-AH11 -> -644.99 | AO12: =AJ12-AJ11 -> -643 | AP12: =AN12-AM12 -> 0 | AQ12: =AO12-AN12 -> 1.99 | AR12: =K12-D12 -> -55.5 | AS12: =AI12-AG12 -> 8.04 | AT12: =AJ12-AH12 -> 8.04 | AU12: =ABS(AR12/K12) -> 0.024093143 | AV12: =ABS(AS12/AI12) -> 0.0075139485 | AW12: =ABS(AR12/AVERAGE(K12,D12)) -> 0.023806358 | AX12: =ABS((AG12-AH12)/AVERAGE(AG12,AH12)) -> 2.1091199e-16 | BP12: =ABS((AR13-AS13)/((ABS(AR13)+ABS(AS13))/2))/10 -> 0.15985023
B13: 44197 | C13: =SUM(Data!C68:C73) -> 720 | D13: =Data!Q74 -> 1667.12 | E13: =Data!Q72 -> 126.16 | F13: =Data!Q73 -> 1540.96 | K13: =Data!U74 -> 1604.65 | L13: =Data!U72 -> 127.49 | N13: =Data!U73 -> 1477.16 | R13: =K12-K13+C13 -> 1418.91 | S13: 60 | T13: 350 | U13: 250 | V13: 50 | Z13: =Data!F71 -> 28.43 | AA13: =Data!F68 -> 249.27 | AB13: =Data!I68-Data!C72 -> 655 | AC13: =SUM(Data!I69:I73) -> 105.24 | AD13: =SUM(Data!F68:F73) -> 531.7 | AE13: =SUM(Data!I68:I73) -> 880.24 | AF13: =SUM(AD13:AE13) -> 1411.94 | AG13: =C13-AF13 -> -691.94 | AH13: =D13-D12 -> -691.94 | AI13: =C13-R13 -> -698.91 | AJ13: =K13-K12 -> -698.91 | AK13: =AG13-AH13 -> 0 | AL13: =AI13-AJ13 -> 0 | AM13: =AG13-AG12 -> 386.11 | AN13: =AH13-AH12 -> 386.11 | AO13: =AJ13-AJ12 -> 371.1 | AP13: =AN13-AM13 -> 0 | AQ13: =AO13-AN13 -> -15.01 | AR13: =K13-D13 -> -62.47 | AS13: =AI13-AG13 -> -6.97 | AT13: =AJ13-AH13 -> -6.97 | AU13: =ABS(AR13/K13) -> 0.038930608 | AV13: =ABS(AS13/AI13) -> 0.0099726717 | AW13: =ABS(AR13/AVERAGE(K13,D13)) -> 0.038187281 | AX13: =ABS((AG13-AH13)/AVERAGE(AG13,AH13)) -> 0 | BP13: =ABS((AR14-AS14)/((ABS(AR14)+ABS(AS14))/2))/10 -> 0.2
B14: 44228 | C14: =SUM(Data!C76:C81) -> 120 | D14: =Data!Q82 -> 698.06 | E14: =Data!Q80 -> 57.1 | F14: =Data!Q81 -> 640.96 | K14: =Data!U82 -> 649.4 | L14: =Data!U80 -> 64.23 | N14: =Data!U81 -> 585.17 | R14: =K13-K14+C14 -> 1075.25 | S14: 60 | T14: 250 | U14: 300 | V14: 60 | Z14: =Data!F77 -> 55.98 | AA14: =Data!F76 -> 218.02 | AB14: =Data!I76-Data!C81 -> 480 | AC14: =SUM(Data!I77:I81) -> 52.11 | AD14: =SUM(Data!F76:F80) -> 436.95 | AE14: =SUM(Data!I76:I81) -> 652.11 | AF14: =SUM(AD14:AE14) -> 1089.06 | AG14: =C14-AF14 -> -969.06 | AH14: =D14-D13 -> -969.06 | AI14: =C14-R14 -> -955.25 | AJ14: =K14-K13 -> -955.25 | AK14: =AG14-AH14 -> 0 | AL14: =AI14-AJ14 -> 0 | AM14: =AG14-AG13 -> -277.12 | AN14: =AH14-AH13 -> -277.12 | AO14: =AJ14-AJ13 -> -256.34 | AP14: =AN14-AM14 -> 0 | AQ14: =AO14-AN14 -> 20.78 | AR14: =K14-D14 -> -48.66 | AS14: =AI14-AG14 -> 13.81 | AT14: =AJ14-AH14 -> 13.81 | AU14: =ABS(AR14/K14) -> 0.074930705 | AV14: =ABS(AS14/AI14) -> 0.014456948 | AW14: =ABS(AR14/AVERAGE(K14,D14)) -> 0.072224778 | AX14: =ABS((AG14-AH14)/AVERAGE(AG14,AH14)) -> 0 | BP14: =ABS((AR15-AS15)/((ABS(AR15)+ABS(AS15))/2))/10 -> 0.19225603
B15: 44256 | C15: =SUM(Data!C84:C90) -> 1507.95 | D15: =Data!Q91 -> 1048.52 | E15: =Data!Q89 -> 457.56 | F15: =Data!Q90 -> 590.96 | K15: =Data!U91 -> 998.88 | L15: =Data!U89 -> 459.71 | N15: =Data!U90 -> 539.17 | R15: =K14-K15+C15 -> 1158.47 | S15: 60 | T15: 300 | U15: 150 | V15: 60 | Z15: =Data!F85 -> 53.58 | AA15: =Data!F84 -> 195.15 | AB15: =Data!I85 -> 300 | AC15: =Data!I84+SUM(Data!I86:I90) -> 453.76 | AD15: =SUM(Data!F84:F87) -> 403.73 | AE15: =SUM(Data!I84:I90) -> 753.76 | AF15: =SUM(AD15:AE15) -> 1157.49 | AG15: =C15-AF15 -> 350.46 | AH15: =D15-D14 -> 350.46 | AI15: =C15-R15 -> 349.48 | AJ15: =K15-K14 -> 349.48 | AK15: =AG15-AH15 -> 0 | AL15: =AI15-AJ15 -> 0 | AM15: =AG15-AG14 -> 1319.52 | AN15: =AH15-AH14 -> 1319.52 | AO15: =AJ15-AJ14 -> 1304.73 | AP15: =AN15-AM15 -> 0 | AQ15: =AO15-AN15 -> -14.79 | AR15: =K15-D15 -> -49.64 | AS15: =AI15-AG15 -> -0.98 | AT15: =AJ15-AH15 -> -0.98 | AU15: =ABS(AR15/K15) -> 0.049695659 | AV15: =ABS(AS15/AI15) -> 0.0028041662 | AW15: =ABS(AR15/AVERAGE(K15,D15)) -> 0.048490769 | AX15: =ABS((AG15-AH15)/AVERAGE(AG15,AH15)) -> 0 | BP15: =ABS((AR16-AS16)/((ABS(AR16)+ABS(AS16))/2))/10 -> 0.2
B16: 44287 | C16: =SUM(Data!C93:C99) -> 300 | D16: =Data!Q100 -> 426.57 | E16: =Data!Q98 -> 156.61 | F16: =Data!Q99 -> 269.96 | K16: =Data!U100 -> 400.4 | L16: =Data!U98 -> 174.23 | N16: =Data!U99 -> 226.17 | O16: =Data!AD99 -> 18 | R16: =K15-K16+C16 -> 898.48 | S16: 60 | T16: 250 | U16: 200 | V16: 60 | Z16: =Data!F94 -> 70.93 | AA16: =Data!F93 -> 250.29 | AB16: =Data!I93 -> 305 | AC16: =SUM(Data!I94:I99) -> 92.73 | AD16: =SUM(Data!F93:F98) -> 524.22 | AE16: =SUM(Data!I93:I99) -> 397.73 | AF16: =SUM(AD16:AE16) -> 921.95 | AG16: =C16-AF16 -> -621.95 | AH16: =D16-D15 -> -621.95 | AI16: =C16-R16 -> -598.48 | AJ16: =K16-K15 -> -598.48 | AK16: =AG16-AH16 -> 0 | AL16: =AI16-AJ16 -> 0 | AM16: =AG16-AG15 -> -972.41 | AN16: =AH16-AH15 -> -972.41 | AO16: =AJ16-AJ15 -> -947.96 | AP16: =AN16-AM16 -> 0 | AQ16: =AO16-AN16 -> 24.45 | AR16: =K16-D16 -> -26.17 | AS16: =AI16-AG16 -> 23.47 | AT16: =AJ16-AH16 -> 23.47 | AU16: =ABS(AR16/K16) -> 0.06535964 | AV16: =ABS(AS16/AI16) -> 0.039216014 | AW16: =ABS(AR16/AVERAGE(K16,D16)) -> 0.063291292 | AX16: =ABS((AG16-AH16)/AVERAGE(AG16,AH16)) -> 0 | BP16: =ABS((AR17-AS17)/((ABS(AR17)+ABS(AS17))/2))/10 -> 0.2
B17: 44317 | C17: =SUM(Data!C102:C109) -> 3513.28 | D17: =Data!Q110 -> 2958.95 | E17: =Data!Q108 -> 868.99 | F17: =Data!Q109 -> 2089.96 | K17: =Data!U110 -> 2941.73 | L17: =Data!U108 -> 889.55 | N17: =Data!U109 -> 2052.18 | O17: =Data!AD109 -> 36.69 | R17: =K16-K17+C17 -> 971.95 | S17: 100 | T17: 250 | U17: 200 | V17: 60 | Z17: =Data!F103 -> 145.55 | AA17: =Data!F102 -> 263.29 | AB17: =Data!I102 -> 320 | AC17: =SUM(Data!I103:I108) -> 87.06 | AD17: =SUM(Data!F102:F107) -> 573.84 | AE17: =SUM(Data!I102:I108) -> 407.06 | AF17: =SUM(AD17:AE17) -> 980.9 | AG17: =C17-AF17 -> 2532.38 | AH17: =D17-D16 -> 2532.38 | AI17: =C17-R17 -> 2541.33 | AJ17: =K17-K16 -> 2541.33 | AK17: =AG17-AH17 -> 0 | AL17: =AI17-AJ17 -> 0 | AM17: =AG17-AG16 -> 3154.33 | AN17: =AH17-AH16 -> 3154.33 | AO17: =AJ17-AJ16 -> 3139.81 | AP17: =AN17-AM17 -> 0 | AQ17: =AO17-AN17 -> -14.52 | AR17: =K17-D17 -> -17.22 | AS17: =AI17-AG17 -> 8.95 | AT17: =AJ17-AH17 -> 8.95 | AU17: =ABS(AR17/K17) -> 0.0058536983 | AV17: =ABS(AS17/AI17) -> 0.003521778 | AW17: =ABS(AR17/AVERAGE(K17,D17)) -> 0.0058366154 | AX17: =ABS((AG17-AH17)/AVERAGE(AG17,AH17)) -> 0 | BP17: =ABS((AR18-AS18)/((ABS(AR18)+ABS(AS18))/2))/10 -> 0.13920776
B18: 44348 | C18: =SUM(Data!C112:C118) -> 2925 | D18: =Data!Q119 -> 3999.29 | E18: =Data!Q117 -> 1089.33 | F18: =Data!Q118 -> 2909.96 | K18: =Data!U119 -> 3978.31 | L18: =Data!U117 -> 1100.09 | N18: =Data!U118 -> 2878.22 | O18: =Data!AD118 -> 46.39 | R18: =K17-K18+C18 -> 1888.42 | S18: 160 | T18: 300 | U18: 400 | V18: 80 | Z18: =Data!F113 -> 160.44 | AA18: =Data!F112 -> 307.92 | AB18: =Data!I112 -> 510 | AC18: =SUM(Data!I113:I118) -> 195.07 | AD18: =SUM(Data!F112:F117) -> 1179.59 | AE18: =SUM(Data!I112:I118) -> 705.07 | AF18: =SUM(AD18:AE18) -> 1884.66 | AG18: =C18-AF18 -> 1040.34 | AH18: =D18-D17 -> 1040.34 | AI18: =C18-R18 -> 1036.58 | AJ18: =K18-K17 -> 1036.58 | AK18: =AG18-AH18 -> 0 | AL18: =AI18-AJ18 -> 0 | AM18: =AG18-AG17 -> -1492.04 | AN18: =AH18-AH17 -> -1492.04 | AO18: =AJ18-AJ17 -> -1504.75 | AP18: =AN18-AM18 -> 0 | AQ18: =AO18-AN18 -> -12.71 | AR18: =K18-D18 -> -20.98 | AS18: =AI18-AG18 -> -3.76 | AT18: =AJ18-AH18 -> -3.76 | AU18: =ABS(AR18/K18) -> 0.0052735961 | AV18: =ABS(AS18/AI18) -> 0.0036273129 | AW18: =ABS(AR18/AVERAGE(K18,D18)) -> 0.0052597272 | AX18: =ABS((AG18-AH18)/AVERAGE(AG18,AH18)) -> 2.1855708e-16 | BP18: =ABS((AR19-AS19)/((ABS(AR19)+ABS(AS19))/2))/10 -> 0.19372114
B19: 44378 | C19: =SUM(Data!C121:C125) -> 3965 | D19: =Data!Q126 -> 6005.93 | E19: =Data!Q123 -> 1095.97 | F19: =Data!Q124 -> 3809.96 | G19: =Data!Q125 -> 1100 | K19: =Data!U126 -> 5984.61 | L19: =Data!U123 -> 1102.34 | M19: =Data!U125 -> 1100 | N19: =Data!U124 -> 3782.27 | O19: =Data!AD124 -> 59.24 | R19: =K18-K19+C19 -> 1958.7 | S19: 160 | T19: 300 | U19: 350 | V19: 80 | Z19: =Data!F122 -> 147.3 | AA19: =Data!F121 -> 290.85 | AB19: =Data!I121 -> 450 | AC19: =SUM(Data!I122:I125) -> 205.21 | AD19: =SUM(Data!F121:F125) -> 1303.15 | AE19: =SUM(Data!I121:I125) -> 655.21 | AF19: =SUM(AD19:AE19) -> 1958.36 | AG19: =C19-AF19 -> 2006.64 | AH19: =D19-D18 -> 2006.64 | AI19: =C19-R19 -> 2006.3 | AJ19: =K19-K18 -> 2006.3 | AK19: =AG19-AH19 -> 0 | AL19: =AI19-AJ19 -> 0 | AM19: =AG19-AG18 -> 966.3 | AN19: =AH19-AH18 -> 966.3 | AO19: =AJ19-AJ18 -> 969.72 | AP19: =AN19-AM19 -> 0 | AQ19: =AO19-AN19 -> 3.42 | AR19: =K19-D19 -> -21.32 | AS19: =AI19-AG19 -> -0.34 | AT19: =AJ19-AH19 -> -0.34 | AU19: =ABS(AR19/K19) -> 0.0035624711 | AV19: =ABS(AS19/AI19) -> 0.00016946618 | AW19: =ABS(AR19/AVERAGE(K19,D19)) -> 0.0035561368 | AX19: =ABS((AG19-AH19)/AVERAGE(AG19,AH19)) -> 2.2662129e-16 | BP19: =ABS((AR20-AS20)/((ABS(AR20)+ABS(AS20))/2))/10 -> 0.026294821
B20: 44409 | C20: =SUM(Data!C129:C134) -> 3065 | D20: =Data!Q135 -> 6793.16 | E20: =Data!Q132 -> 563.2 | F20: =Data!Q133 -> 4229.96 | G20: =Data!Q134 -> 2000 | K20: =Data!U135 -> 6797.52 | L20: =Data!U132 -> 587.19 | M20: =Data!U134 -> 2000 | N20: =Data!U133 -> 4210.33 | O20: =Data!AD133 -> 67.73 | R20: =K19-K20+C20 -> 2252.09 | S20: 160 | T20: 300 | U20: 300 | V20: 120 | Z20: =Data!F129 -> 188.84 | AA20: =Data!F128 -> 305.31 | AB20: =Data!I128 -> 390 | AC20: =SUM(Data!I129:I134) -> 280.21 | AD20: =SUM(Data!F128:F133) -> 1587.56 | AE20: =SUM(Data!I128:I134) -> 670.21 | AF20: =SUM(AD20:AE20) -> 2257.77 | AG20: =C20-AF20 -> 807.23 | AH20: =D20-D19 -> 787.23 | AI20: =C20-R20 -> 812.91 | AJ20: =K20-K19 -> 812.91 | AK20: =AG20-AH20 -> 20 | AL20: =AI20-AJ20 -> 0 | AM20: =AG20-AG19 -> -1199.41 | AN20: =AH20-AH19 -> -1219.41 | AO20: =AJ20-AJ19 -> -1193.39 | AP20: =AN20-AM20 -> -20 | AQ20: =AO20-AN20 -> 26.02 | AR20: =K20-D20 -> 4.36 | AS20: =AI20-AG20 -> 5.68 | AT20: =AJ20-AH20 -> 25.68 | AU20: =ABS(AR20/K20) -> 0.0006414104 | AV20: =ABS(AS20/AI20) -> 0.0069872434 | AW20: =ABS(AR20/AVERAGE(K20,D20)) -> 0.00064161617 | AX20: =ABS((AG20-AH20)/AVERAGE(AG20,AH20)) -> 0.025086863 | BP20: =ABS((AR21-AS21)/((ABS(AR21)+ABS(AS21))/2))/10 -> 0.052466907
B21: 44440 | C21: =SUM(Data!C137:C141) -> 3000 | D21: =Data!Q142 -> 7868.26 | E21: =Data!Q139 -> 638.3 | F21: =Data!Q140 -> 4729.96 | G21: =Data!Q141 -> 2500 | K21: =Data!U142 -> 7862.13 | L21: =Data!U139 -> 643.74 | M21: =Data!U141 -> 2500 | N21: =Data!U140 -> 4718.39 | O21: =Data!AD140 -> 102.59 | R21: =K20-K21+C21 -> 1935.39 | S21: 160 | T21: 300 | U21: 300 | V21: 120 | Z21: =Data!F138 -> 155.61 | AA21: =Data!F137 -> 396.16 | AB21: =Data!I137 -> 338 | AC21: =SUM(Data!I138:I141) -> 30.13 | AD21: =SUM(Data!F137:F141) -> 1556.77 | AE21: =SUM(Data!I137:I141) -> 368.13 | AF21: =SUM(AD21:AE21) -> 1924.9 | AG21: =C21-AF21 -> 1075.1 | AH21: =D21-D20 -> 1075.1 | AI21: =C21-R21 -> 1064.61 | AJ21: =K21-K20 -> 1064.61 | AK21: =AG21-AH21 -> 0 | AL21: =AI21-AJ21 -> 0 | AM21: =AG21-AG20 -> 267.87 | AN21: =AH21-AH20 -> 287.87 | AO21: =AJ21-AJ20 -> 251.7 | AP21: =AN21-AM21 -> 20 | AQ21: =AO21-AN21 -> -36.17 | AR21: =K21-D21 -> -6.13 | AS21: =AI21-AG21 -> -10.49 | AT21: =AJ21-AH21 -> -10.49 | AU21: =ABS(AR21/K21) -> 0.00077968693 | AV21: =ABS(AS21/AI21) -> 0.0098533735 | AW21: =ABS(AR21/AVERAGE(K21,D21)) -> 0.00077938309 | AX21: =ABS((AG21-AH21)/AVERAGE(AG21,AH21)) -> 4.2298144e-16 | BP21: =ABS((AR22-AS22)/((ABS(AR22)+ABS(AS22))/2))/10 -> 0.018405645 | BT21: =6/30 -> 0.2 | BU21: =BT21*1000 -> 200 | BW21: =Health!N32 -> 147.65
B22: 44470 | C22: =SUM(Data!C144:C150) -> 3140 | D22: =Data!Q151 -> 8916.67 | E22: =Data!Q148 -> 666.71 | F22: =Data!Q149 -> 5249.96 | G22: =Data!Q150 -> 3000 | K22: =Data!U151 -> 8946.91 | L22: =Data!Q148 -> 666.71 | M22: =Data!U150 -> 3000 | N22: =Data!U149 -> 5249.46 | O22: =Data!AD149 -> 5.89 | R22: =K21-K22+C22 -> 2055.22 | S22: 160 | T22: 300 | U22: 300 | V22: 200 | Z22: =Data!F145 -> 163.83 | AA22: =Data!F144 -> 273.86 | AB22: =Data!I144 -> 300 | AC22: =SUM(Data!I145:I150) -> 368.9 | AD22: =SUM(Data!F144:F150) -> 1422.69 | AE22: =SUM(Data!I144:I150) -> 668.9 | AF22: =SUM(AD22:AE22) -> 2091.59 | AG22: =C22-AF22 -> 1048.41 | AH22: =D22-D21 -> 1048.41 | AI22: =C22-R22 -> 1084.78 | AJ22: =K22-K21 -> 1084.78 | AK22: =AG22-AH22 -> 0 | AL22: =AI22-AJ22 -> 0 | AM22: =AG22-AG21 -> -26.69 | AN22: =AH22-AH21 -> -26.69 | AO22: =AJ22-AJ21 -> 20.17 | AP22: =AN22-AM22 -> 1.3642421e-12 | AQ22: =AO22-AN22 -> 46.86 | AR22: =K22-D22 -> 30.24 | AS22: =AI22-AG22 -> 36.37 | AT22: =AJ22-AH22 -> 36.37 | AU22: =ABS(AR22/K22) -> 0.0033799379 | AV22: =ABS(AS22/AI22) -> 0.033527536 | AW22: =ABS(AR22/AVERAGE(K22,D22)) -> 0.0033856595 | AX22: =ABS((AG22-AH22)/AVERAGE(AG22,AH22)) -> 8.6749907e-16 | BP22: =ABS((AR23-AS23)/((ABS(AR23)+ABS(AS23))/2))/10 -> 0.13487957 | BT22: =19/31 -> 0.61290323 | BU22: =BT22*1000 -> 612.90323 | BW22: =Health!N33 -> 148.9
B23: 44501 | C23: =SUM(Data!C153:C160) -> 3000 | D23: =Data!Q161 -> 9629.73 | E23: =Data!Q158 -> 379.77 | F23: =Data!Q159 -> 5749.96 | G23: =Data!Q160 -> 3500 | K23: =Data!U161 -> 9667.27 | L23: =Data!U158 -> 409.73 | M23: =Data!U160 -> 3500 | N23: =Data!U159 -> 5757.54 | O23: =Data!AD159 -> 31.89 | R23: =K22-K23+C23 -> 2279.64 | S23: 160 | T23: 300 | U23: 250 | V23: 200 | Z23: =Data!F154 -> 153.47 | AA23: =Data!F153 -> 405.92 | AB23: =Data!I153 -> 260 | AC23: =SUM(Data!I154:I160) -> 171.55 | AD23: =SUM(Data!F153:F160) -> 1855.39 | AE23: =SUM(Data!I153:I160) -> 431.55 | AF23: =SUM(AD23:AE23) -> 2286.94 | AG23: =C23-AF23 -> 713.06 | AH23: =D23-D22 -> 713.06 | AI23: =C23-R23 -> 720.36 | AJ23: =K23-K22 -> 720.36 | AK23: =AG23-AH23 -> 0 | AL23: =AI23-AJ23 -> 0 | AM23: =AG23-AG22 -> -335.35 | AN23: =AH23-AH22 -> -335.35 | AO23: =AJ23-AJ22 -> -364.42 | AP23: =AN23-AM23 -> -1.3642421e-12 | AQ23: =AO23-AN23 -> -29.07 | AR23: =K23-D23 -> 37.54 | AS23: =AI23-AG23 -> 7.3 | AT23: =AJ23-AH23 -> 7.3 | AU23: =ABS(AR23/K23) -> 0.0038832059 | AV23: =ABS(AS23/AI23) -> 0.010133822 | AW23: =ABS(AR23/AVERAGE(K23,D23)) -> 0.0038907602 | AX23: =ABS((AG23-AH23)/AVERAGE(AG23,AH23)) -> 6.3774065e-16 | BP23: =ABS((AR24-AS24)/((ABS(AR24)+ABS(AS24))/2))/10 -> 0.19830956 | BT23: =19/30 -> 0.63333333 | BU23: =BT23*1000 -> 633.33333 | BW23: =Health!N34 -> 152.96
B24: 44531 | C24: =SUM(Data!C163:C171) -> 4870 | D24: =Data!Q172 -> 11743.84 | E24: =Data!Q169 -> 493.88 | F24: =Data!Q170 -> 6749.96 | G24: =Data!Q171 -> 4500 | K24: =Data!U172 -> 11781.54 | L24: =Data!U169 -> 519.91 | M24: =Data!U171 -> 4500 | N24: =Data!U170 -> 6761.63 | O24: =Data!AD170 -> 48.42 | R24: =K23-K24+C24 -> 2755.73 | S24: 160 | T24: 300 | U24: 200 | V24: 200 | Z24: =Data!F164 -> 181.02 | AA24: =Data!F163 -> 451.51 | AB24: =Data!I163 -> 140 | AC24: =SUM(Data!I164:I171) -> 86.34 | AD24: =SUM(Data!F163:F171) -> 2529.55 | AE24: =SUM(Data!I163:I171) -> 226.34 | AF24: =AD24+AE24 -> 2755.89 | AG24: =C24-AF24 -> 2114.11 | AH24: =D24-D23 -> 2114.11 | AI24: =C24-R24 -> 2114.27 | AJ24: =K24-K23 -> 2114.27 | AK24: =AG24-AH24 -> 0 | AL24: =AI24-AJ24 -> 0 | AM24: =AG24-AG23 -> 1401.05 | AN24: =AH24-AH23 -> 1401.05 | AO24: =AJ24-AJ23 -> 1393.91 | AP24: =AN24-AM24 -> 0 | AQ24: =AO24-AN24 -> -7.14 | AR24: =K24-D24 -> 37.7 | AS24: =AI24-AG24 -> 0.16 | AT24: =AJ24-AH24 -> 0.16 | AU24: =ABS(AR24/K24) -> 0.0031999212 | AV24: =ABS(AS24/AI24) -> 7.5676238e-05 | AW24: =ABS(AR24/AVERAGE(K24,D24)) -> 0.0032050492 | AX24: =ABS((AG24-AH24)/AVERAGE(AG24,AH24)) -> 4.3020217e-16 | BP24: =ABS((AR25-AS25)/((ABS(AR25)+ABS(AS25))/2))/10 -> 0.2 | BT24: =16/31 -> 0.51612903 | BU24: =BT24*1000 -> 516.12903 | BW24: =Health!N35 -> 157.45
B25: 44562 | C25: =SUM(Data!C175:C182) -> 3000 | D25: =Data!Q183 -> 12613.77 | E25: =Data!Q180 -> 563.81 | F25: =Data!Q181 -> 7149.96 | G25: =Data!Q182 -> 4900 | K25: =Data!U183 -> 12636.22 | L25: =Data!U180 -> 568.53 | M25: =Data!U182 -> 4900 | N25: =Data!U181 -> 7167.69 | O25: =Data!AD181 -> 56.57 | R25: =K24-K25+C25 -> 2145.32 | S25: 160 | T25: 350 | U25: 100 | V25: 150 | Z25: =Data!F175 -> 200.77 | AA25: =Data!F174 -> 348.52 | AB25: =Data!I174 -> 110 | AC25: =SUM(Data!I175:I182) -> 257.53 | AD25: =SUM(Data!F174:F182) -> 1762.54 | AE25: =SUM(Data!I174:I182) -> 367.53 | AF25: =AD25+AE25 -> 2130.07 | AG25: =C25-AF25 -> 869.93 | AH25: =D25-D24 -> 869.93 | AI25: =C25-R25 -> 854.68 | AJ25: =K25-K24 -> 854.68 | AK25: =AG25-AH25 -> 0 | AL25: =AI25-AJ25 -> 0 | AM25: =AG25-AG24 -> -1244.18 | AN25: =AH25-AH24 -> -1244.18 | AO25: =AJ25-AJ24 -> -1259.59 | AP25: =AN25-AM25 -> 0 | AQ25: =AO25-AN25 -> -15.41 | AR25: =K25-D25 -> 22.45 | AS25: =AI25-AG25 -> -15.25 | AT25: =AJ25-AH25 -> -15.25 | AU25: =ABS(AR25/K25) -> 0.0017766389 | AV25: =ABS(AS25/AI25) -> 0.017842935 | AW25: =ABS(AR25/AVERAGE(K25,D25)) -> 0.0017782185 | AX25: =ABS((AG25-AH25)/AVERAGE(AG25,AH25)) -> 5.2274016e-16 | BP25: =ABS((AR26-AS26)/((ABS(AR26)+ABS(AS26))/2))/10 -> 0.09065213 | BT25: =16/31 -> 0.51612903 | BU25: =BT25*1000 -> 516.12903 | BW25: =Health!N36 -> 160.6
B26: 44593 | C26: =SUM(Data!C185:C191) -> 3000 | D26: =Data!Q192 -> 13715.39 | E26: =Data!Q189 -> 965.43 | F26: =Data!Q190 -> 7449.96 | G26: =Data!Q191 -> 5300 | K26: =Data!U192 -> 13751.38 | L26: =Data!U189 -> 975.64 | M26: =Data!U191 -> 5300 | N26: =Data!U190 -> 7475.74 | O26: =Data!AD190 -> 62.06 | R26: =K25-K26+C26 -> 1884.84 | S26: 160 | T26: 350 | U26: 100 | V26: 150 | Z26: =Data!F186 -> 191.03 | AA26: =Data!F185 -> 307.1 | AB26: =Data!I185 -> 175 | AC26: =SUM(Data!I186:I191) -> 114.25 | AD26: =SUM(Data!F185:F191) -> 1609.13 | AE26: =SUM(Data!I185:I191) -> 289.25 | AF26: =AD26+AE26 -> 1898.38 | AG26: =C26-AF26 -> 1101.62 | AH26: =D26-D25 -> 1101.62 | AI26: =C26-R26 -> 1115.16 | AJ26: =K26-K25 -> 1115.16 | AK26: =AG26-AH26 -> 0 | AL26: =AI26-AJ26 -> 0 | AM26: =AG26-AG25 -> 231.69 | AN26: =AH26-AH25 -> 231.69 | AO26: =AJ26-AJ25 -> 260.48 | AP26: =AN26-AM26 -> 4.5474735e-13 | AQ26: =AO26-AN26 -> 28.79 | AR26: =K26-D26 -> 35.99 | AS26: =AI26-AG26 -> 13.54 | AT26: =AJ26-AH26 -> 13.54 | AU26: =ABS(AR26/K26) -> 0.0026171919 | AV26: =ABS(AS26/AI26) -> 0.012141755 | AW26: =ABS(AR26/AVERAGE(K26,D26)) -> 0.0026206212 | AX26: =ABS((AG26-AH26)/AVERAGE(AG26,AH26)) -> 8.2559749e-16 | BP26: =ABS((AR27-AS27)/((ABS(AR27)+ABS(AS27))/2))/10 -> 0.14375874 | BT26: =19/29 -> 0.65517241 | BU26: =BT26*1000 -> 655.17241 | BW26: =Health!N37 -> 160.52
B27: 44621 | C27: =SUM(Data!C194:C201) -> 3200 | D27: =Data!Q202 -> 14195.84 | E27: =Data!Q199 -> 745.88 | F27: =Data!Q200 -> 7749.96 | G27: =Data!Q201 -> 5700 | K27: =Data!U202 -> 14238.87 | L27: =Data!U199 -> 754.07 | M27: =Data!U201 -> 5700 | N27: =Data!U200 -> 7784.8 | O27: =Data!AD200 -> 64.04 | R27: =K26-K27+C27 -> 2712.51 | S27: 160 | T27: 350 | U27: 100 | V27: 150 | Z27: =Data!F195 -> 218.19 | AA27: =Data!F194 -> 564.87 | AB27: =Data!I194 -> 170 | AC27: =SUM(Data!I195:I201) -> 671.49 | AD27: =SUM(Data!F194:F201) -> 1878.06 | AE27: =SUM(Data!I194:I201) -> 841.49 | AF27: =AD27+AE27 -> 2719.55 | AG27: =C27-AF27 -> 480.45 | AH27: =D27-D26 -> 480.45 | AI27: =C27-R27 -> 487.49 | AJ27: =K27-K26 -> 487.49 | AK27: =AG27-AH27 -> 9.094947e-13 | AL27: =AI27-AJ27 -> 0 | AM27: =AG27-AG26 -> -621.17 | AN27: =AH27-AH26 -> -621.17 | AO27: =AJ27-AJ26 -> -627.67 | AP27: =AN27-AM27 -> -1.8189894e-12 | AQ27: =AO27-AN27 -> -6.5 | AR27: =K27-D27 -> 43.03 | AS27: =AI27-AG27 -> 7.04 | AT27: =AJ27-AH27 -> 7.04 | AU27: =ABS(AR27/K27) -> 0.0030220095 | AV27: =ABS(AS27/AI27) -> 0.014441322 | AW27: =ABS(AR27/AVERAGE(K27,D27)) -> 0.0030265827 | AX27: =ABS((AG27-AH27)/AVERAGE(AG27,AH27)) -> 1.8930059e-15 | BP27: =ABS((AR28-AS28)/((ABS(AR28)+ABS(AS28))/2))/10 -> 0.18471775 | BT27: =19/31 -> 0.61290323 | BU27: =BT27*1000 -> 612.90323 | BW27: =Health!N38 -> 162.4
B28: 44652 | C28: =SUM(Data!C204:C212) -> 3000 | D28: =Data!Q213 -> 10253.7 | E28: =Data!Q210 -> 503.74 | F28: =Data!Q211 -> 3749.96 | G28: =Data!Q212 -> 6000 | K28: =Data!U213 -> 10251.92 | L28: =Data!U210 -> 457.08 | M28: =Data!U212 -> 6000 | N28: =Data!U211 -> 3794.84 | O28: =Data!AD211 -> 54.47 | R28: =K27-K28+C28 -> 6986.95 | S28: 200 | T28: 400 | U28: 100 | V28: 150 | Z28: =Data!F205 -> 281.74 | AA28: =Data!F204 -> 383.9 | AB28: =Data!I204 -> 120 | AC28: =SUM(Data!I205:I212) -> 300.01 | AD28: =SUM(Data!F204:F212) -> 6522.13 | AE28: =SUM(Data!I204:I212) -> 420.01 | AF28: =AD28+AE28 -> 6942.14 | AG28: =C28-AF28 -> -3942.14 | AH28: =D28-D27 -> -3942.14 | AI28: =C28-R28 -> -3986.95 | AJ28: =K28-K27 -> -3986.95 | AK28: =AG28-AH28 -> 0 | AL28: =AI28-AJ28 -> 0 | AM28: =AG28-AG27 -> -4422.59 | AN28: =AH28-AH27 -> -4422.59 | AO28: =AJ28-AJ27 -> -4474.44 | AP28: =AN28-AM28 -> 0 | AQ28: =AO28-AN28 -> -51.85 | AR28: =K28-D28 -> -1.78 | AS28: =AI28-AG28 -> -44.81 | AT28: =AJ28-AH28 -> -44.81 | AU28: =ABS(AR28/K28) -> 0.00017362601 | AV28: =ABS(AS28/AI28) -> 0.011239168 | AW28: =ABS(AR28/AVERAGE(K28,D28)) -> 0.00017361094 | AX28: =ABS((AG28-AH28)/AVERAGE(AG28,AH28)) -> 2.3071091e-16 | BP28: =ABS((AR29-AS29)/((ABS(AR29)+ABS(AS29))/2))/10 -> 0.0039634825 | BT28: =24/30 -> 0.8 | BU28: =BT28*1000 -> 800 | BW28: =Health!N39 -> 162.55
B29: 44682 | C29: =SUM(Data!C215:C224) -> 2169 | D29: =Data!Q225 -> 9798.64 | E29: =Data!Q222 -> 1548.68 | F29: =Data!Q223 -> 2249.96 | G29: =Data!Q224 -> 6000 | K29: =Data!U225 -> 9752.84 | L29: =Data!U222 -> 1455.98 | M29: =Data!U224 -> 6000 | N29: =Data!U223 -> 2296.86 | O29: =Data!AD223 -> 95.58 | R29: =K28-K29+C29 -> 2668.08 | S29: 200 | T29: 400 | U29: 100 | V29: 150 | Z29: =Data!F216 -> 239.45 | AA29: =Data!F215 -> 581.74 | AB29: =Data!I215 -> 140 | AC29: =SUM(Data!I216:I224) -> 281.3 | AD29: =SUM(Data!F215:F224) -> 2202.76 | AE29: =SUM(Data!I215:I224) -> 421.3 | AF29: =AD29+AE29 -> 2624.06 | AG29: =C29-AF29 -> -455.06 | AH29: =D29-D28 -> -455.06 | AI29: =C29-R29 -> -499.08 | AJ29: =K29-K28 -> -499.08 | AK29: =AG29-AH29 -> -4.5474735e-13 | AL29: =AI29-AJ29 -> 0 | AM29: =AG29-AG28 -> 3487.08 | AN29: =AH29-AH28 -> 3487.08 | AO29: =AJ29-AJ28 -> 3487.87 | AP29: =AN29-AM29 -> 0 | AQ29: =AO29-AN29 -> 0.79 | AR29: =K29-D29 -> -45.8 | AS29: =AI29-AG29 -> -44.02 | AT29: =AJ29-AH29 -> -44.02 | AU29: =ABS(AR29/K29) -> 0.004696068 | AV29: =ABS(AS29/AI29) -> 0.088202292 | AW29: =ABS(AR29/AVERAGE(K29,D29)) -> 0.0046850673 | AX29: =ABS((AG29-AH29)/AVERAGE(AG29,AH29)) -> 9.9931295e-16 | BP29: =ABS((AR30-AS30)/((ABS(AR30)+ABS(AS30))/2))/10 -> 0.093526649 | BT29: =24/31 -> 0.77419355 | BU29: =BT29*1000 -> 774.19355 | BW29: =Health!N40 -> 164.5
B30: 44713 | C30: =SUM(Data!C227:C232) -> 1582.04 | D30: =Data!Q233 -> 9319.54 | E30: =Data!Q230 -> 2069.58 | F30: =Data!Q231 -> 1249.96 | G30: =Data!Q232 -> 6000 | K30: =Data!U233 -> 9247.67 | L30: =Data!U230 -> 1947.8 | M30: =Data!U232 -> 6000 | N30: =Data!U231 -> 1299.87 | O30: =Data!AD231 -> 97.93 | R30: =K29-K30+C30 -> 2087.21 | S30: 200 | T30: 400 | U30: 80 | V30: 150 | Z30: =Data!F228 -> 293.08 | AA30: =Data!F227 -> 674.58 | AB30: =Data!I227 -> 160 | AC30: =SUM(Data!I227:I232) -> 242.48 | AD30: =SUM(Data!F227:F232) -> 1818.66 | AE30: =SUM(Data!I227:I233) -> 242.48 | AF30: =AD30+AE30 -> 2061.14 | AG30: =C30-AF30 -> -479.1 | AH30: =D30-D29 -> -479.1 | AI30: =C30-R30 -> -505.17 | AJ30: =K30-K29 -> -505.17 | AK30: =AG30-AH30 -> 4.5474735e-13 | AL30: =AI30-AJ30 -> 0 | AM30: =AG30-AG29 -> -24.04 | AN30: =AH30-AH29 -> -24.04 | AO30: =AJ30-AJ29 -> -6.09 | AP30: =AN30-AM30 -> -9.094947e-13 | AQ30: =AO30-AN30 -> 17.95 | AR30: =K30-D30 -> -71.87 | AS30: =AI30-AG30 -> -26.07 | AT30: =AJ30-AH30 -> -26.07 | AU30: =ABS(AR30/K30) -> 0.0077716874 | AV30: =ABS(AS30/AI30) -> 0.05160639 | AW30: =ABS(AR30/AVERAGE(K30,D30)) -> 0.0077416047 | AX30: =ABS((AG30-AH30)/AVERAGE(AG30,AH30)) -> 9.4917001e-16 | BP30: =ABS((AR31-AS31)/((ABS(AR31)+ABS(AS31))/2))/10 -> 0.2 | BT30: =24/30 -> 0.8 | BU30: =BT30*1000 -> 800 | BW30: =Health!N41 -> 166.28
B31: 44743 | C31: =SUM(Data!C235:C244) -> 1567.04 | D31: =Data!Q245 -> 8643.57 | E31: =Data!Q242 -> 1793.61 | F31: =Data!Q243 -> 849.96 | G31: =Data!Q244 -> 6000 | K31: =Data!U245 -> 8597.33 | L31: =Data!U242 -> 1688.45 | M31: =Data!U244 -> 6000 | N31: =Data!U243 -> 908.88 | O31: =Data!AD243 -> 113.49 | R31: =K30-K31+C31 -> 2217.38 | S31: 200 | T31: 500 | U31: 0 | V31: 150 | Z31: =Data!F236 -> 228.94 | AA31: =Data!F235 -> 543.72 | AB31: =Data!I235 -> 140 | AC31: =SUM(Data!I236:I244) -> 367.34 | AD31: =SUM(Data!F235:F244) -> 1735.67 | AE31: =SUM(AC31+AB31) -> 507.34 | AF31: =AD31+AE31 -> 2243.01 | AG31: =C31-AF31 -> -675.97 | AH31: =D31-D30 -> -675.97 | AI31: =C31-R31 -> -650.34 | AJ31: =K31-K30 -> -650.34 | AK31: =AG31-AH31 -> 0 | AL31: =AI31-AJ31 -> 0 | AM31: =AG31-AG30 -> -196.87 | AN31: =AH31-AH30 -> -196.87 | AO31: =AJ31-AJ30 -> -145.17 | AP31: =AN31-AM31 -> 9.094947e-13 | AQ31: =AO31-AN31 -> 51.7 | AR31: =K31-D31 -> -46.24 | AS31: =AI31-AG31 -> 25.63 | AT31: =AJ31-AH31 -> 25.63 | AU31: =ABS(AR31/K31) -> 0.005378414 | AV31: =ABS(AS31/AI31) -> 0.039410155 | AW31: =ABS(AR31/AVERAGE(K31,D31)) -> 0.0053639891 | AX31: =ABS((AG31-AH31)/AVERAGE(AG31,AH31)) -> 6.7273304e-16 | BP31: =ABS((AR32-AS32)/((ABS(AR32)+ABS(AS32))/2))/10 -> 0.15418473 | BT31: =25/30 -> 0.83333333 | BU31: =BT31*1000 -> 833.33333 | BW31: =Health!N42 -> 168.55
B32: 44774 | C32: =SUM(Data!C247:C256) -> 0 | D32: =Data!Q257 -> 6215.33 | E32: =Data!Q254 -> 225.37 | F32: =Data!Q255 -> 289.96 | G32: =Data!Q256 -> 5700 | K32: =Data!U257 -> 6162.22 | L32: =Data!U254 -> 149.33 | M32: =Data!U256 -> 5700 | N32: =Data!U255 -> 312.89 | O32: =Data!AD255 -> 105.55 | R32: =K31-K32+C32 -> 2435.11 | S32: 200 | T32: 500 | U32: 0 | V32: 150 | Z32: =Data!F248 -> 216.94 | AA32: =Data!F247 -> 498.76 | AB32: =Data!I247 -> 100 | AC32: =SUM(Data!I248:I256) -> 600.46 | AD32: =SUM(Data!F247:F256) -> 1727.78 | AE32: =SUM(Data!I247:I256) -> 700.46 | AF32: =AD32+AE32 -> 2428.24 | AG32: =C32-AF32 -> -2428.24 | AH32: =D32-D31 -> -2428.24 | AI32: =C32-R32 -> -2435.11 | AJ32: =K32-K31 -> -2435.11 | AK32: =AG32-AH32 -> 0 | AL32: =AI32-AJ32 -> 0 | AM32: =AG32-AG31 -> -1752.27 | AN32: =AH32-AH31 -> -1752.27 | AO32: =AJ32-AJ31 -> -1784.77 | AP32: =AN32-AM32 -> 0 | AQ32: =AO32-AN32 -> -32.5 | AR32: =K32-D32 -> -53.11 | AS32: =AI32-AG32 -> -6.87 | AT32: =AJ32-AH32 -> -6.87 | AU32: =ABS(AR32/K32) -> 0.0086186472 | AV32: =ABS(AS32/AI32) -> 0.0028212278 | AW32: =ABS(AR32/AVERAGE(K32,D32)) -> 0.008581666 | AX32: =ABS((AG32-AH32)/AVERAGE(AG32,AH32)) -> 0 | BP32: =ABS((AR33-AS33)/((ABS(AR33)+ABS(AS33))/2))/10 -> 0.2 | BT32: =27/31 -> 0.87096774 | BU32: =BT32*1000 -> 870.96774 | BW32: =Health!N43 -> 169.95
B33: 44805 | C33: =SUM(Data!C259:C265) -> 1507.04 | D33: =Data!Q266 -> 5591.15 | E33: =Data!Q263 -> 1501.19 | F33: =Data!Q264 -> 489.96 | G33: =Data!Q265 -> 3600 | K33: =Data!U266 -> 5542.64 | L33: =Data!U263 -> 1521.75 | M33: =Data!U265 -> 3600 | N33: =Data!U264 -> 420.89 | O33: =Data!AD264 -> 103.66 | R33: =K32-K33+C33 -> 2126.62 | S33: 200 | T33: 500 | U33: 0 | V33: 150 | Z33: =Data!F260 -> 184.94 | AA33: =Data!F259 -> 673.68 | AB33: 0 | AC33: =SUM(Data!I259:I265) -> 332.44 | AD33: =SUM(Data!F259:F265) -> 1798.78 | AE33: =SUM(Data!I259:I265) -> 332.44 | AF33: =AD33+AE33 -> 2131.22 | AG33: =C33-AF33 -> -624.18 | AH33: =D33-D32 -> -624.18 | AI33: =C33-R33 -> -619.58 | AJ33: =K33-K32 -> -619.58 | AK33: =AG33-AH33 -> 0 | AL33: =AI33-AJ33 -> 0 | AM33: =AG33-AG32 -> 1804.06 | AN33: =AH33-AH32 -> 1804.06 | AO33: =AJ33-AJ32 -> 1815.53 | AP33: =AN33-AM33 -> 0 | AQ33: =AO33-AN33 -> 11.47 | AR33: =K33-D33 -> -48.51 | AS33: =AI33-AG33 -> 4.6 | AT33: =AJ33-AH33 -> 4.6 | AU33: =ABS(AR33/K33) -> 0.008752147 | AV33: =ABS(AS33/AI33) -> 0.0074243843 | AW33: =ABS(AR33/AVERAGE(K33,D33)) -> 0.0087140138 | AX33: =ABS((AG33-AH33)/AVERAGE(AG33,AH33)) -> 0 | BP33: =ABS((AR34-AS34)/((ABS(AR34)+ABS(AS34))/2))/10 -> 0.065039887 | BT33: =26/30 -> 0.86666667 | BU33: =BT33*1000 -> 866.66667 | BW33: =Health!N44 -> 171.68
B34: 44835 | C34: =SUM(Data!C268:C276) -> 1507.04 | D34: =Data!Q277 -> 4637.26 | E34: =Data!Q274 -> 1647.3 | F34: =Data!Q275 -> 489.96 | G34: =Data!Q276 -> 2500 | K34: =Data!U277 -> 4538.42 | L34: =Data!Q274 -> 1647.3 | M34: =Data!Q276 -> 2500 | N34: =Data!Q275 -> 489.96 | O34: =Data!AD275 -> 109.32 | R34: =K33-K34+C34 -> 2511.26 | S34: 200 | T34: 400 | U34: 0 | V34: 150 | Z34: =Data!F269 -> 205.16 | AA34: =Data!F268 -> 619.2 | AB34: 0 | AC34: =SUM(Data!I268:I276) -> 428.4 | AD34: =SUM(Data!F268:F276) -> 2032.53 | AE34: =SUM(Data!I268:I276) -> 428.4 | AF34: =AD34+AE34 -> 2460.93 | AG34: =C34-AF34 -> -953.89 | AH34: =D34-D33 -> -953.89 | AI34: =C34-R34 -> -1004.22 | AJ34: =K34-K33 -> -1004.22 | AK34: =AG34-AH34 -> 0 | AL34: =AI34-AJ34 -> 0 | AM34: =AG34-AG33 -> -329.71 | AN34: =AH34-AH33 -> -329.71 | AO34: =AJ34-AJ33 -> -384.64 | AP34: =AN34-AM34 -> -4.5474735e-13 | AQ34: =AO34-AN34 -> -54.93 | AR34: =K34-D34 -> -98.84 | AS34: =AI34-AG34 -> -50.33 | AT34: =AJ34-AH34 -> -50.33 | AU34: =ABS(AR34/K34) -> 0.021778504 | AV34: =ABS(AS34/AI34) -> 0.0501185 | AW34: =ABS(AR34/AVERAGE(K34,D34)) -> 0.021543907 | AX34: =ABS((AG34-AH34)/AVERAGE(AG34,AH34)) -> 4.7672934e-16 | BP34: =ABS((AR35-AS35)/((ABS(AR35)+ABS(AS35))/2))/10 -> 0.12891613 | BT34: =22/31 -> 0.70967742 | BU34: =BT34*1000 -> 709.67742 | BW34: =Health!N45 -> 178.06667
B35: 44866 | C35: =SUM(Data!C279:C288) -> 1507.04 | D35: =Data!Q289 -> 3809.64 | E35: =Data!Q286 -> 1519.68 | F35: =Data!Q287 -> 489.96 | G35: =Data!Q288 -> 1800 | K35: =Data!U289 -> 3683.55 | L35: =Data!U286 -> 1443.66 | M35: =Data!U288 -> 1800 | N35: =Data!U287 -> 439.89 | O35: =Data!AD287 -> 91.37 | R35: =K34-K35+C35 -> 2361.91 | S35: 160 | T35: 350 | U35: 0 | V35: 150 | Z35: =Data!F280 -> 178.95 | AA35: =Data!F279 -> 523.52 | AB35: 0 | AC35: =SUM(Data!I279:I288) -> 281.03 | AD35: =SUM(Data!F279:F288) -> 2053.63 | AE35: =SUM(Data!I279:I288) -> 281.03 | AF35: =AD35+AE35 -> 2334.66 | AG35: =C35-AF35 -> -827.62 | AH35: =D35-D34 -> -827.62 | AI35: =C35-R35 -> -854.87 | AJ35: =K35-K34 -> -854.87 | AK35: =AG35-AH35 -> 0 | AL35: =AI35-AJ35 -> 0 | AM35: =AG35-AG34 -> 126.27 | AN35: =AH35-AH34 -> 126.27 | AO35: =AJ35-AJ34 -> 149.35 | AP35: =AN35-AM35 -> 4.5474735e-13 | AQ35: =AO35-AN35 -> 23.08 | AR35: =K35-D35 -> -126.09 | AS35: =AI35-AG35 -> -27.25 | AT35: =AJ35-AH35 -> -27.25 | AU35: =ABS(AR35/K35) -> 0.034230566 | AV35: =ABS(AS35/AI35) -> 0.031876192 | AW35: =ABS(AR35/AVERAGE(K35,D35)) -> 0.033654558 | AX35: =ABS((AG35-AH35)/AVERAGE(AG35,AH35)) -> 0 | BP35: =ABS((AR36-AS36)/((ABS(AR36)+ABS(AS36))/2))/10 -> 0.12645815 | BT35: =22/30 -> 0.73333333 | BU35: =BT35*1000 -> 733.33333 | BW35: =Health!N46 -> 180.75
B36: 44896 | C36: =SUM(Data!C291:C300) -> 1557.04 | D36: =Data!Q301 -> 2792.53 | E36: =Data!Q298 -> 807.57 | F36: =Data!Q299 -> 484.96 | G36: =Data!Q300 -> 1500 | K36: =Data!U301 -> 2636.23 | L36: =Data!U298 -> 693.33 | M36: =Data!U300 -> 1500 | N36: =Data!U299 -> 442.9 | O36: =Data!AD299 -> 88.54 | R36: =K35-K36+C36 -> 2604.36 | S36: 160 | T36: 350 | U36: 0 | V36: 150 | Z36: =Data!F292 -> 157 | AA36: =Data!F291 -> 397.56 | AB36: =Data!I299 -> 70 | AC36: =SUM(Data!I291:I299) -> 521.12 | AD36: =SUM(Data!F291:F300) -> 2048.03 | AE36: =SUM(Data!I291:I299) -> 521.12 | AF36: =AD36+AE36 -> 2569.15 | AG36: =C36-AF36 -> -1012.11 | AH36: =D36-D35 -> -1017.11 | AI36: =C36-R36 -> -1047.32 | AJ36: =K36-K35 -> -1047.32 | AK36: =AG36-AH36 -> 5 | AL36: =AI36-AJ36 -> 0 | AM36: =AG36-AG35 -> -184.49 | AN36: =AH36-AH35 -> -189.49 | AO36: =AJ36-AJ35 -> -192.45 | AP36: =AN36-AM36 -> -5 | AQ36: =AO36-AN36 -> -2.96 | AR36: =K36-D36 -> -156.3 | AS36: =AI36-AG36 -> -35.21 | AT36: =AJ36-AH36 -> -30.21 | AU36: =ABS(AR36/K36) -> 0.059289212 | AV36: =ABS(AS36/AI36) -> 0.033619142 | AW36: =ABS(AR36/AVERAGE(K36,D36)) -> 0.05758221 | AX36: =ABS((AG36-AH36)/AVERAGE(AG36,AH36)) -> 0.0049280019 | BP36: =ABS((AR37-AS37)/((ABS(AR37)+ABS(AS37))/2))/10 -> 0.2 | BT36: =26/31 -> 0.83870968 | BU36: =BT36*1000 -> 838.70968 | BW36: =Health!N47 -> 180.05
B37: 44927 | C37: =SUM(Data!C303:C311) -> 0 | D37: =Data!Q312 -> 988.79 | E37: =Data!Q309 -> 353.83 | F37: =Data!Q310 -> 434.96 | G37: =Data!Q311 -> 200 | K37: =Data!U312 -> 872.24 | L37: =Data!U309 -> 274.34 | M37: =Data!U311 -> 200 | N37: =Data!U310 -> 397.9 | O37: =Data!AD310 -> 123.28 | R37: =K36-K37+C37 -> 1763.99 | S37: 160 | T37: 350 | U37: 0 | V37: 150 | Z37: =Data!F304 -> 169.01 | AA37: =Data!F303 -> 408.37 | AB37: 0 | AC37: =SUM(Data!I303:I311) -> 338.2 | AD37: =SUM(Data!F303:F311) -> 1465.54 | AE37: =SUM(Data!I303:I311) -> 338.2 | AF37: =AD37+AE37 -> 1803.74 | AG37: =C37-AF37 -> -1803.74 | AH37: =D37-D36 -> -1803.74 | AI37: =C37-R37 -> -1763.99 | AJ37: =K37-K36 -> -1763.99 | AK37: =AG37-AH37 -> 0 | AL37: =AI37-AJ37 -> 0 | AM37: =AG37-AG36 -> -791.63 | AN37: =AH37-AH36 -> -786.63 | AO37: =AJ37-AJ36 -> -716.67 | AP37: =AN37-AM37 -> 5 | AQ37: =AO37-AN37 -> 69.96 | AR37: =K37-D37 -> -116.55 | AS37: =AI37-AG37 -> 39.75 | AT37: =AJ37-AH37 -> 39.75 | AU37: =ABS(AR37/K37) -> 0.13362148 | AV37: =ABS(AS37/AI37) -> 0.022534141 | AW37: =ABS(AR37/AVERAGE(K37,D37)) -> 0.12525322 | AX37: =ABS((AG37-AH37)/AVERAGE(AG37,AH37)) -> 0 | BP37: =ABS((AR38-AS38)/((ABS(AR38)+ABS(AS38))/2))/10 -> 0.2 | BT37: =25/31 -> 0.80645161 | BU37: =BT37*1000 -> 806.45161 | BW37: =Health!N48 -> 178.2
B38: 44958 | C38: =SUM(Data!C314:C319) -> 1917.79 | D38: =Data!Q320 -> 1469.33 | E38: =Data!Q317 -> 1134.37 | F38: =Data!Q318 -> 334.96 | G38: =Data!Q319 -> 0 | K38: =Data!U320 -> 1435.68 | L38: =Data!U317 -> 1138.78 | M38: =Data!U319 -> 0 | N38: =Data!U318 -> 296.9 | O38: =Data!AD318 -> 125.51 | R38: =K37-K38+C38 -> 1354.35 | S38: 160 | T38: 350 | U38: 0 | V38: 150 | Z38: =Data!F315 -> 170.38 | AA38: =Data!F314 -> 232.7 | AB38: 0 | AC38: =SUM(Data!I314:I319) -> 289.17 | AD38: =SUM(Data!F314:F319) -> 1148.08 | AE38: =AC38 -> 289.17 | AF38: =AD38+AE38 -> 1437.25 | AG38: =C38-AF38 -> 480.54 | AH38: =D38-D37 -> 480.54 | AI38: =C38-R38 -> 563.44 | AJ38: =K38-K37 -> 563.44 | AK38: =AG38-AH38 -> 0 | AL38: =AI38-AJ38 -> 0 | AM38: =AG38-AG37 -> 2284.28 | AN38: =AH38-AH37 -> 2284.28 | AO38: =AJ38-AJ37 -> 2327.43 | AP38: =AN38-AM38 -> 0 | AQ38: =AO38-AN38 -> 43.15 | AR38: =K38-D38 -> -33.65 | AS38: =AI38-AG38 -> 82.9 | AT38: =AJ38-AH38 -> 82.9 | AU38: =ABS(AR38/K38) -> 0.023438371 | AV38: =ABS(AS38/AI38) -> 0.1471319 | AW38: =ABS(AR38/AVERAGE(K38,D38)) -> 0.023166874 | AX38: =ABS((AG38-AH38)/AVERAGE(AG38,AH38)) -> 2.3658142e-16 | BP38: =ABS((AR39-AS39)/((ABS(AR39)+ABS(AS39))/2))/10 -> 0.035057561 | BT38: =24/29 -> 0.82758621 | BU38: =BT38*1000 -> 827.58621 | BW38: =Health!N49 -> 175.8
B39: 44986 | C39: =SUM(Data!C322:C328) -> 1917.79 | D39: =Data!Q329 -> 1951.43 | E39: =Data!Q326 -> 1456.47 | F39: =Data!Q327 -> 494.96 | G39: =Data!Q328 -> 0 | K39: =Data!U329 -> 1838.62 | L39: =Data!U326 -> 1373.71 | M39: =Data!U328 -> 0 | N39: =Data!U327 -> 464.91 | O39: =Data!AD327 -> 151.18 | R39: =K38-K39+C39 -> 1514.85 | S39: 160 | T39: 350 | U39: 0 | V39: 150 | Z39: =Data!F323 -> 250.6 | AA39: =Data!F322 -> 473.38 | AB39: =Data!I325 -> 40 | AC39: =SUM(Data!I322:I328) -> 476.63 | AD39: =SUM(Data!F322:F328) -> 959.06 | AE39: =SUM(Data!I322:I328) -> 476.63 | AF39: =AD39+AE39 -> 1435.69 | AG39: =C39-AF39 -> 482.1 | AH39: =D39-D38 -> 482.1 | AI39: =C39-R39 -> 402.94 | AJ39: =K39-K38 -> 402.94 | AK39: =AG39-AH39 -> 0 | AL39: =AI39-AJ39 -> 0 | AM39: =AG39-AG38 -> 1.56 | AN39: =AH39-AH38 -> 1.56 | AO39: =AJ39-AJ38 -> -160.5 | AP39: =AN39-AM39 -> -3.4106051e-13 | AQ39: =AO39-AN39 -> -162.06 | AR39: =K39-D39 -> -112.81 | AS39: =AI39-AG39 -> -79.16 | AT39: =AJ39-AH39 -> -79.16 | AU39: =ABS(AR39/K39) -> 0.061355799 | AV39: =ABS(AS39/AI39) -> 0.19645605 | AW39: =ABS(AR39/AVERAGE(K39,D39)) -> 0.059529558 | AX39: =ABS((AG39-AH39)/AVERAGE(AG39,AH39)) -> 4.7163177e-16 | BP39: =ABS((AR40-AS40)/((ABS(AR40)+ABS(AS40))/2))/10 -> 0.083098228 | BT39: =25/31 -> 0.80645161 | BU39: =BT39*1000 -> 806.45161 | BW39: =Health!N50 -> 177.25
B40: 45017 | C40: =SUM(Data!C331:C335) -> 1917.79 | D40: =Data!Q337 -> 2535.88 | E40: =Data!Q334 -> 2035.92 | F40: =Data!Q335 -> 499.96 | G40: =Data!Q336 -> 0 | K40: =Data!U337 -> 2343.72 | L40: =Data!U334 -> 1874.79 | M40: =Data!U336 -> 0 | N40: =Data!U335 -> 468.93 | O40: =Data!AD335 -> 152.55 | R40: =K39-K40+C40 -> 1412.69 | S40: 160 | T40: 350 | U40: 0 | V40: 150 | Z40: =Data!F332 -> 153.17 | AA40: =Data!F331 -> 296 | AB40: =Data!I333 -> 90 | AC40: =SUM(Data!I331:I336) -> 703.33 | AD40: =SUM(Data!F331:F336) -> 630.01 | AE40: =SUM(Data!I331:I336) -> 703.33 | AF40: =AD40+AE40 -> 1333.34 | AG40: =C40-AF40 -> 584.45 | AH40: =D40-D39 -> 584.45 | AI40: =C40-R40 -> 505.1 | AJ40: =K40-K39 -> 505.1 | AK40: =AG40-AH40 -> 0 | AL40: =AI40-AJ40 -> 0 | AM40: =AG40-AG39 -> 102.35 | AN40: =AH40-AH39 -> 102.35 | AO40: =AJ40-AJ39 -> 102.16 | AP40: =AN40-AM40 -> 4.5474735e-13 | AQ40: =AO40-AN40 -> -0.19 | AR40: =K40-D40 -> -192.16 | AS40: =AI40-AG40 -> -79.35 | AT40: =AJ40-AH40 -> -79.35 | AU40: =ABS(AR40/K40) -> 0.081989316 | AV40: =ABS(AS40/AI40) -> 0.1570976 | AW40: =ABS(AR40/AVERAGE(K40,D40)) -> 0.078760554 | AX40: =ABS((AG40-AH40)/AVERAGE(AG40,AH40)) -> 3.8903871e-16 | BP40: =ABS((AR41-AS41)/((ABS(AR41)+ABS(AS41))/2))/10 -> 0.17753141 | BT40: =21/30 -> 0.7 | BU40: =BT40*1000 -> 700 | BW40: =Health!N51 -> 177.32
B41: 45047 | C41: =SUM(Data!C339:C343) -> 1917.79 | D41: =Data!Q344 -> 2893.11 | E41: =Data!Q341 -> 2393.15 | F41: =Data!Q342 -> 499.96 | G41: =Data!Q343 -> 0 | K41: =Data!U344 -> 2688.79 | L41: =Data!U341 -> 2212.82 | M41: =Data!U343 -> 0 | N41: =Data!U342 -> 475.97 | O41: =Data!AD342 -> 145.25 | R41: =K40-K41+C41 -> 1572.72 | S41: 160 | T41: 350 | U41: 0 | V41: 150 | Z41: =Data!F340 -> 203.83 | AA41: =Data!F339 -> 337.46 | AB41: =Data!I340 -> 200 | AC41: =SUM(Data!I339:I343)-AB41 -> 654.27 | AD41: =SUM(Data!F339:F342) -> 706.29 | AE41: =SUM(Data!I339:I343) -> 854.27 | AF41: =AD41+AE41 -> 1560.56 | AG41: =C41-AF41 -> 357.23 | AH41: =D41-D40 -> 357.23 | AI41: =C41-R41 -> 345.07 | AJ41: =K41-K40 -> 345.07 | AK41: =AG41-AH41 -> 4.5474735e-13 | AL41: =AI41-AJ41 -> 0 | AM41: =AG41-AG40 -> -227.22 | AN41: =AH41-AH40 -> -227.22 | AO41: =AJ41-AJ40 -> -160.03 | AP41: =AN41-AM41 -> -6.8212103e-13 | AQ41: =AO41-AN41 -> 67.19 | AR41: =K41-D41 -> -204.32 | AS41: =AI41-AG41 -> -12.16 | AT41: =AJ41-AH41 -> -12.16 | AU41: =ABS(AR41/K41) -> 0.075989572 | AV41: =ABS(AS41/AI41) -> 0.035239227 | AW41: =ABS(AR41/AVERAGE(K41,D41)) -> 0.073208047 | AX41: =ABS((AG41-AH41)/AVERAGE(AG41,AH41)) -> 1.272982e-15 | BP41: =ABS((AR42-AS42)/((ABS(AR42)+ABS(AS42))/2))/10 -> 0.14667624 | BT41: =19/31 -> 0.61290323 | BU41: =BT41*1000 -> 612.90323 | BW41: =Health!N52 -> 178
B42: 45078 | C42: =SUM(Data!C347:C350) -> 2154.54 | D42: =Data!Q351 -> 3259.47 | E42: =Data!Q348 -> 1825.76 | F42: =Data!Q349 -> 1233.71 | G42: =Data!Q350 -> 200 | K42: =Data!U351 -> 3018.01 | L42: =Data!U348 -> 1710.85 | M42: =Data!U350 -> 200 | N42: =Data!U349 -> 1107.16 | O42: =Data!AD349 -> 160.33 | R42: =K41-K42+C42 -> 1825.32 | S42: 160 | T42: 350 | U42: 0 | V42: 150 | Z42: =Data!F347 -> 263.52 | AA42: =Data!F346 -> 531 | AB42: 40 | AC42: =SUM(Data!I346:I350) -> 444.7 | AD42: =SUM(Data!F346:F350) -> 1343.48 | AE42: =SUM(Data!I346:I350) -> 444.7 | AF42: =AD42+AE42 -> 1788.18 | AG42: =C42-AF42 -> 366.36 | AH42: =D42-D41 -> 366.36 | AI42: =C42-R42 -> 329.22 | AJ42: =K42-K41 -> 329.22 | AK42: =AG42-AH42 -> 0 | AL42: =AI42-AJ42 -> 0 | AM42: =AG42-AG41 -> 9.13 | AN42: =AH42-AH41 -> 9.13 | AO42: =AJ42-AJ41 -> -15.85 | AP42: =AN42-AM42 -> 2.2737368e-13 | AQ42: =AO42-AN42 -> -24.98 | AR42: =K42-D42 -> -241.46 | AS42: =AI42-AG42 -> -37.14 | AT42: =AJ42-AH42 -> -37.14 | AU42: =ABS(AR42/K42) -> 0.080006362 | AV42: =ABS(AS42/AI42) -> 0.1128121 | AW42: =ABS(AR42/AVERAGE(K42,D42)) -> 0.076928959 | AX42: =ABS((AG42-AH42)/AVERAGE(AG42,AH42)) -> 6.206291e-16 | BP42: =ABS((AR43-AS43)/((ABS(AR43)+ABS(AS43))/2))/10 -> 0.17532675 | BT42: =17/30 -> 0.56666667 | BU42: =BT42*1000 -> 566.66667 | BW42: =Health!N53 -> 175.53333
B43: 45108 | C43: =SUM(Data!C354:C358) -> 1799.55 | D43: =Data!Q359 -> 2177.06 | E43: =Data!Q356 -> 1543.35 | F43: =Data!Q357 -> 433.71 | G43: =Data!Q358 -> 200 | K43: =Data!U359 -> 1918.61 | L43: =Data!U356 -> 1404.18 | M43: =Data!U358 -> 200 | N43: =Data!U357 -> 314.43 | O43: =Data!AD357 -> 154.07 | R43: =K42-K43+C43 -> 2898.95 | S43: 160 | T43: 350 | U43: 0 | V43: 150 | Z43: =Data!F354 -> 380.47 | AA43: =Data!F353 -> 832 | AB43: 0 | AC43: =SUM(Data!I353:I358) -> 504.49 | AD43: =SUM(Data!F353:F358) -> 2377.47 | AE43: =AC43 -> 504.49 | AF43: =AD43+AE43 -> 2881.96 | AG43: =C43-AF43 -> -1082.41 | AH43: =D43-D42 -> -1082.41 | AI43: =C43-R43 -> -1099.4 | AJ43: =K43-K42 -> -1099.4 | AK43: =AG43-AH43 -> 0 | AL43: =AI43-AJ43 -> 0 | AM43: =AG43-AG42 -> -1448.77 | AN43: =AH43-AH42 -> -1448.77 | AO43: =AJ43-AJ42 -> -1428.62 | AP43: =AN43-AM43 -> 0 | AQ43: =AO43-AN43 -> 20.15 | AR43: =K43-D43 -> -258.45 | AS43: =AI43-AG43 -> -16.99 | AT43: =AJ43-AH43 -> -16.99 | AU43: =ABS(AR43/K43) -> 0.1347069 | AV43: =ABS(AS43/AI43) -> 0.015453884 | AW43: =ABS(AR43/AVERAGE(K43,D43)) -> 0.12620646 | AX43: =ABS((AG43-AH43)/AVERAGE(AG43,AH43)) -> 2.1006243e-16 | BP43: =ABS((AR44-AS44)/((ABS(AR44)+ABS(AS44))/2))/10 -> 0.2 | BT43: =17/30 -> 0.56666667 | BU43: =BT43*1000 -> 566.66667 | BW43: =Health!N54 -> 171.7
B44: 45139 | C44: =SUM(Data!C361:C365) -> 2668.82 | D44: =Data!Q366 -> 3319.92 | E44: =Data!Q363 -> 2686.21 | F44: =Data!Q364 -> 433.71 | G44: =Data!Q365 -> 200 | K44: =Data!U366 -> 3111.71 | L44: =Data!U363 -> 2593.19 | M44: =Data!U365 -> 200 | N44: =Data!U364 -> 318.52 | O44: =Data!AD364 -> 154.07 | R44: =K43-K44+C44 -> 1475.72 | S44: 160 | T44: 350 | U44: 0 | V44: 150 | Z44: =Data!F362 -> 291.97 | AA44: =Data!F361 -> 481.11 | AB44: =0 -> 0 | AC44: =SUM(Data!I361:I365) -> 580.72 | AD44: =SUM(Data!F361:F365) -> 945.24 | AE44: =AC44 -> 580.72 | AF44: =AD44+AE44 -> 1525.96 | AG44: =C44-AF44 -> 1142.86 | AH44: =D44-D43 -> 1142.86 | AI44: =C44-R44 -> 1193.1 | AJ44: =K44-K43 -> 1193.1 | AK44: =AG44-AH44 -> 0 | AL44: =AI44-AJ44 -> 0 | AM44: =AG44-AG43 -> 2225.27 | AN44: =AH44-AH43 -> 2225.27 | AO44: =AJ44-AJ43 -> 2292.5 | AP44: =AN44-AM44 -> 0 | AQ44: =AO44-AN44 -> 67.23 | AR44: =K44-D44 -> -208.21 | AS44: =AI44-AG44 -> 50.24 | AT44: =AJ44-AH44 -> 50.24 | AU44: =ABS(AR44/K44) -> 0.066911762 | AV44: =ABS(AS44/AI44) -> 0.042108792 | AW44: =ABS(AR44/AVERAGE(K44,D44)) -> 0.06474564 | AX44: =ABS((AG44-AH44)/AVERAGE(AG44,AH44)) -> 0 | BP44: =ABS((AR45-AS45)/((ABS(AR45)+ABS(AS45))/2))/10 -> 0.1281174 | BT44: =27/31 -> 0.87096774 | BU44: =BT44*1000 -> 870.96774 | BW44: =Health!N55 -> 172.72
B45: 45170 | C45: =SUM(Data!C368:C374) -> 2790.04 | D45: =Data!Q375 -> 3608.82 | E45: =Data!Q372 -> 2970.11 | F45: =Data!Q373 -> 538.71 | G45: =Data!Q374 -> 100 | K45: =Data!U375 -> 3342.2 | L45: =Data!U372 -> 2807.56 | M45: =Data!U374 -> 100 | N45: =Data!U373 -> 434.64 | O45: =Data!AD373 -> 144.48 | R45: =K44-K45+C45 -> 2559.55 | S45: 160 | T45: 350 | U45: 0 | V45: 150 | Z45: =Data!F369 -> 251.67 | AA45: =Data!F368 -> 631.79 | AB45: =0 -> 0 | AC45: =SUM(Data!I368:I374) -> 451.68 | AD45: =SUM(Data!F368:F374) -> 2049.46 | AE45: =SUM(Data!I368:I374) -> 451.68 | AF45: =AD45+AE45 -> 2501.14 | AG45: =C45-AF45 -> 288.9 | AH45: =D45-D44 -> 288.9 | AI45: =C45-R45 -> 230.49 | AJ45: =K45-K44 -> 230.49 | AK45: =AG45-AH45 -> 0 | AL45: =AI45-AJ45 -> 0 | AM45: =AG45-AG44 -> -853.96 | AN45: =AH45-AH44 -> -853.96 | AO45: =AJ45-AJ44 -> -962.61 | AP45: =AN45-AM45 -> 0 | AQ45: =AO45-AN45 -> -108.65 | AR45: =K45-D45 -> -266.62 | AS45: =AI45-AG45 -> -58.41 | AT45: =AJ45-AH45 -> -58.41 | AU45: =ABS(AR45/K45) -> 0.079773802 | AV45: =ABS(AS45/AI45) -> 0.25341663 | AW45: =ABS(AR45/AVERAGE(K45,D45)) -> 0.076713921 | AX45: =ABS((AG45-AH45)/AVERAGE(AG45,AH45)) -> 0 | BP45: =ABS((AR46-AS46)/((ABS(AR46)+ABS(AS46))/2))/10 -> 0.17452379 | BT45: =23/30 -> 0.76666667 | BU45: =BT45*1000 -> 766.66667 | BW45: =Health!N56 -> 175.95
B46: 45200 | C46: =SUM(Data!C377:C383) -> 2870.05 | D46: =Data!Q384 -> 2908.95 | E46: =Data!Q381 -> 2470.24 | F46: =Data!Q382 -> 338.71 | G46: =Data!Q383 -> 100 | K46: =Data!U384 -> 2622.87 | L46: =Data!U381 -> 2285.12 | M46: =Data!U383 -> 100 | N46: =Data!U382 -> 237.75 | O46: =Data!AD382 -> 184.07 | R46: =K45-K46+C46 -> 3589.38 | S46: 160 | T46: 350 | U46: 0 | V46: 150 | Z46: =Data!F378 -> 211.78 | AA46: =Data!F377 -> 610.11 | AB46: 0 | AC46: =SUM(Data!I377:I383) -> 537.27 | AD46: =SUM(Data!F377:F383) -> 3032.65 | AE46: =AC46 -> 537.27 | AF46: =AD46+AE46 -> 3569.92 | AG46: =C46-AF46 -> -699.87 | AH46: =D46-D45 -> -699.87 | AI46: =C46-R46 -> -719.33 | AJ46: =K46-K45 -> -719.33 | AK46: =AG46-AH46 -> 0 | AL46: =AI46-AJ46 -> 0 | AM46: =AG46-AG45 -> -988.77 | AN46: =AH46-AH45 -> -988.77 | AO46: =AJ46-AJ45 -> -949.82 | AP46: =AN46-AM46 -> 0 | AQ46: =AO46-AN46 -> 38.95 | AR46: =K46-D46 -> -286.08 | AS46: =AI46-AG46 -> -19.46 | AT46: =AJ46-AH46 -> -19.46 | AU46: =ABS(AR46/K46) -> 0.10907136 | AV46: =ABS(AS46/AI46) -> 0.027052952 | AW46: =ABS(AR46/AVERAGE(K46,D46)) -> 0.1034307 | AX46: =ABS((AG46-AH46)/AVERAGE(AG46,AH46)) -> 0 | BP46: =ABS((AR47-AS47)/((ABS(AR47)+ABS(AS47))/2))/10 -> 0.16768068 | BT46: =21/31 -> 0.67741935 | BU46: =BT46*1000 -> 677.41935 | BW46: =Health!N57 -> 179.73333
B47: 45231 | C47: =SUM(Data!C386:C394) -> 2790.04 | D47: =Data!Q395 -> 2540.85 | E47: =Data!Q392 -> 1802.14 | F47: =Data!Q393 -> 438.71 | G47: =Data!Q394 -> 300 | H47: 0 | K47: =Data!U395 -> 2227.2 | L47: =Data!U392 -> 1584.41 | M47: =Data!U394 -> 300 | N47: =Data!U393 -> 342.79 | O47: =Data!AD393 -> 201.48 | P47: 0 | Q47: 0 | R47: =K46-K47+C47 -> 3185.71 | S47: 160 | T47: 350 | U47: 0 | V47: 150 | Z47: =Data!F387 -> 195.75 | AA47: =Data!F386 -> 455.66 | AB47: =Data!I390 -> 60 | AC47: =SUM(Data!I386:I394) -> 961.73 | AD47: =SUM(Data!F386:F394) -> 2196.41 | AE47: =SUM(Data!I386:I394) -> 961.73 | AF47: =AD47+AE47 -> 3158.14 | AG47: =C47-AF47 -> -368.1 | AH47: =D47-D46 -> -368.1 | AI47: =C47-R47 -> -395.67 | AJ47: =K47-K46 -> -395.67 | AK47: =AG47-AH47 -> 0 | AL47: =AI47-AJ47 -> 0 | AM47: =AG47-AG46 -> 331.77 | AN47: =AH47-AH46 -> 331.77 | AO47: =AJ47-AJ46 -> 323.66 | AP47: =AN47-AM47 -> 0 | AQ47: =AO47-AN47 -> -8.11 | AR47: =K47-D47 -> -313.65 | AS47: =AI47-AG47 -> -27.57 | AT47: =AJ47-AH47 -> -27.57 | AU47: =ABS(AR47/K47) -> 0.14082705 | AV47: =ABS(AS47/AI47) -> 0.069679278 | AW47: =ABS(AR47/AVERAGE(K47,D47)) -> 0.13156322 | AX47: =ABS((AG47-AH47)/AVERAGE(AG47,AH47)) -> 0 | AZ47: Real | BD47: Virtual | BH47: Total | BL47: Nert | BP47: =ABS((AR48-AS48)/((ABS(AR48)+ABS(AS48))/2))/10 -> 0.2 | BT47: =19/30 -> 0.63333333 | BU47: =BT47*1000 -> 633.33333 | BW47: =Health!N58 -> 183.84
B48: 45261 | C48: =SUM(Data!C398:C400) -> 3130.18 | D48: =Data!Q406 -> 1620 | E48: =Data!Q402 -> 332.98 | F48: =Data!Q403 -> 193.71 | G48: =Data!Q404 -> 345 | H48: =Data!Q405+Data!C401 -> 748.31 | K48: =Data!U406 -> 1597.87 | L48: =Data!U402 -> 202.9 | M48: =Data!U404 -> 200 | N48: =Data!U403 -> 248.87 | O48: =Data!AD404 -> 292.73 | P48: =Data!AD405 -> 653.37 | Q48: =Data!U405 -> 946.1 | R48: =K47-K48+C48 -> 3759.51 | S48: 160 | T48: 350 | U48: 0 | V48: 150 | Z48: =Data!F398 -> 146.61 | AA48: =Data!F397 -> 400.14 | AB48: =Data!I398 -> 315 | AC48: =SUM(Data!I397:I405)-Data!I398 -> 1467.5 | AD48: =SUM(Data!F397:F405) -> 1986.66 | AE48: =SUM(Data!I397:I405) -> 1782.5 | AF48: =AD48+AE48 -> 3769.16 | AG48: =C48-AF48 -> -638.98 | AH48: =D48-D47 -> -920.85 | AI48: =C48-R48 -> -629.33 | AJ48: =K48-K47 -> -629.33 | AK48: =AG48-AH48 -> 281.87 | AL48: =AI48-AJ48 -> 0 | AM48: =AG48-AG47 -> -270.88 | AN48: =AH48-AH47 -> -552.75 | AO48: =AJ48-AJ47 -> -233.66 | AP48: =AN48-AM48 -> -281.87 | AQ48: =AO48-AN48 -> 319.09 | AR48: =K48-D48 -> -22.13 | AS48: =AI48-AG48 -> 9.65 | AT48: =AJ48-AH48 -> 291.52 | AU48: =ABS(AR48/K48) -> 0.013849687 | AV48: =ABS(AS48/AI48) -> 0.015333768 | AW48: =ABS(AR48/AVERAGE(K48,D48)) -> 0.01375444 | AX48: =ABS((AG48-AH48)/AVERAGE(AG48,AH48)) -> 0.36141118 | AZ48: 0 | BA48: 0 | BB48: 0 | BC48: 0 | BD48: 0 | BE48: 0 | BF48: 0 | BG48: 0 | BH48: 0 | BI48: 0 | BJ48: 0 | BK48: 0 | BL48: 0 | BM48: 0 | BP48: =ABS((AR49-AS49)/((ABS(AR49)+ABS(AS49))/2))/10 -> 0.2 | BT48: =17/30 -> 0.56666667 | BU48: =BT48*1000 -> 566.66667 | BW48: =Health!N59 -> 188.8
B49: 45292 | C49: =SUM((OFFSET(Data!$C$410,17*(ROW(Data!Y434)-434),0)):(OFFSET(Data!$C$419,17*(ROW(Data!Y434)-434),0))) -> 2788.91 | D49: =(OFFSET(Data!$P$409,17*(ROW(Data!Y434)-434),0)) -> 1881.8473 | E49: =(OFFSET(Data!$P$412,17*(ROW(Data!Y434)-434),0)) -> 1016.61 | F49: =(OFFSET(Data!$P$418,17*(ROW(Data!Y434)-434),0)) -> 3.88 | G49: =(OFFSET(Data!$P$415,17*(ROW(Data!Y434)-434),0)) -> 145 | H49: =(OFFSET(Data!$P$421,17*(ROW(Data!Y434)-434),0)) -> 716.3573 | K49: =(OFFSET(Data!$Q$409,17*(ROW(Data!Y434)-434),0)) -> 1881.8473 | L49: =Data!Q412 -> 1014.61 | M49: =Data!Q415 -> 147 | N49: =Data!Q418 -> 3.88 | O49: =Data!U410 -> 137.8773 | P49: =Data!S410 -> 578.48 | Q49: =Data!Q421 -> 716.3573 | R49: =K48-K49+C49 -> 2504.9327 | S49: 150 | T49: 400 | U49: 0 | V49: 200 | Z49: =(OFFSET(Data!$F$412,17*(ROW(Data!Y434)-434),0)) -> 115.4 | AA49: =(OFFSET(Data!$F$411,17*(ROW(Data!Y434)-434),0)) -> 170.99 | AB49: =Data!I415 -> 232 | AC49: =SUM((OFFSET(Data!$I$410,17*(ROW(Data!Y434)-434),0)):(OFFSET(Data!$I$423,17*(ROW(Data!Y434)-434),0))) -> 884.59 | AD49: =SUM((OFFSET(Data!$F$410,17*(ROW(Data!Y434)-434),0)):(OFFSET(Data!$F$423,17*(ROW(Data!Y434)-434),0))) -> 1654.99 | AE49: =SUM(Data!I410:I423) -> 884.59 | AF49: =AD49+AE49 -> 2539.58 | AG49: =C49-AF49 -> 249.33 | AH49: =D49-D48 -> 261.8473 | AI49: =C49-R49 -> 283.9773 | AJ49: =K49-K48 -> 283.9773 | AK49: =AG49-AH49 -> -12.517304 | AL49: =AI49-AJ49 -> 0 | AM49: =AG49-AG48 -> 888.31 | AN49: =AH49-AH48 -> 1182.6973 | AO49: =AJ49-AJ48 -> 913.3073 | AP49: =AN49-AM49 -> 294.3873 | AQ49: =AO49-AN49 -> -269.39 | AR49: =K49-D49 -> 2.5011104e-12 | AS49: =AI49-AG49 -> 34.647304 | AT49: =AJ49-AH49 -> 22.13 | AU49: =ABS(AR49/K49) -> 1.3290719e-15 | AV49: =ABS(AS49/AI49) -> 0.1220073 | AW49: =ABS(AR49/AVERAGE(K49,D49)) -> 1.3290719e-15 | AX49: =ABS((AG49-AH49)/AVERAGE(AG49,AH49)) -> 0.048974414 | AZ49: =Data!S421 -> 40.13 | BA49: =Data!T421 -> 0.08654489 | BB49: =Data!U421 -> 59.426575 | BC49: =Data!V421 -> 0.17102481 | BD49: =Data!S422 -> -66.86 | BE49: =Data!T422 -> -0.1036043 | BF49: =Data!U422 -> 28.90073 | BG49: =Data!V422 -> 0.2652013 | BH49: =Data!S423 -> -26.73 | BI49: =Data!T423 -> -0.024102143 | BJ49: =Data!U423 -> 88.327304 | BK49: =Data!V423 -> 0.19350927 | BL49: =Data!W423 -> 61.597304 | BM49: =Data!X423 -> 0.039347232 | BP49: =ABS((AR50-AS50)/((ABS(AR50)+ABS(AS50))/2))/10 -> 1.9245817e-14 | BT49: =23/31 -> 0.74193548 | BU49: =BT49*1000 -> 741.93548 | BW49: =Health!N60 -> 186.53333
B50: 45323 | C50: =SUM((OFFSET(Data!$C$410,17*(ROW(Data!Y435)-434),0)):(OFFSET(Data!$C$423,17*(ROW(Data!Y435)-434),0))) -> 2526.49 | D50: =(OFFSET(Data!$P$409,17*(ROW(Data!Y435)-434),0)) -> 1434.2373 | E50: =(OFFSET(Data!$P$412,17*(ROW(Data!Y435)-434),0)) -> 578.75 | F50: =(OFFSET(Data!$P$418,17*(ROW(Data!Y435)-434),0)) -> 3.88 | G50: =(OFFSET(Data!$P$415,17*(ROW(Data!Y435)-434),0)) -> 145 | H50: =(OFFSET(Data!$P$421,17*(ROW(Data!Y435)-434),0)) -> 706.6073 | K50: =(OFFSET(Data!$Q$409,17*(ROW(Data!Y435)-434),0)) -> 1447.2329 | L50: =(OFFSET(Data!$Q$412,17*(ROW(Data!Y435)-434),0)) -> 797.37 | M50: =(OFFSET(Data!$Q$415,17*(ROW(Data!Y435)-434),0)) -> 147 | N50: =(OFFSET(Data!$Q$418,17*(ROW(Data!Y435)-434),0)) -> 3.88 | O50: =(OFFSET(Data!$U$410,17*(ROW(Data!Y435)-434),0)) -> 54.34291 | P50: =(OFFSET(Data!$S$410,17*(ROW(Data!Y435)-434),0)) -> 444.64 | Q50: =(OFFSET(Data!$Q$421,17*(ROW(Data!Y435)-434),0)) -> 498.98291 | R50: =K49-K50+C50 -> 2961.1044 | S50: 150 | T50: 400 | U50: 0 | V50: 200 | Z50: =(OFFSET(Data!$F$412,17*(ROW(Data!Y435)-434),0)) -> 119.51 | AA50: =(OFFSET(Data!$F$411,17*(ROW(Data!Y435)-434),0)) -> 131.58 | AB50: =Data!I432 -> 295 | AC50: =AE50-AB50 -> 1063.01 | AD50: =SUM((OFFSET(Data!$F$410,17*(ROW(Data!Y435)-434),0)):(OFFSET(Data!$F$423,17*(ROW(Data!Y435)-434),0))) -> 1616.09 | AE50: =SUM((OFFSET(Data!$I$410,17*(ROW(Data!Y435)-434),0)):(OFFSET(Data!$I$423,17*(ROW(Data!Y435)-434),0))) -> 1358.01 | AF50: =AD50+AE50 -> 2974.1 | AG50: =C50-AF50 -> -447.61 | AH50: =D50-D49 -> -447.61 | AI50: =C50-R50 -> -434.61439 | AJ50: =K50-K49 -> -434.61439 | AK50: =AG50-AH50 -> 0 | AL50: =AI50-AJ50 -> 0 | AM50: =AG50-AG49 -> -696.94 | AN50: =AH50-AH49 -> -709.4573 | AO50: =AJ50-AJ49 -> -718.5917 | AP50: =AN50-AM50 -> -12.517304 | AQ50: =AO50-AN50 -> -9.1343948 | AR50: =K50-D50 -> 12.995605 | AS50: =AI50-AG50 -> 12.995605 | AT50: =AJ50-AH50 -> 12.995605 | AU50: =ABS(AR50/K50) -> 0.0089796225 | AV50: =ABS(AS50/AI50) -> 0.029901461 | AW50: =ABS(AR50/AVERAGE(K50,D50)) -> 0.0090201212 | AX50: =ABS((AG50-AH50)/AVERAGE(AG50,AH50)) -> 5.0797273e-16 | AZ50: =Data!S438 -> 81.89 | BA50: =Data!T438 -> 0.093731043 | BB50: =Data!U438 -> 77.61704 | BC50: =Data!V438 -> 0.17379817 | BD50: =Data!S439 -> -75.72 | BE50: =Data!T439 -> -0.14551464 | BF50: =Data!U439 -> 44.48587 | BG50: =Data!V439 -> 4.5131063 | BH50: =Data!S440 -> 6.17 | BI50: =Data!T440 -> 0.0044260167 | BJ50: =Data!U440 -> 122.10291 | BK50: =Data!V440 -> 0.26750555 | BL50: =Data!W440 -> 128.27291 | BM50: =Data!X440 -> 0.069318723 | BP50: =ABS((AR51-AS51)/((ABS(AR51)+ABS(AS51))/2))/10 -> 0.2 | BT50: =15/29 -> 0.51724138 | BU50: =BT50*1000 -> 517.24138 | BW50: =Health!N61 -> 184
B51: 45352 | C51: =SUM((OFFSET(Data!$C$410,17*(ROW(Data!Y436)-434),0)):(OFFSET(Data!$C$423,17*(ROW(Data!Y436)-434),0))) -> 2562.49 | D51: =(OFFSET(Data!$P$409,17*(ROW(Data!Y436)-434),0)) -> 1425.8873 | E51: =(OFFSET(Data!$P$412,17*(ROW(Data!Y436)-434),0)) -> 470.4 | F51: =(OFFSET(Data!$P$418,17*(ROW(Data!Y436)-434),0)) -> 103.88 | G51: =(OFFSET(Data!$P$415,17*(ROW(Data!Y436)-434),0)) -> 145 | H51: =(OFFSET(Data!$P$421,17*(ROW(Data!Y436)-434),0)) -> 706.6073 | K51: =(OFFSET(Data!$Q$409,17*(ROW(Data!Y436)-434),0)) -> 1432.4183 | L51: =(OFFSET(Data!$Q$412,17*(ROW(Data!Y436)-434),0)) -> 706.02 | M51: =(OFFSET(Data!$Q$415,17*(ROW(Data!Y436)-434),0)) -> 147 | N51: =(OFFSET(Data!$Q$418,17*(ROW(Data!Y436)-434),0)) -> 103.9 | O51: =(OFFSET(Data!$U$410,17*(ROW(Data!Y436)-434),0)) -> 73.698303 | P51: =(OFFSET(Data!$S$410,17*(ROW(Data!Y436)-434),0)) -> 401.8 | Q51: =(OFFSET(Data!$Q$421,17*(ROW(Data!Y436)-434),0)) -> 475.4983 | R51: =K50-K51+C51 -> 2577.3046 | S51: 150 | T51: 400 | U51: 0 | V51: 200 | Z51: =(OFFSET(Data!$F$412,17*(ROW(Data!Y436)-434),0)) -> 145.36 | AA51: =(OFFSET(Data!$F$411,17*(ROW(Data!Y436)-434),0)) -> 56.28 | AB51: =Data!I453 -> 300 | AC51: =AE51-AB51 -> 785.2 | AD51: =SUM((OFFSET(Data!$F$410,17*(ROW(Data!Y436)-434),0)):(OFFSET(Data!$F$423,17*(ROW(Data!Y436)-434),0))) -> 1485.64 | AE51: =SUM((OFFSET(Data!$I$410,17*(ROW(Data!Y436)-434),0)):(OFFSET(Data!$I$423,17*(ROW(Data!Y436)-434),0))) -> 1085.2 | AF51: =AD51+AE51 -> 2570.84 | AG51: =C51-AF51 -> -8.35 | AH51: =D51-D50 -> -8.35 | AI51: =C51-R51 -> -14.814607 | AJ51: =K51-K50 -> -14.814607 | AK51: =AG51-AH51 -> 0 | AL51: =AI51-AJ51 -> 0 | AM51: =AG51-AG50 -> 439.26 | AN51: =AH51-AH50 -> 439.26 | AO51: =AJ51-AJ50 -> 419.79979 | AP51: =AN51-AM51 -> 0 | AQ51: =AO51-AN51 -> -19.460212 | AR51: =K51-D51 -> 6.5309983 | AS51: =AI51-AG51 -> -6.4646069 | AT51: =AJ51-AH51 -> -6.4646069 | AU51: =ABS(AR51/K51) -> 0.0045594212 | AV51: =ABS(AS51/AI51) -> 0.43636709 | AW51: =ABS(AR51/AVERAGE(K51,D51)) -> 0.0045698391 | AX51: =ABS((AG51-AH51)/AVERAGE(AG51,AH51)) -> 0 | AZ51: =Data!S455 -> 101.31 | BA51: =Data!T455 -> 0.088582471 | BB51: =Data!U455 -> 57.593508 | BC51: =Data!V455 -> 0.11061922 | BD51: =Data!S456 -> -78.55 | BE51: =Data!T456 -> -0.1635266 | BF51: =Data!U456 -> 70.124795 | BG51: =Data!V456 -> 19.623518 | BH51: =Data!S457 -> 22.76 | BI51: =Data!T457 -> 0.014014519 | BJ51: =Data!U457 -> 127.7183 | BK51: =Data!V457 -> 0.24363493 | BL51: =Data!W457 -> 150.4783 | BM51: =Data!X457 -> 0.070046923 | BP51: =ABS((AR52-AS52)/((ABS(AR52)+ABS(AS52))/2))/10 -> 0.017781548 | BT51: =12/30 -> 0.4 | BU51: =BT51*1000 -> 400 | BW51: =Health!N62 -> 184.4
B52: 45383 | C52: =SUM((OFFSET(Data!$C$410,17*(ROW(Data!Y437)-434),0)):(OFFSET(Data!$C$423,17*(ROW(Data!Y437)-434),0))) -> 2938.48 | D52: =(OFFSET(Data!$P$409,17*(ROW(Data!Y437)-434),0)) -> 1690.1373 | E52: =(OFFSET(Data!$P$412,17*(ROW(Data!Y437)-434),0)) -> 709.95 | F52: =(OFFSET(Data!$P$418,17*(ROW(Data!Y437)-434),0)) -> 103.88 | G52: =(OFFSET(Data!$P$415,17*(ROW(Data!Y437)-434),0)) -> 85 | H52: =(OFFSET(Data!$P$421,17*(ROW(Data!Y437)-434),0)) -> 791.3073 | K52: =(OFFSET(Data!$Q$409,17*(ROW(Data!Y437)-434),0)) -> 1656.6737 | L52: =(OFFSET(Data!$Q$412,17*(ROW(Data!Y437)-434),0)) -> 976.6 | M52: =(OFFSET(Data!$Q$415,17*(ROW(Data!Y437)-434),0)) -> 89 | N52: =(OFFSET(Data!$Q$418,17*(ROW(Data!Y437)-434),0)) -> 103.91 | O52: =(OFFSET(Data!$U$410,17*(ROW(Data!Y437)-434),0)) -> 62.643727 | P52: =(OFFSET(Data!$S$410,17*(ROW(Data!Y437)-434),0)) -> 424.52 | Q52: =(OFFSET(Data!$Q$421,17*(ROW(Data!Y437)-434),0)) -> 487.16373 | R52: =K51-K52+C52 -> 2714.2246 | S52: 150 | T52: 400 | U52: 0 | V52: 200 | W52: =SUM((OFFSET(Data!$F$410,17*(ROW(Data!Y437)-434),0)):(OFFSET(Data!$F$423,17*(ROW(Data!Y437)-434),0))) -> 1469.96 | X52: =SUM((OFFSET(Data!$I$410,17*(ROW(Data!Y437)-434),0)):(OFFSET(Data!$I$423,17*(ROW(Data!Y437)-434),0))) -> 1204.27 | Y52: =W52+X52 -> 2674.23 | Z52: =(OFFSET(Data!$F$412,17*(ROW(Data!Y437)-434),0)) -> 138.9 | AA52: =(OFFSET(Data!$F$411,17*(ROW(Data!Y437)-434),0)) -> 107.05 | AB52: =Data!I467 -> 321 | AC52: =AE52-AB52 -> 883.27 | AD52: =SUM((OFFSET(Data!$F$410,17*(ROW(Data!Y437)-434),0)):(OFFSET(Data!$F$423,17*(ROW(Data!Y437)-434),0))) -> 1469.96 | AE52: =SUM((OFFSET(Data!$I$410,17*(ROW(Data!Y437)-434),0)):(OFFSET(Data!$I$423,17*(ROW(Data!Y437)-434),0))) -> 1204.27 | AF52: =AD52+AE52 -> 2674.23 | AG52: =C52-AF52 -> 264.25 | AH52: =D52-D51 -> 264.25 | AI52: =C52-R52 -> 224.25542 | AJ52: =K52-K51 -> 224.25542 | AK52: =AG52-AH52 -> 0 | AL52: =AI52-AJ52 -> 2.2737368e-13 | AM52: =AG52-AG51 -> 272.6 | AN52: =AH52-AH51 -> 272.6 | AO52: =AJ52-AJ51 -> 239.07003 | AP52: =AN52-AM52 -> 0 | AQ52: =AO52-AN52 -> -33.529969 | AR52: =K52-D52 -> -33.463577 | AS52: =AI52-AG52 -> -39.994575 | AT52: =AJ52-AH52 -> -39.994575 | AU52: =ABS(AR52/K52) -> 0.020199256 | AV52: =ABS(AS52/AI52) -> 0.17834385 | AW52: =ABS(AR52/AVERAGE(K52,D52)) -> 0.019997291 | AX52: =ABS((AG52-AH52)/AVERAGE(AG52,AH52)) -> 0 | AZ52: =Data!S472 -> 110.79 | BA52: =Data!T472 -> 0.09297193 | BB52: =Data!U472 -> 57.593508 | BC52: =Data!V472 -> 0.11061922 | BD52: =Data!S473 -> -127.86 | BE52: =Data!T473 -> -0.23147109 | BF52: =Data!U473 -> 59.07022 | BG52: =Data!V473 -> 16.530038 | BH52: =Data!S474 -> -17.07 | BI52: =Data!T474 -> -0.0097876757 | BJ52: =Data!U474 -> 116.66373 | BK52: =Data!V474 -> 0.22254727 | BL52: =Data!W474 -> 99.593727 | BM52: =Data!X474 -> 0.043907738 | BP52: =ABS((AR53-AS53)/((ABS(AR53)+ABS(AS53))/2))/10 -> 0.2 | BT52: =11/30 -> 0.36666667 | BU52: =BT52*1000 -> 366.66667 | BW52: =Health!N63 -> 181.35
B53: 45413 | C53: =SUM((OFFSET(Data!$C$410,17*(ROW(Data!Y438)-434),0)):(OFFSET(Data!$C$423,17*(ROW(Data!Y438)-434),0))) -> 2554.25 | D53: =(OFFSET(Data!$P$409,17*(ROW(Data!Y438)-434),0)) -> 1636.0073 | E53: =(OFFSET(Data!$P$412,17*(ROW(Data!Y438)-434),0)) -> 648.14 | F53: =(OFFSET(Data!$P$418,17*(ROW(Data!Y438)-434),0)) -> 103.88 | G53: =(OFFSET(Data!$P$415,17*(ROW(Data!Y438)-434),0)) -> 85 | H53: =(OFFSET(Data!$P$421,17*(ROW(Data!Y438)-434),0)) -> 798.9873 | K53: =(OFFSET(Data!$Q$409,17*(ROW(Data!Y438)-434),0)) -> 1634.7778 | L53: =(OFFSET(Data!$Q$412,17*(ROW(Data!Y438)-434),0)) -> 1014.75 | M53: =(OFFSET(Data!$Q$415,17*(ROW(Data!Y438)-434),0)) -> 89 | N53: =(OFFSET(Data!$Q$418,17*(ROW(Data!Y438)-434),0)) -> 103.94 | O53: =(OFFSET(Data!$U$410,17*(ROW(Data!Y438)-434),0)) -> 70.687754 | P53: =(OFFSET(Data!$S$410,17*(ROW(Data!Y438)-434),0)) -> 356.4 | Q53: =(OFFSET(Data!$Q$421,17*(ROW(Data!Y438)-434),0)) -> 427.08775 | R53: =K52-K53+C53 -> 2576.146 | S53: 150 | T53: 400 | U53: 0 | V53: 200 | W53: =SUM((OFFSET(Data!$F$410,17*(ROW(Data!Y438)-434),0)):(OFFSET(Data!$F$423,17*(ROW(Data!Y438)-434),0))) -> 1428.41 | X53: =SUM((OFFSET(Data!$I$410,17*(ROW(Data!Y438)-434),0)):(OFFSET(Data!$I$423,17*(ROW(Data!Y438)-434),0))) -> 1179.97 | Y53: =W53+X53 -> 2608.38 | Z53: =(OFFSET(Data!$F$412,17*(ROW(Data!Y438)-434),0)) -> 161 | AA53: =(OFFSET(Data!$F$411,17*(ROW(Data!Y438)-434),0)) -> 187.41 | AB53: =Data!I484 -> 440 | AC53: =AE53-AB53 -> 739.97 | AD53: =SUM((OFFSET(Data!$F$410,17*(ROW(Data!Y438)-434),0)):(OFFSET(Data!$F$423,17*(ROW(Data!Y438)-434),0))) -> 1428.41 | AE53: =SUM((OFFSET(Data!$I$410,17*(ROW(Data!Y438)-434),0)):(OFFSET(Data!$I$423,17*(ROW(Data!Y438)-434),0))) -> 1179.97 | AF53: =AD53+AE53 -> 2608.38 | AG53: =C53-AF53 -> -54.13 | AH53: =D53-D52 -> -54.13 | AI53: =C53-R53 -> -21.895973 | AJ53: =K53-K52 -> -21.895973 | AK53: =AG53-AH53 -> -4.5474735e-13 | AL53: =AI53-AJ53 -> 0 | AM53: =AG53-AG52 -> -318.38 | AN53: =AH53-AH52 -> -318.38 | AO53: =AJ53-AJ52 -> -246.1514 | AP53: =AN53-AM53 -> 4.5474735e-13 | AQ53: =AO53-AN53 -> 72.228602 | AR53: =K53-D53 -> -1.22955 | AS53: =AI53-AG53 -> 32.234027 | AT53: =AJ53-AH53 -> 32.234027 | AU53: =ABS(AR53/K53) -> 0.0007521206 | AV53: =ABS(AS53/AI53) -> 1.4721441 | AW53: =ABS(AR53/AVERAGE(K53,D53)) -> 0.00075183786 | AX53: =ABS((AG53-AH53)/AVERAGE(AG53,AH53)) -> 8.4010226e-15 | AZ53: =Data!S489 -> 114.53 | BA53: =Data!T489 -> 0.088799467 | BB53: =Data!U489 -> 56.564776 | BC53: =Data!V489 -> 0.10643376 | BD53: =Data!S490 -> -107.87 | BE53: =Data!T490 -> -0.23234325 | BF53: =Data!U490 -> 67.922979 | BG53: =Data!V490 -> 24.567263 | BH53: =Data!S491 -> 6.66 | BI53: =Data!T491 -> 0.0037969704 | BJ53: =Data!U491 -> 124.48775 | BK53: =Data!V491 -> 0.23302713 | BL53: =Data!W491 -> 131.14775 | BM53: =Data!X491 -> 0.05731356 | BP53: =ABS((AR54-AS54)/((ABS(AR54)+ABS(AS54))/2))/10 -> 0.0037349988 | BT53: =8/31 -> 0.25806452 | BU53: =BT53*1000 -> 258.06452 | BW53: =Health!N64 -> 180.05
B54: 45444 | C54: =SUM((OFFSET(Data!$C$410,17*(ROW(Data!Y439)-434),0)):(OFFSET(Data!$C$423,17*(ROW(Data!Y439)-434),0))) -> 3573.27 | D54: =(OFFSET(Data!$P$409,17*(ROW(Data!Y439)-434),0)) -> 2355.3473 | E54: =(OFFSET(Data!$P$412,17*(ROW(Data!Y439)-434),0)) -> 126.32 | F54: =(OFFSET(Data!$P$418,17*(ROW(Data!Y439)-434),0)) -> 503.88 | G54: =(OFFSET(Data!$P$415,17*(ROW(Data!Y439)-434),0)) -> 585 | H54: =(OFFSET(Data!$P$421,17*(ROW(Data!Y439)-434),0)) -> 1140.1473 | K54: =(OFFSET(Data!$Q$409,17*(ROW(Data!Y439)-434),0)) -> 2387.6522 | L54: =(OFFSET(Data!$Q$412,17*(ROW(Data!Y439)-434),0)) -> 559.7 | M54: =(OFFSET(Data!$Q$415,17*(ROW(Data!Y439)-434),0)) -> 589 | N54: =(OFFSET(Data!$Q$418,17*(ROW(Data!Y439)-434),0)) -> 503.98 | O54: =(OFFSET(Data!$U$410,17*(ROW(Data!Y439)-434),0)) -> 73.582219 | P54: =(OFFSET(Data!$S$410,17*(ROW(Data!Y439)-434),0)) -> 661.39 | Q54: =(OFFSET(Data!$Q$421,17*(ROW(Data!Y439)-434),0)) -> 734.97222 | R54: =K53-K54+C54 -> 2820.3955 | S54: 150 | T54: 400 | U54: 0 | V54: 200 | W54: =SUM((OFFSET(Data!$F$410,17*(ROW(Data!Y439)-434),0)):(OFFSET(Data!$F$423,17*(ROW(Data!Y439)-434),0))) -> 1791.26 | X54: =SUM((OFFSET(Data!$I$410,17*(ROW(Data!Y439)-434),0)):(OFFSET(Data!$I$423,17*(ROW(Data!Y439)-434),0))) -> 1062.67 | Y54: =W54+X54 -> 2853.93 | Z54: =(OFFSET(Data!$F$412,17*(ROW(Data!Y439)-434),0)) -> 131.89 | AA54: =(OFFSET(Data!$F$411,17*(ROW(Data!Y439)-434),0)) -> 144.37 | AB54: =Data!I501 -> 425 | AC54: =AE54-AB54 -> 637.67 | AD54: =SUM((OFFSET(Data!$F$410,17*(ROW(Data!Y439)-434),0)):(OFFSET(Data!$F$423,17*(ROW(Data!Y439)-434),0))) -> 1791.26 | AE54: =SUM((OFFSET(Data!$I$410,17*(ROW(Data!Y439)-434),0)):(OFFSET(Data!$I$423,17*(ROW(Data!Y439)-434),0))) -> 1062.67 | AF54: =AD54+AE54 -> 2853.93 | AG54: =C54-AF54 -> 719.34 | AH54: =D54-D53 -> 719.34 | AI54: =C54-R54 -> 752.87446 | AJ54: =K54-K53 -> 752.87446 | AK54: =AG54-AH54 -> 0 | AL54: =AI54-AJ54 -> 0 | AM54: =AG54-AG53 -> 773.47 | AN54: =AH54-AH53 -> 773.47 | AO54: =AJ54-AJ53 -> 774.77044 | AP54: =AN54-AM54 -> 0 | AQ54: =AO54-AN54 -> 1.3004376 | AR54: =K54-D54 -> 32.304915 | AS54: =AI54-AG54 -> 33.534465 | AT54: =AJ54-AH54 -> 33.534465 | AU54: =ABS(AR54/K54) -> 0.013529992 | AV54: =ABS(AS54/AI54) -> 0.044541907 | AW54: =ABS(AR54/AVERAGE(K54,D54)) -> 0.013622145 | AX54: =ABS((AG54-AH54)/AVERAGE(AG54,AH54)) -> 6.3217303e-16 | AZ54: =Data!S506 -> 130.29 | BA54: =Data!T506 -> 0.088149331 | BB54: =Data!U506 -> 47.242186 | BC54: =Data!V506 -> 0.078555277 | BD54: =Data!S507 -> -135.05 | BE54: =Data!T507 -> -0.16956707 | BF54: =Data!U507 -> 70.750033 | BG54: =Data!V507 -> 24.980714 | BH54: =Data!S508 -> -4.76 | BI54: =Data!T508 -> -0.0020927676 | BJ54: =Data!U508 -> 117.99222 | BK54: =Data!V508 -> 0.19528023 | BL54: =Data!W508 -> 113.23222 | BM54: =Data!X508 -> 0.039334225 | BP54: =ABS((AR55-AS55)/((ABS(AR55)+ABS(AS55))/2))/10 -> 0.076253013 | BT54: =9/30 -> 0.3 | BU54: =BT54*1000 -> 300 | BW54: =Health!N65 -> 178.36
B55: 45474 | C55: =SUM((OFFSET(Data!$C$410,17*(ROW(Data!Y440)-434),0)):(OFFSET(Data!$C$423,17*(ROW(Data!Y440)-434),0))) -> 3579.38 | D55: =(OFFSET(Data!$P$409,17*(ROW(Data!Y440)-434),0)) -> 3121.7073 | E55: =(OFFSET(Data!$P$412,17*(ROW(Data!Y440)-434),0)) -> 1185.72 | F55: =(OFFSET(Data!$P$418,17*(ROW(Data!Y440)-434),0)) -> 513.88 | G55: =(OFFSET(Data!$P$415,17*(ROW(Data!Y440)-434),0)) -> 85 | H55: =(OFFSET(Data!$P$421,17*(ROW(Data!Y440)-434),0)) -> 1337.1073 | K55: =(OFFSET(Data!$Q$409,17*(ROW(Data!Y440)-434),0)) -> 3095.4943 | L55: =(OFFSET(Data!$Q$412,17*(ROW(Data!Y440)-434),0)) -> 1592.48 | M55: =(OFFSET(Data!$Q$415,17*(ROW(Data!Y440)-434),0)) -> 94 | N55: =(OFFSET(Data!$Q$418,17*(ROW(Data!Y440)-434),0)) -> 514.03 | O55: =(OFFSET(Data!$U$410,17*(ROW(Data!Y440)-434),0)) -> 98.224335 | P55: =(OFFSET(Data!$S$410,17*(ROW(Data!Y440)-434),0)) -> 796.76 | Q55: =(OFFSET(Data!$Q$421,17*(ROW(Data!Y440)-434),0)) -> 894.98433 | R55: =K54-K55+C55 -> 2871.5379 | S55: 150 | T55: 400 | U55: 0 | V55: 200 | W55: =SUM((OFFSET(Data!$F$410,17*(ROW(Data!Y440)-434),0)):(OFFSET(Data!$F$423,17*(ROW(Data!Y440)-434),0))) -> 1660.39 | X55: =SUM((OFFSET(Data!$I$410,17*(ROW(Data!Y440)-434),0)):(OFFSET(Data!$I$423,17*(ROW(Data!Y440)-434),0))) -> 1152.63 | Y55: =W55+X55 -> 2813.02 | Z55: =(OFFSET(Data!$F$412,17*(ROW(Data!Y440)-434),0)) -> 164.39 | AA55: =(OFFSET(Data!$F$411,17*(ROW(Data!Y440)-434),0)) -> 211 | AB55: =Data!I517 -> 536 | AC55: =AE55-AB55 -> 616.63 | AD55: =SUM((OFFSET(Data!$F$410,17*(ROW(Data!Y440)-434),0)):(OFFSET(Data!$F$423,17*(ROW(Data!Y440)-434),0))) -> 1660.39 | AE55: =SUM((OFFSET(Data!$I$410,17*(ROW(Data!Y440)-434),0)):(OFFSET(Data!$I$423,17*(ROW(Data!Y440)-434),0))) -> 1152.63 | AF55: =AD55+AE55 -> 2813.02 | AG55: =C55-AF55 -> 766.36 | AH55: =D55-D54 -> 766.36 | AI55: =C55-R55 -> 707.84212 | AJ55: =K55-K54 -> 707.84212 | AK55: =AG55-AH55 -> 0 | AL55: =AI55-AJ55 -> 0 | AM55: =AG55-AG54 -> 47.02 | AN55: =AH55-AH54 -> 47.02 | AO55: =AJ55-AJ54 -> -45.032349 | AP55: =AN55-AM55 -> -4.5474735e-13 | AQ55: =AO55-AN55 -> -92.052349 | AR55: =K55-D55 -> -26.21297 | AS55: =AI55-AG55 -> -58.517884 | AT55: =AJ55-AH55 -> -58.517884 | AU55: =ABS(AR55/K55) -> 0.0084681046 | AV55: =ABS(AS55/AI55) -> 0.082670815 | AW55: =ABS(AR55/AVERAGE(K55,D55)) -> 0.0084324014 | AX55: =ABS((AG55-AH55)/AVERAGE(AG55,AH55)) -> 0 | AZ55: =Data!S523 -> 153.21 | BA55: =Data!T523 -> 0.0959007 | BB55: =Data!U523 -> 38.397858 | BC55: =Data!V523 -> 0.062923363 | BD55: =Data!S524 -> -168.82 | BE55: =Data!T524 -> -0.17483792 | BF55: =Data!U524 -> 79.236476 | BG55: =Data!V524 -> 4.1730075 | BH55: =Data!S525 -> -15.61 | BI55: =Data!T525 -> -0.006090115 | BJ55: =Data!U525 -> 117.63433 | BK55: =Data!V525 -> 0.18695263 | BL55: =Data!W525 -> 102.02433 | BM55: =Data!X525 -> 0.031958606 | BP55: =ABS((AR56-AS56)/((ABS(AR56)+ABS(AS56))/2))/10 -> 0.036821826 | BT55: =11/31 -> 0.35483871 | BU55: =BT55*1000 -> 354.83871 | BW55: =Health!N66 -> 175.45
B56: 45505 | C56: =SUM((OFFSET(Data!$C$410,17*(ROW(Data!Y441)-434),0)):(OFFSET(Data!$C$423,17*(ROW(Data!Y441)-434),0))) -> 2526.5 | D56: =(OFFSET(Data!$P$409,17*(ROW(Data!Y441)-434),0)) -> 3071.1173 | E56: =(OFFSET(Data!$P$412,17*(ROW(Data!Y441)-434),0)) -> 737.96 | F56: =(OFFSET(Data!$P$418,17*(ROW(Data!Y441)-434),0)) -> 513.88 | G56: =(OFFSET(Data!$P$415,17*(ROW(Data!Y441)-434),0)) -> 85 | H56: =(OFFSET(Data!$P$421,17*(ROW(Data!Y441)-434),0)) -> 1734.2773 | K56: =(OFFSET(Data!$Q$409,17*(ROW(Data!Y441)-434),0)) -> 2986.8221 | L56: =(OFFSET(Data!$Q$412,17*(ROW(Data!Y441)-434),0)) -> 1151.33 | M56: =(OFFSET(Data!$Q$415,17*(ROW(Data!Y441)-434),0)) -> 74 | N56: =(OFFSET(Data!$Q$418,17*(ROW(Data!Y441)-434),0)) -> 514.25 | O56: =(OFFSET(Data!$U$410,17*(ROW(Data!Y441)-434),0)) -> 148.96214 | P56: =(OFFSET(Data!$S$410,17*(ROW(Data!Y441)-434),0)) -> 1098.28 | Q56: =(OFFSET(Data!$Q$421,17*(ROW(Data!Y441)-434),0)) -> 1247.2421 | R56: =K55-K56+C56 -> 2635.1722 | S56: 150 | T56: 400 | U56: 0 | V56: 200 | W56: =SUM((OFFSET(Data!$F$410,17*(ROW(Data!Y441)-434),0)):(OFFSET(Data!$F$423,17*(ROW(Data!Y441)-434),0))) -> 1442.37 | X56: =SUM((OFFSET(Data!$I$410,17*(ROW(Data!Y441)-434),0)):(OFFSET(Data!$I$423,17*(ROW(Data!Y441)-434),0))) -> 1134.72 | Y56: =W56+X56 -> 2577.09 | Z56: =(OFFSET(Data!$F$412,17*(ROW(Data!Y441)-434),0)) -> 84.86 | AA56: =(OFFSET(Data!$F$411,17*(ROW(Data!Y441)-434),0)) -> 88.83 | AB56: =Data!I534 -> 360 | AC56: =AE56-AB56 -> 774.72 | AD56: =SUM((OFFSET(Data!$F$410,17*(ROW(Data!Y441)-434),0)):(OFFSET(Data!$F$423,17*(ROW(Data!Y441)-434),0))) -> 1442.37 | AE56: =SUM((OFFSET(Data!$I$410,17*(ROW(Data!Y441)-434),0)):(OFFSET(Data!$I$423,17*(ROW(Data!Y441)-434),0))) -> 1134.72 | AF56: =AD56+AE56 -> 2577.09 | AG56: =C56-AF56 -> -50.59 | AH56: =D56-D55 -> -50.59 | AI56: =C56-R56 -> -108.67219 | AJ56: =K56-K55 -> -108.67219 | AK56: =AG56-AH56 -> 0 | AL56: =AI56-AJ56 -> 0 | AM56: =AG56-AG55 -> -816.95 | AN56: =AH56-AH55 -> -816.95 | AO56: =AJ56-AJ55 -> -816.51431 | AP56: =AN56-AM56 -> 0 | AQ56: =AO56-AN56 -> 0.43569453 | AR56: =K56-D56 -> -84.29516 | AS56: =AI56-AG56 -> -58.08219 | AT56: =AJ56-AH56 -> -58.08219 | AU56: =ABS(AR56/K56) -> 0.028222357 | AV56: =ABS(AS56/AI56) -> 0.53447151 | AW56: =ABS(AR56/AVERAGE(K56,D56)) -> 0.027829648 | AX56: =ABS((AG56-AH56)/AVERAGE(AG56,AH56)) -> 0 | AZ56: =Data!S540 -> 149.23 | BA56: =Data!T540 -> 0.082815379 | BB56: =Data!U540 -> 26.557935 | BC56: =Data!V540 -> 0.042692698 | BD56: =Data!S541 -> -149.93 | BE56: =Data!T541 -> -0.12011601 | BF56: =Data!U541 -> 81.81421 | BG56: =Data!V541 -> 1.2184174 | BH56: =Data!S542 -> -0.7 | BI56: =Data!T542 -> -0.00022949541 | BJ56: =Data!U542 -> 108.37214 | BK56: =Data!V542 -> 0.15723883 | BL56: =Data!W542 -> 107.67214 | BM56: =Data!X542 -> 0.02879404 | BP56: =ABS((AR57-AS57)/((ABS(AR57)+ABS(AS57))/2))/10 -> 0.050834355 | BT56: =13/31 -> 0.41935484 | BU56: =BT56*1000 -> 419.35484 | BW56: =Health!N67 -> 173.95
B57: 45536 | C57: =SUM((OFFSET(Data!$C$410,17*(ROW(Data!Y442)-434),0)):(OFFSET(Data!$C$423,17*(ROW(Data!Y442)-434),0))) -> 2910.46 | D57: =(OFFSET(Data!$P$409,17*(ROW(Data!Y442)-434),0)) -> 2948.0073 | E57: =(OFFSET(Data!$P$412,17*(ROW(Data!Y442)-434),0)) -> 415.7 | F57: =(OFFSET(Data!$P$418,17*(ROW(Data!Y442)-434),0)) -> 513.88 | G57: =(OFFSET(Data!$P$415,17*(ROW(Data!Y442)-434),0)) -> 85 | H57: =(OFFSET(Data!$P$421,17*(ROW(Data!Y442)-434),0)) -> 1933.4273 | K57: =(OFFSET(Data!$Q$409,17*(ROW(Data!Y442)-434),0)) -> 3071.6829 | L57: =(OFFSET(Data!$Q$412,17*(ROW(Data!Y442)-434),0)) -> 937.78 | M57: =(OFFSET(Data!$Q$415,17*(ROW(Data!Y442)-434),0)) -> 74 | N57: =(OFFSET(Data!$Q$418,17*(ROW(Data!Y442)-434),0)) -> 514.4 | O57: =(OFFSET(Data!$U$410,17*(ROW(Data!Y442)-434),0)) -> 218.72294 | P57: =(OFFSET(Data!$S$410,17*(ROW(Data!Y442)-434),0)) -> 1326.78 | Q57: =(OFFSET(Data!$Q$421,17*(ROW(Data!Y442)-434),0)) -> 1545.5029 | R57: =K56-K57+C57 -> 2825.5992 | S57: 150 | T57: 400 | U57: 0 | V57: 200 | W57: =SUM((OFFSET(Data!$F$410,17*(ROW(Data!Y442)-434),0)):(OFFSET(Data!$F$423,17*(ROW(Data!Y442)-434),0))) -> 1578.48 | X57: =SUM((OFFSET(Data!$I$410,17*(ROW(Data!Y442)-434),0)):(OFFSET(Data!$I$423,17*(ROW(Data!Y442)-434),0))) -> 1455.09 | Y57: =W57+X57 -> 3033.57 | Z57: =(OFFSET(Data!$F$412,17*(ROW(Data!Y442)-434),0)) -> 128.73 | AA57: =(OFFSET(Data!$F$411,17*(ROW(Data!Y442)-434),0)) -> 141.15 | AB57: =Data!I553 -> 331 | AC57: =AE57-AB57 -> 1124.09 | AD57: =SUM((OFFSET(Data!$F$410,17*(ROW(Data!Y442)-434),0)):(OFFSET(Data!$F$423,17*(ROW(Data!Y442)-434),0))) -> 1578.48 | AE57: =SUM((OFFSET(Data!$I$410,17*(ROW(Data!Y442)-434),0)):(OFFSET(Data!$I$423,17*(ROW(Data!Y442)-434),0))) -> 1455.09 | AF57: =AD57+AE57 -> 3033.57 | AG57: =C57-AF57 -> -123.11 | AH57: =D57-D56 -> -123.11 | AI57: =C57-R57 -> 84.860791 | AJ57: =K57-K56 -> 84.860791 | AK57: =AG57-AH57 -> 0 | AL57: =AI57-AJ57 -> 0 | AM57: =AG57-AG56 -> -72.52 | AN57: =AH57-AH56 -> -72.52 | AO57: =AJ57-AJ56 -> 193.53298 | AP57: =AN57-AM57 -> 0 | AQ57: =AO57-AN57 -> 266.05298 | AR57: =K57-D57 -> 123.67563 | AS57: =AI57-AG57 -> 207.97079 | AT57: =AJ57-AH57 -> 207.97079 | AU57: =ABS(AR57/K57) -> 0.04026315 | AV57: =ABS(AS57/AI57) -> 2.4507289 | AW57: =ABS(AR57/AVERAGE(K57,D57)) -> 0.041090364 | AX57: =ABS((AG57-AH57)/AVERAGE(AG57,AH57)) -> 0 | AZ57: =Data!S557 -> 109.95 | BA57: =Data!T557 -> 0.059690554 | BB57: =Data!U557 -> 20.787058 | BC57: =Data!V557 -> 0.033108691 | BD57: =Data!S558 -> -31.39 | BE57: =Data!T558 -> -0.023111982 | BF57: =Data!U558 -> 107.34588 | BG57: =Data!V558 -> 0.96380601 | BH57: =Data!S559 -> 78.56 | BI57: =Data!T559 -> 0.024548696 | BJ57: =Data!U559 -> 128.13294 | BK57: =Data!V559 -> 0.17333532 | BL57: =Data!W559 -> 206.69294 | BM57: =Data!X559 -> 0.052468259 | BP57: =ABS((AR58-AS58)/((ABS(AR58)+ABS(AS58))/2))/10 -> 0.092977352 | BT57: =12/30 -> 0.4 | BU57: =BT57*1000 -> 400 | BW57: =Health!N68 -> 171.25
B58: 45566 | C58: =SUM((OFFSET(Data!$C$410,17*(ROW(Data!Y443)-434),0)):(OFFSET(Data!$C$423,17*(ROW(Data!Y443)-434),0))) -> 3436.62 | D58: =(OFFSET(Data!$P$409,17*(ROW(Data!Y443)-434),0)) -> 2965.7673 | E58: =(OFFSET(Data!$P$412,17*(ROW(Data!Y443)-434),0)) -> 236.08 | F58: =(OFFSET(Data!$P$418,17*(ROW(Data!Y443)-434),0)) -> 513.88 | G58: =(OFFSET(Data!$P$415,17*(ROW(Data!Y443)-434),0)) -> 85 | H58: =(OFFSET(Data!$P$421,17*(ROW(Data!Y443)-434),0)) -> 2130.8073 | K58: =(OFFSET(Data!$Q$409,17*(ROW(Data!Y443)-434),0)) -> 3160.6221 | L58: =(OFFSET(Data!$Q$412,17*(ROW(Data!Y443)-434),0)) -> 908.56 | M58: =(OFFSET(Data!$Q$415,17*(ROW(Data!Y443)-434),0)) -> 77 | N58: =(OFFSET(Data!$Q$418,17*(ROW(Data!Y443)-434),0)) -> 514.59 | O58: =(OFFSET(Data!$U$410,17*(ROW(Data!Y443)-434),0)) -> 293.24206 | P58: =(OFFSET(Data!$S$410,17*(ROW(Data!Y443)-434),0)) -> 1367.23 | Q58: =(OFFSET(Data!$Q$421,17*(ROW(Data!Y443)-434),0)) -> 1660.4721 | R58: =K57-K58+C58 -> 3347.6809 | S58: 150 | T58: 400 | U58: 0 | V58: 200 | W58: =SUM((OFFSET(Data!$F$410,17*(ROW(Data!Y443)-434),0)):(OFFSET(Data!$F$423,17*(ROW(Data!Y443)-434),0))) -> 1964.19 | X58: =SUM((OFFSET(Data!$I$410,17*(ROW(Data!Y443)-434),0)):(OFFSET(Data!$I$423,17*(ROW(Data!Y443)-434),0))) -> 1454.67 | Y58: =W58+X58 -> 3418.86 | Z58: =(OFFSET(Data!$F$412,17*(ROW(Data!Y443)-434),0)) -> 127.4 | AA58: =(OFFSET(Data!$F$411,17*(ROW(Data!Y443)-434),0)) -> 273.12 | AB58: =Data!I569 -> 207 | AC58: =AE58-AB58 -> 1247.67 | AD58: =SUM((OFFSET(Data!$F$410,17*(ROW(Data!Y443)-434),0)):(OFFSET(Data!$F$423,17*(ROW(Data!Y443)-434),0))) -> 1964.19 | AE58: =SUM((OFFSET(Data!$I$410,17*(ROW(Data!Y443)-434),0)):(OFFSET(Data!$I$423,17*(ROW(Data!Y443)-434),0))) -> 1454.67 | AF58: =AD58+AE58 -> 3418.86 | AG58: =C58-AF58 -> 17.76 | AH58: =D58-D57 -> 17.76 | AI58: =C58-R58 -> 88.939127 | AJ58: =K58-K57 -> 88.939127 | AK58: =AG58-AH58 -> 0 | AL58: =AI58-AJ58 -> 0 | AM58: =AG58-AG57 -> 140.87 | AN58: =AH58-AH57 -> 140.87 | AO58: =AJ58-AJ57 -> 4.0783364 | AP58: =AN58-AM58 -> 0 | AQ58: =AO58-AN58 -> -136.79166 | AR58: =K58-D58 -> 194.85476 | AS58: =AI58-AG58 -> 71.179127 | AT58: =AJ58-AH58 -> 71.179127 | AU58: =ABS(AR58/K58) -> 0.061650762 | AV58: =ABS(AS58/AI58) -> 0.80031286 | AW58: =ABS(AR58/AVERAGE(K58,D58)) -> 0.063611614 | AX58: =ABS((AG58-AH58)/AVERAGE(AG58,AH58)) -> 0 | AZ58: =Data!S574 -> 173.47 | BA58: =Data!T574 -> 0.088424798 | BB58: =Data!U574 -> 10.629431 | BC58: =Data!V574 -> 0.016660535 | BD58: =Data!S575 -> -81.16 | BE58: =Data!T575 -> -0.056034632 | BF58: =Data!U575 -> 142.02263 | BG58: =Data!V575 -> 0.93918243 | BH58: =Data!S576 -> 92.31 | BI58: =Data!T576 -> 0.027069032 | BJ58: =Data!U576 -> 152.65206 | BK58: =Data!V576 -> 0.19342143 | BL58: =Data!W576 -> 244.96206 | BM58: =Data!X576 -> 0.058332773 | BP58: =ABS((AR59-AS59)/((ABS(AR59)+ABS(AS59))/2))/10 -> 0.2 | BT58: =22/31 -> 0.70967742 | BU58: =BT58*1000 -> 709.67742 | BW58: =Health!N69 -> 169.2
B59: 45597 | C59: =SUM((OFFSET(Data!$C$410,17*(ROW(Data!Y444)-434),0)):(OFFSET(Data!$C$423,17*(ROW(Data!Y444)-434),0))) -> 2929.97 | D59: =(OFFSET(Data!$P$409,17*(ROW(Data!Y444)-434),0)) -> 2711.4873 | E59: =(OFFSET(Data!$P$412,17*(ROW(Data!Y444)-434),0)) -> 276.86 | F59: =(OFFSET(Data!$P$418,17*(ROW(Data!Y444)-434),0)) -> 213.88 | G59: =(OFFSET(Data!$P$415,17*(ROW(Data!Y444)-434),0)) -> 85 | H59: =(OFFSET(Data!$P$421,17*(ROW(Data!Y444)-434),0)) -> 2135.7473 | K59: =(OFFSET(Data!$Q$409,17*(ROW(Data!Y444)-434),0)) -> 2837.1333 | L59: =(OFFSET(Data!$Q$412,17*(ROW(Data!Y444)-434),0)) -> 944.51 | M59: =(OFFSET(Data!$Q$415,17*(ROW(Data!Y444)-434),0)) -> 77 | N59: =(OFFSET(Data!$Q$418,17*(ROW(Data!Y444)-434),0)) -> 214.71 | O59: =(OFFSET(Data!$U$410,17*(ROW(Data!Y444)-434),0)) -> 100.47334 | P59: =(OFFSET(Data!$S$410,17*(ROW(Data!Y444)-434),0)) -> 1500.44 | Q59: =(OFFSET(Data!$Q$421,17*(ROW(Data!Y444)-434),0)) -> 1600.9133 | R59: =K58-K59+C59 -> 3253.4587 | S59: 150 | T59: 400 | U59: 0 | V59: 200 | W59: =SUM((OFFSET(Data!$F$410,17*(ROW(Data!Y444)-434),0)):(OFFSET(Data!$F$423,17*(ROW(Data!Y444)-434),0))) -> 1692.49 | X59: =SUM((OFFSET(Data!$I$410,17*(ROW(Data!Y444)-434),0)):(OFFSET(Data!$I$423,17*(ROW(Data!Y444)-434),0))) -> 1491.76 | Y59: =W59+X59 -> 3184.25 | Z59: =(OFFSET(Data!$F$412,17*(ROW(Data!Y444)-434),0)) -> 113.97 | AA59: =(OFFSET(Data!$F$411,17*(ROW(Data!Y444)-434),0)) -> 147.35 | AB59: =Data!I585 -> 289 | AC59: =AE59-AB59 -> 1202.76 | AD59: =SUM((OFFSET(Data!$F$410,17*(ROW(Data!Y444)-434),0)):(OFFSET(Data!$F$423,17*(ROW(Data!Y444)-434),0))) -> 1692.49 | AE59: =SUM((OFFSET(Data!$I$410,17*(ROW(Data!Y444)-434),0)):(OFFSET(Data!$I$423,17*(ROW(Data!Y444)-434),0))) -> 1491.76 | AF59: =AD59+AE59 -> 3184.25 | AG59: =C59-AF59 -> -254.28 | AH59: =D59-D58 -> -254.28 | AI59: =C59-R59 -> -323.48872 | AJ59: =K59-K58 -> -323.48872 | AK59: =AG59-AH59 -> -4.5474735e-13 | AL59: =AI59-AJ59 -> 0 | AM59: =AG59-AG58 -> -272.04 | AN59: =AH59-AH58 -> -272.04 | AO59: =AJ59-AJ58 -> -412.42785 | AP59: =AN59-AM59 -> 4.5474735e-13 | AQ59: =AO59-AN59 -> -140.38785 | AR59: =K59-D59 -> 125.64604 | AS59: =AI59-AG59 -> -69.208721 | AT59: =AJ59-AH59 -> -69.208721 | AU59: =ABS(AR59/K59) -> 0.044286264 | AV59: =ABS(AS59/AI59) -> 0.21394477 | AW59: =ABS(AR59/AVERAGE(K59,D59)) -> 0.045289107 | AX59: =ABS((AG59-AH59)/AVERAGE(AG59,AH59)) -> 1.7883725e-15 | AZ59: =Data!S591 -> 182.88 | BA59: =Data!T591 -> 0.091817369 | BB59: =Data!U591 -> 106.61207 | BC59: =Data!V594 -> 0 | BD59: =Data!S592 -> -67.95 | BE59: =Data!T592 -> -0.043324683 | BF59: =Data!U592 -> 141.61127 | BG59: =Data!V592 -> -3.4423527 | BH59: =Data!S593 -> 114.93 | BI59: =Data!T593 -> 0.032282166 | BJ59: =Data!U593 -> 248.22334 | BK59: =Data!V593 -> 0.27914728 | BL59: =Data!W593 -> 363.15334 | BM59: =Data!X593 -> 0.081618681 | BP59: =ABS((AR60-AS60)/((ABS(AR60)+ABS(AS60))/2))/10 -> 0.062715636 | BT59: =19/30 -> 0.63333333 | BU59: =BT59*1000 -> 633.33333 | BW59: =Health!N70 -> 175.15
B60: 45627 | C60: =SUM((OFFSET(Data!$C$410,17*(ROW(Data!Y445)-434),0)):(OFFSET(Data!$C$423,17*(ROW(Data!Y445)-434),0))) -> 3491.27 | D60: =(OFFSET(Data!$P$409,17*(ROW(Data!Y445)-434),0)) -> 2758.3873 | E60: =(OFFSET(Data!$P$412,17*(ROW(Data!Y445)-434),0)) -> -33.96 | F60: =(OFFSET(Data!$P$418,17*(ROW(Data!Y445)-434),0)) -> 313.88 | G60: =(OFFSET(Data!$P$415,17*(ROW(Data!Y445)-434),0)) -> 235 | H60: =(OFFSET(Data!$P$421,17*(ROW(Data!Y445)-434),0)) -> 2243.4673 | K60: =(OFFSET(Data!$Q$409,17*(ROW(Data!Y445)-434),0)) -> 3021.5528 | L60: =(OFFSET(Data!$Q$412,17*(ROW(Data!Y445)-434),0)) -> 574.58 | M60: =(OFFSET(Data!$Q$415,17*(ROW(Data!Y445)-434),0)) -> 227 | N60: =(OFFSET(Data!$Q$418,17*(ROW(Data!Y445)-434),0)) -> 314.8 | O60: =(OFFSET(Data!$U$410,17*(ROW(Data!Y445)-434),0)) -> 221.81277 | P60: =(OFFSET(Data!$S$410,17*(ROW(Data!Y445)-434),0)) -> 1683.36 | Q60: =(OFFSET(Data!$Q$421,17*(ROW(Data!Y445)-434),0)) -> 1905.1728 | R60: =K59-K60+C60 -> 3306.8506 | S60: 150 | T60: 400 | U60: 0 | V60: 200 | W60: =SUM((OFFSET(Data!$F$410,17*(ROW(Data!Y445)-434),0)):(OFFSET(Data!$F$423,17*(ROW(Data!Y445)-434),0))) -> 1990.04 | X60: =SUM((OFFSET(Data!$I$410,17*(ROW(Data!Y445)-434),0)):(OFFSET(Data!$I$423,17*(ROW(Data!Y445)-434),0))) -> 1454.33 | Y60: =W60+X60 -> 3444.37 | Z60: =(OFFSET(Data!$F$412,17*(ROW(Data!Y445)-434),0)) -> 76.11 | AA60: =(OFFSET(Data!$F$411,17*(ROW(Data!Y445)-434),0)) -> 92.64 | AB60: =Data!I604 -> 312 | AC60: =AE60-AB60 -> 1142.33 | AD60: =SUM((OFFSET(Data!$F$410,17*(ROW(Data!Y445)-434),0)):(OFFSET(Data!$F$423,17*(ROW(Data!Y445)-434),0))) -> 1990.04 | AE60: =SUM((OFFSET(Data!$I$410,17*(ROW(Data!Y445)-434),0)):(OFFSET(Data!$I$423,17*(ROW(Data!Y445)-434),0))) -> 1454.33 | AF60: =AD60+AE60 -> 3444.37 | AG60: =C60-AF60 -> 46.9 | AH60: =D60-D59 -> 46.9 | AI60: =C60-R60 -> 184.41943 | AJ60: =K60-K59 -> 184.41943 | AK60: =AG60-AH60 -> 0 | AL60: =AI60-AJ60 -> 0 | AM60: =AG60-AG59 -> 301.18 | AN60: =AH60-AH59 -> 301.18 | AO60: =AJ60-AJ59 -> 507.90815 | AP60: =AN60-AM60 -> -4.5474735e-13 | AQ60: =AO60-AN60 -> 206.72815 | AR60: =K60-D60 -> 263.16546 | AS60: =AI60-AG60 -> 137.51943 | AT60: =AJ60-AH60 -> 137.51943 | AU60: =ABS(AR60/K60) -> 0.0870961 | AV60: =ABS(AS60/AI60) -> 0.7456884 | AW60: =ABS(AR60/AVERAGE(K60,D60)) -> 0.091061658 | AX60: =ABS((AG60-AH60)/AVERAGE(AG60,AH60)) -> 0 | AZ60: =Data!S608 -> 234.13 | BA60: =Data!T608 -> 0.11199767 | BB60: =Data!U608 -> -6.7535393 | BC60: =Data!V611 -> 0 | BD60: =Data!S609 -> -16.32 | BE60: =Data!T609 -> -0.0096018074 | BF60: =Data!U609 -> 240.10631 | BG60: =Data!V609 -> -13.125197 | BH60: =Data!S610 -> 217.81 | BI60: =Data!T610 -> 0.057467079 | BJ60: =Data!U610 -> 233.35277 | BK60: =Data!V610 -> 0.21899748 | BL60: =Data!W610 -> 451.16277 | BM60: =Data!X610 -> 0.09291367 | BP60: =ABS((AR61-AS61)/((ABS(AR61)+ABS(AS61))/2))/10 -> 0.15182659 | BT60: =21/31 -> 0.67741935 | BU60: =BT60*1000 -> 677.41935 | BW60: =Health!N71 -> 180.5
B61: 45658 | C61: =SUM((OFFSET(Data!$C$410,17*(ROW(Data!Y446)-434),0)):(OFFSET(Data!$C$423,17*(ROW(Data!Y446)-434),0))) -> 2932.32 | D61: =(OFFSET(Data!$P$409,17*(ROW(Data!Y446)-434),0)) -> 3187.6473 | E61: =(OFFSET(Data!$P$412,17*(ROW(Data!Y446)-434),0)) -> 295.3 | F61: =(OFFSET(Data!$P$418,17*(ROW(Data!Y446)-434),0)) -> 213.88 | G61: =(OFFSET(Data!$P$415,17*(ROW(Data!Y446)-434),0)) -> 435 | H61: =(OFFSET(Data!$P$421,17*(ROW(Data!Y446)-434),0)) -> 2243.4673 | K61: =(OFFSET(Data!$Q$409,17*(ROW(Data!Y446)-434),0)) -> 3492.563 | L61: =(OFFSET(Data!$Q$412,17*(ROW(Data!Y446)-434),0)) -> 883.49 | M61: =(OFFSET(Data!$Q$415,17*(ROW(Data!Y446)-434),0)) -> 427 | N61: =(OFFSET(Data!$Q$418,17*(ROW(Data!Y446)-434),0)) -> 214.84 | O61: =(OFFSET(Data!$U$410,17*(ROW(Data!Y446)-434),0)) -> 242.22296 | P61: =(OFFSET(Data!$S$410,17*(ROW(Data!Y446)-434),0)) -> 1725.01 | Q61: =(OFFSET(Data!$Q$421,17*(ROW(Data!Y446)-434),0)) -> 1967.233 | R61: =K60-K61+C61 -> 2461.3098 | S61: 150 | T61: 400 | U61: 0 | V61: 200 | W61: =SUM((OFFSET(Data!$F$410,17*(ROW(Data!Y446)-434),0)):(OFFSET(Data!$F$423,17*(ROW(Data!Y446)-434),0))) -> 1404.28 | X61: =SUM((OFFSET(Data!$I$410,17*(ROW(Data!Y446)-434),0)):(OFFSET(Data!$I$423,17*(ROW(Data!Y446)-434),0))) -> 1098.78 | Y61: =W61+X61 -> 2503.06 | Z61: =(OFFSET(Data!$F$412,17*(ROW(Data!Y446)-434),0)) -> 131.44 | AA61: =(OFFSET(Data!$F$411,17*(ROW(Data!Y446)-434),0)) -> 37.84 | AB61: =Data!I619 -> 287 | AC61: =AE61-AB61 -> 811.78 | AD61: =SUM((OFFSET(Data!$F$410,17*(ROW(Data!Y446)-434),0)):(OFFSET(Data!$F$423,17*(ROW(Data!Y446)-434),0))) -> 1404.28 | AE61: =SUM((OFFSET(Data!$I$410,17*(ROW(Data!Y446)-434),0)):(OFFSET(Data!$I$423,17*(ROW(Data!Y446)-434),0))) -> 1098.78 | AF61: =AD61+AE61 -> 2503.06 | AG61: =C61-AF61 -> 429.26 | AH61: =D61-D60 -> 429.26 | AI61: =C61-R61 -> 471.01019 | AJ61: =K61-K60 -> 471.01019 | AK61: =AG61-AH61 -> 0 | AL61: =AI61-AJ61 -> 0 | AM61: =AG61-AG60 -> 382.36 | AN61: =AH61-AH60 -> 382.36 | AO61: =AJ61-AJ60 -> 286.59077 | AP61: =AN61-AM61 -> 0 | AQ61: =AO61-AN61 -> -95.769235 | AR61: =K61-D61 -> 304.91565 | AS61: =AI61-AG61 -> 41.750191 | AT61: =AJ61-AH61 -> 41.750191 | AU61: =ABS(AR61/K61) -> 0.087304268 | AV61: =ABS(AS61/AI61) -> 0.088639676 | AW61: =ABS(AR61/AVERAGE(K61,D61)) -> 0.091289239 | AX61: =ABS((AG61-AH61)/AVERAGE(AG61,AH61)) -> 0 | AZ61: =Data!S625 -> 234.13 | BA61: =Data!T625 -> 0.11199767 | BB61: =Data!U625 -> -6.7535393 | BC61: =Data!V628 -> 0 | BD61: =Data!S626 -> -34.67 | BE61: =Data!T626 -> -0.019702446 | BF61: =Data!U626 -> 260.5165 | BG61: =Data!V626 -> -14.240902 | BH61: =Data!S627 -> 199.46 | BI61: =Data!T627 -> 0.051805505 | BJ61: =Data!U627 -> 253.76296 | BK61: =Data!V627 -> 0.23815209 | BL61: =Data!W627 -> 453.22296 | BM61: =Data!X627 -> 0.092198693 | BP61: =ABS((AR62-AS62)/((ABS(AR62)+ABS(AS62))/2))/10 -> 0.2 | BW61: =Health!N72 -> 182.08
B62: 45689 | C62: =SUM((OFFSET(Data!$C$410,17*(ROW(Data!Y447)-434),0)):(OFFSET(Data!$C$423,17*(ROW(Data!Y447)-434),0))) -> 3406.3 | D62: =(OFFSET(Data!$P$409,17*(ROW(Data!Y447)-434),0)) -> 4023.4973 | E62: =(OFFSET(Data!$P$412,17*(ROW(Data!Y447)-434),0)) -> 681.15 | F62: =(OFFSET(Data!$P$418,17*(ROW(Data!Y447)-434),0)) -> 563.88 | G62: =(OFFSET(Data!$P$415,17*(ROW(Data!Y447)-434),0)) -> 535 | H62: =(OFFSET(Data!$P$421,17*(ROW(Data!Y447)-434),0)) -> 2243.4673 | K62: =(OFFSET(Data!$Q$409,17*(ROW(Data!Y447)-434),0)) -> 4240.9214 | L62: =(OFFSET(Data!$Q$412,17*(ROW(Data!Y447)-434),0)) -> 1257.64 | M62: =(OFFSET(Data!$Q$415,17*(ROW(Data!Y447)-434),0)) -> 527 | N62: =(OFFSET(Data!$Q$418,17*(ROW(Data!Y447)-434),0)) -> 564.89 | O62: =(OFFSET(Data!$U$410,17*(ROW(Data!Y447)-434),0)) -> 228.17144 | P62: =(OFFSET(Data!$S$410,17*(ROW(Data!Y447)-434),0)) -> 1663.22 | Q62: =(OFFSET(Data!$Q$421,17*(ROW(Data!Y447)-434),0)) -> 1891.3914 | R62: =K61-K62+C62 -> 2657.9415 | S62: 150 | T62: 400 | U62: 0 | V62: 200 | W62: =SUM((OFFSET(Data!$F$410,17*(ROW(Data!Y447)-434),0)):(OFFSET(Data!$F$423,17*(ROW(Data!Y447)-434),0))) -> 1442.91 | X62: =SUM((OFFSET(Data!$I$410,17*(ROW(Data!Y447)-434),0)):(OFFSET(Data!$I$423,17*(ROW(Data!Y447)-434),0))) -> 1127.54 | Y62: =W62+X62 -> 2570.45 | Z62: =(OFFSET(Data!$F$412,17*(ROW(Data!Y447)-434),0)) -> 79.16 | AA62: =(OFFSET(Data!$F$411,17*(ROW(Data!Y447)-434),0)) -> 43.75 | AB62: =Data!I639 -> 141 | AC62: =AE62-AB62 -> 986.54 | AD62: =SUM((OFFSET(Data!$F$410,17*(ROW(Data!Y447)-434),0)):(OFFSET(Data!$F$423,17*(ROW(Data!Y447)-434),0))) -> 1442.91 | AE62: =SUM((OFFSET(Data!$I$410,17*(ROW(Data!Y447)-434),0)):(OFFSET(Data!$I$423,17*(ROW(Data!Y447)-434),0))) -> 1127.54 | AF62: =AD62+AE62 -> 2570.45 | AG62: =C62-AF62 -> 835.85 | AH62: =D62-D61 -> 835.85 | AI62: =C62-R62 -> 748.35848 | AJ62: =K62-K61 -> 748.35848 | AK62: =AG62-AH62 -> 0 | AL62: =AI62-AJ62 -> 0 | AM62: =AG62-AG61 -> 406.59 | AN62: =AH62-AH61 -> 406.59 | AO62: =AJ62-AJ61 -> 277.34829 | AP62: =AN62-AM62 -> 0 | AQ62: =AO62-AN62 -> -129.24171 | AR62: =K62-D62 -> 217.42414 | AS62: =AI62-AG62 -> -87.491519 | AT62: =AJ62-AH62 -> -87.491519 | AU62: =ABS(AR62/K62) -> 0.051268136 | AV62: =ABS(AS62/AI62) -> 0.11691124 | AW62: =ABS(AR62/AVERAGE(K62,D62)) -> 0.052616921 | AX62: =ABS((AG62-AH62)/AVERAGE(AG62,AH62)) -> 0 | AZ62: =Data!S642 -> 237.43 | BA62: =Data!T642 -> 0.11223405 | BB62: =Data!U642 -> -18.770827 | BC62: =Data!V645 -> 0 | BD62: =Data!S643 -> -71.46 | BE62: =Data!T643 -> -0.041194918 | BF62: =Data!U643 -> 228.48227 | BG62: =Data!V643 -> -735.07818 | BH62: =Data!S644 -> 165.97 | BI62: =Data!T644 -> 0.043107187 | BJ62: =Data!U644 -> 209.71144 | BK62: =Data!V644 -> 0.19142115 | BL62: =Data!W644 -> 375.68144 | BM62: =Data!X644 -> 0.07596092 | BP62: =ABS((AR63-AS63)/((ABS(AR63)+ABS(AS63))/2))/10 -> 0.2
B63: 45717 | C63: =SUM((OFFSET(Data!$C$410,17*(ROW(Data!Y448)-434),0)):(OFFSET(Data!$C$423,17*(ROW(Data!Y448)-434),0))) -> 3301.88 | D63: =(OFFSET(Data!$P$409,17*(ROW(Data!Y448)-434),0)) -> 4559.2373 | E63: =(OFFSET(Data!$P$412,17*(ROW(Data!Y448)-434),0)) -> 526.89 | F63: =(OFFSET(Data!$P$418,17*(ROW(Data!Y448)-434),0)) -> 1063.88 | G63: =(OFFSET(Data!$P$415,17*(ROW(Data!Y448)-434),0)) -> 535 | H63: =(OFFSET(Data!$P$421,17*(ROW(Data!Y448)-434),0)) -> 2433.4673 | K63: =(OFFSET(Data!$Q$409,17*(ROW(Data!Y448)-434),0)) -> 4587.2583 | L63: =(OFFSET(Data!$Q$412,17*(ROW(Data!Y448)-434),0)) -> 1079.45 | M63: =(OFFSET(Data!$Q$415,17*(ROW(Data!Y448)-434),0)) -> 530 | N63: =(OFFSET(Data!$Q$418,17*(ROW(Data!Y448)-434),0)) -> 1065.12 | O63: =(OFFSET(Data!$U$410,17*(ROW(Data!Y448)-434),0)) -> 224.61826 | P63: =(OFFSET(Data!$S$410,17*(ROW(Data!Y448)-434),0)) -> 1688.07 | Q63: =(OFFSET(Data!$Q$421,17*(ROW(Data!Y448)-434),0)) -> 1912.6883 | R63: =K62-K63+C63 -> 2955.5432 | S63: 150 | T63: 400 | U63: 0 | V63: 200 | W63: =SUM((OFFSET(Data!$F$410,17*(ROW(Data!Y448)-434),0)):(OFFSET(Data!$F$423,17*(ROW(Data!Y448)-434),0))) -> 1488.16 | X63: =SUM((OFFSET(Data!$I$410,17*(ROW(Data!Y448)-434),0)):(OFFSET(Data!$I$423,17*(ROW(Data!Y448)-434),0))) -> 1277.98 | Y63: =W63+X63 -> 2766.14 | Z63: =(OFFSET(Data!$F$412,17*(ROW(Data!Y448)-434),0)) -> 79.2 | AA63: =(OFFSET(Data!$F$411,17*(ROW(Data!Y448)-434),0)) -> 28.96 | AB63: =Data!I654 -> 289 | AC63: =AE63-AB63 -> 988.98 | AD63: =SUM((OFFSET(Data!$F$410,17*(ROW(Data!Y448)-434),0)):(OFFSET(Data!$F$423,17*(ROW(Data!Y448)-434),0))) -> 1488.16 | AE63: =SUM((OFFSET(Data!$I$410,17*(ROW(Data!Y448)-434),0)):(OFFSET(Data!$I$423,17*(ROW(Data!Y448)-434),0))) -> 1277.98 | AF63: =AD63+AE63 -> 2766.14 | AG63: =C63-AF63 -> 535.74 | AH63: =D63-D62 -> 535.74 | AI63: =C63-R63 -> 346.33683 | AJ63: =K63-K62 -> 346.33683 | AK63: =AG63-AH63 -> 0 | AL63: =AI63-AJ63 -> 0 | AM63: =AG63-AG62 -> -300.11 | AN63: =AH63-AH62 -> -300.11 | AO63: =AJ63-AJ62 -> -402.02166 | AP63: =AN63-AM63 -> 0 | AQ63: =AO63-AN63 -> -101.91166 | AR63: =K63-D63 -> 28.02096 | AS63: =AI63-AG63 -> -189.40317 | AT63: =AJ63-AH63 -> -189.40317 | AU63: =ABS(AR63/K63) -> 0.0061084332 | AV63: =ABS(AS63/AI63) -> 0.54687565 | AW63: =ABS(AR63/AVERAGE(K63,D63)) -> 0.0061271468 | AX63: =ABS((AG63-AH63)/AVERAGE(AG63,AH63)) -> 0 | AZ63: =Data!S659 -> 237.43 | BA63: =Data!T659 -> 0.11223405 | BB63: =Data!U659 -> -18.770827 | BC63: =Data!V662 -> 0 | BD63: =Data!S660 -> -236.61 | BE63: =Data!T660 -> -0.12293472 | BF63: =Data!U660 -> 224.92909 | BG63: =Data!V660 -> -723.64683 | BH63: =Data!S661 -> 0.82 | BI63: =Data!T661 -> 0.00020296176 | BJ63: =Data!U661 -> 206.15826 | BK63: =Data!V661 -> 0.18817787 | BL63: =Data!W661 -> 206.97826 | BM63: =Data!X661 -> 0.040301704 | BP63: =ABS((AR64-AS64)/((ABS(AR64)+ABS(AS64))/2))/10 -> 0.163368
B64: 45748 | C64: =SUM((OFFSET(Data!$C$410,17*(ROW(Data!Y449)-434),0)):(OFFSET(Data!$C$423,17*(ROW(Data!Y449)-434),0))) -> 3270.95 | D64: =(OFFSET(Data!$P$409,17*(ROW(Data!Y449)-434),0)) -> 4987.7873 | E64: =(OFFSET(Data!$P$412,17*(ROW(Data!Y449)-434),0)) -> 656.66 | F64: =(OFFSET(Data!$P$418,17*(ROW(Data!Y449)-434),0)) -> 1063.88 | G64: =(OFFSET(Data!$P$415,17*(ROW(Data!Y449)-434),0)) -> 635 | H64: =(OFFSET(Data!$P$421,17*(ROW(Data!Y449)-434),0)) -> 2632.2473 | K64: =(OFFSET(Data!$Q$409,17*(ROW(Data!Y449)-434),0)) -> 4984.6457 | L64: =(OFFSET(Data!$Q$412,17*(ROW(Data!Y449)-434),0)) -> 1083.46 | M64: =(OFFSET(Data!$Q$415,17*(ROW(Data!Y449)-434),0)) -> 630 | N64: =(OFFSET(Data!$Q$418,17*(ROW(Data!Y449)-434),0)) -> 1065.48 | O64: =(OFFSET(Data!$U$410,17*(ROW(Data!Y449)-434),0)) -> 313.32574 | P64: =(OFFSET(Data!$S$410,17*(ROW(Data!Y449)-434),0)) -> 1892.38 | Q64: =(OFFSET(Data!$Q$421,17*(ROW(Data!Y449)-434),0)) -> 2205.7057 | R64: =K63-K64+C64 -> 2873.5625 | S64: 150 | T64: 400 | U64: 0 | V64: 200 | W64: =SUM((OFFSET(Data!$F$410,17*(ROW(Data!Y449)-434),0)):(OFFSET(Data!$F$423,17*(ROW(Data!Y449)-434),0))) -> 1653.22 | X64: =SUM((OFFSET(Data!$I$410,17*(ROW(Data!Y449)-434),0)):(OFFSET(Data!$I$423,17*(ROW(Data!Y449)-434),0))) -> 1189.18 | Y64: =W64+X64 -> 2842.4 | Z64: =(OFFSET(Data!$F$412,17*(ROW(Data!Y449)-434),0)) -> 113.74 | AA64: =(OFFSET(Data!$F$411,17*(ROW(Data!Y449)-434),0)) -> 56.8 | AB64: =Data!I671 -> 180 | AC64: =AE64-AB64 -> 1009.18 | AD64: =SUM((OFFSET(Data!$F$410,17*(ROW(Data!Y449)-434),0)):(OFFSET(Data!$F$423,17*(ROW(Data!Y449)-434),0))) -> 1653.22 | AE64: =SUM((OFFSET(Data!$I$410,17*(ROW(Data!Y449)-434),0)):(OFFSET(Data!$I$423,17*(ROW(Data!Y449)-434),0))) -> 1189.18 | AF64: =AD64+AE64 -> 2842.4 | AG64: =C64-AF64 -> 428.55 | AH64: =D64-D63 -> 428.55 | AI64: =C64-R64 -> 397.38747 | AJ64: =K64-K63 -> 397.38747 | AK64: =AG64-AH64 -> 0 | AL64: =AI64-AJ64 -> 0 | AM64: =AG64-AG63 -> -107.19 | AN64: =AH64-AH63 -> -107.19 | AO64: =AJ64-AJ63 -> 51.050645 | AP64: =AN64-AM64 -> 0 | AQ64: =AO64-AN64 -> 158.24064 | AR64: =K64-D64 -> -3.1415693 | AS64: =AI64-AG64 -> -31.16253 | AT64: =AJ64-AH64 -> -31.16253 | AU64: =ABS(AR64/K64) -> 0.00063024927 | AV64: =ABS(AS64/AI64) -> 0.078418501 | AW64: =ABS(AR64/AVERAGE(K64,D64)) -> 0.00063005072 | AX64: =ABS((AG64-AH64)/AVERAGE(AG64,AH64)) -> 0 | AZ64: =Data!S676 -> 237.43 | BA64: =Data!T676 -> 0.11223405 | BB64: =Data!U676 -> -34.070108 | BC64: =Data!V679 -> 0 | BD64: =Data!S677 -> -182.3 | BE64: =Data!T677 -> -0.087868973 | BF64: =Data!U677 -> 278.93584 | BG64: =Data!V677 -> 8.1109834 | BH64: =Data!S678 -> 55.13 | BI64: =Data!T678 -> 0.013156984 | BJ64: =Data!U678 -> 244.86574 | BK64: =Data!V678 -> 0.21375386 | BL64: =Data!W678 -> 299.99574 | BM64: =Data!X678 -> 0.05622404 | BP64: =ABS((AR65-AS65)/((ABS(AR65)+ABS(AS65))/2))/10 -> 0.00068680931
B65: 45778 | C65: =SUM((OFFSET(Data!$C$410,17*(ROW(Data!Y450)-434),0)):(OFFSET(Data!$C$423,17*(ROW(Data!Y450)-434),0))) -> 3255.71 | D65: =(OFFSET(Data!$P$409,17*(ROW(Data!Y450)-434),0)) -> 4924.6573 | E65: =(OFFSET(Data!$P$412,17*(ROW(Data!Y450)-434),0)) -> 293.53 | F65: =(OFFSET(Data!$P$418,17*(ROW(Data!Y450)-434),0)) -> 1063.88 | G65: =(OFFSET(Data!$P$415,17*(ROW(Data!Y450)-434),0)) -> 635 | H65: =(OFFSET(Data!$P$421,17*(ROW(Data!Y450)-434),0)) -> 2932.2473 | K65: =(OFFSET(Data!$Q$409,17*(ROW(Data!Y450)-434),0)) -> 5380.5016 | L65: =(OFFSET(Data!$Q$412,17*(ROW(Data!Y450)-434),0)) -> 1011.15 | M65: =(OFFSET(Data!$Q$415,17*(ROW(Data!Y450)-434),0)) -> 630 | N65: =(OFFSET(Data!$Q$418,17*(ROW(Data!Y450)-434),0)) -> 1065.79 | O65: =(OFFSET(Data!$U$410,17*(ROW(Data!Y450)-434),0)) -> 274.72159 | P65: =(OFFSET(Data!$S$410,17*(ROW(Data!Y450)-434),0)) -> 2398.84 | Q65: =(OFFSET(Data!$Q$421,17*(ROW(Data!Y450)-434),0)) -> 2673.5616 | R65: =K64-K65+C65 -> 2859.8541 | S65: 150 | T65: 400 | U65: 0 | V65: 200 | W65: =SUM((OFFSET(Data!$F$410,17*(ROW(Data!Y450)-434),0)):(OFFSET(Data!$F$423,17*(ROW(Data!Y450)-434),0))) -> 1891.84 | X65: =SUM((OFFSET(Data!$I$410,17*(ROW(Data!Y450)-434),0)):(OFFSET(Data!$I$423,17*(ROW(Data!Y450)-434),0))) -> 1427 | Y65: =W65+X65 -> 3318.84 | Z65: =(OFFSET(Data!$F$412,17*(ROW(Data!Y450)-434),0)) -> 111.8 | AA65: =(OFFSET(Data!$F$411,17*(ROW(Data!Y450)-434),0)) -> 228.3 | AB65: =Data!I688 -> 542 | AC65: =AE65-AB65 -> 885 | AD65: =SUM((OFFSET(Data!$F$410,17*(ROW(Data!Y450)-434),0)):(OFFSET(Data!$F$423,17*(ROW(Data!Y450)-434),0))) -> 1891.84 | AE65: =SUM((OFFSET(Data!$I$410,17*(ROW(Data!Y450)-434),0)):(OFFSET(Data!$I$423,17*(ROW(Data!Y450)-434),0))) -> 1427 | AF65: =AD65+AE65 -> 3318.84 | AG65: =C65-AF65 -> -63.13 | AH65: =D65-D64 -> -63.13 | AI65: =C65-R65 -> 395.85586 | AJ65: =K65-K64 -> 395.85586 | AK65: =AG65-AH65 -> 0 | AL65: =AI65-AJ65 -> 0 | AM65: =AG65-AG64 -> -491.68 | AN65: =AH65-AH64 -> -491.68 | AO65: =AJ65-AJ64 -> -1.5316115 | AP65: =AN65-AM65 -> 0 | AQ65: =AO65-AN65 -> 490.14839 | AR65: =K65-D65 -> 455.84429 | AS65: =AI65-AG65 -> 458.98586 | AT65: =AJ65-AH65 -> 458.98586 | AU65: =ABS(AR65/K65) -> 0.084721523 | AV65: =ABS(AS65/AI65) -> 1.1594772 | AW65: =ABS(AR65/AVERAGE(K65,D65)) -> 0.088469143 | AX65: =ABS((AG65-AH65)/AVERAGE(AG65,AH65)) -> 0 | AZ65: =Data!S693 -> 267.49 | BA65: =Data!T693 -> 0.12085082 | BB65: =Data!U693 -> -5.9191137 | BC65: =Data!V696 -> 0 | BD65: =Data!S694 -> 122.06 | BE65: =Data!T694 -> 0.053610801 | BF65: =Data!U694 -> 283.11071 | BG65: =Data!V694 -> -33.747392 | BH65: =Data!S695 -> 389.55 | BI65: =Data!T695 -> 0.086756181 | BJ65: =Data!U695 -> 277.19159 | BK65: =Data!V695 -> 0.2419725 | BL65: =Data!W695 -> 666.74159 | BM65: =Data!X695 -> 0.11830637 | BP65: =ABS((AR66-AS66)/((ABS(AR66)+ABS(AS66))/2))/10 -> 0.071585787
B66: 45809 | C66: =SUM((OFFSET(Data!$C$410,17*(ROW(Data!Y451)-434),0)):(OFFSET(Data!$C$423,17*(ROW(Data!Y451)-434),0))) -> 4062.63 | D66: =(OFFSET(Data!$P$409,17*(ROW(Data!Y451)-434),0)) -> 5285.1573 | E66: =(OFFSET(Data!$P$412,17*(ROW(Data!Y451)-434),0)) -> 664.03 | F66: =(OFFSET(Data!$P$418,17*(ROW(Data!Y451)-434),0)) -> 1063.88 | G66: =(OFFSET(Data!$P$415,17*(ROW(Data!Y451)-434),0)) -> 295 | H66: =(OFFSET(Data!$P$421,17*(ROW(Data!Y451)-434),0)) -> 3262.2473 | K66: =(OFFSET(Data!$Q$409,17*(ROW(Data!Y451)-434),0)) -> 6149.8599 | L66: =(OFFSET(Data!$Q$412,17*(ROW(Data!Y451)-434),0)) -> 1419.36 | M66: =(OFFSET(Data!$Q$415,17*(ROW(Data!Y451)-434),0)) -> 290 | N66: =(OFFSET(Data!$Q$418,17*(ROW(Data!Y451)-434),0)) -> 1066.09 | O66: =(OFFSET(Data!$U$410,17*(ROW(Data!Y451)-434),0)) -> 281.65989 | P66: =(OFFSET(Data!$S$410,17*(ROW(Data!Y451)-434),0)) -> 3092.75 | Q66: =(OFFSET(Data!$Q$421,17*(ROW(Data!Y451)-434),0)) -> 3374.4099 | R66: =K65-K66+C66 -> 3293.2717 | S66: 150 | T66: 400 | U66: 0 | V66: 200 | W66: =SUM((OFFSET(Data!$F$410,17*(ROW(Data!Y451)-434),0)):(OFFSET(Data!$F$423,17*(ROW(Data!Y451)-434),0))) -> 1783.79 | X66: =SUM((OFFSET(Data!$I$410,17*(ROW(Data!Y451)-434),0)):(OFFSET(Data!$I$423,17*(ROW(Data!Y451)-434),0))) -> 1918.34 | Y66: =W66+X66 -> 3702.13 | Z66: =(OFFSET(Data!$F$412,17*(ROW(Data!Y451)-434),0)) -> 84.37 | AA66: =(OFFSET(Data!$F$411,17*(ROW(Data!Y451)-434),0)) -> 197.94 | AB66: =Data!I705 -> 298 | AC66: =AE66-AB66 -> 1620.34 | AD66: =SUM((OFFSET(Data!$F$410,17*(ROW(Data!Y451)-434),0)):(OFFSET(Data!$F$423,17*(ROW(Data!Y451)-434),0))) -> 1783.79 | AE66: =SUM((OFFSET(Data!$I$410,17*(ROW(Data!Y451)-434),0)):(OFFSET(Data!$I$423,17*(ROW(Data!Y451)-434),0))) -> 1918.34 | AF66: =AD66+AE66 -> 3702.13 | AG66: =C66-AF66 -> 360.5 | AH66: =D66-D65 -> 360.5 | AI66: =C66-R66 -> 769.3583 | AJ66: =K66-K65 -> 769.3583 | AK66: =AG66-AH66 -> 0 | AL66: =AI66-AJ66 -> 0 | AM66: =AG66-AG65 -> 423.63 | AN66: =AH66-AH65 -> 423.63 | AO66: =AJ66-AJ65 -> 373.50244 | AP66: =AN66-AM66 -> 0 | AQ66: =AO66-AN66 -> -50.127561 | AR66: =K66-D66 -> 864.70259 | AS66: =AI66-AG66 -> 408.8583 | AT66: =AJ66-AH66 -> 408.8583 | AU66: =ABS(AR66/K66) -> 0.14060525 | AV66: =ABS(AS66/AI66) -> 0.53142768 | AW66: =ABS(AR66/AVERAGE(K66,D66)) -> 0.15123765 | AX66: =ABS((AG66-AH66)/AVERAGE(AG66,AH66)) -> 0 | AZ66: =Data!S710 -> 349.62 | BA66: =Data!T710 -> 0.14301141 | BB66: =Data!U710 -> -5.9191137 | BC66: =Data!V713 -> 0 | BD66: =Data!S711 -> 487.28 | BE66: =Data!T711 -> 0.18702192 | BF66: =Data!U711 -> 290.049 | BG66: =Data!V711 -> -34.574451 | BH66: =Data!S712 -> 836.9 | BI66: =Data!T712 -> 0.16571719 | BJ66: =Data!U712 -> 284.12989 | BK66: =Data!V712 -> 0.24802924 | BL66: =Data!W712 -> 1121.0299 | BM66: =Data!X712 -> 0.18093618 | BP66: =ABS((AR67-AS67)/((ABS(AR67)+ABS(AS67))/2))/10 -> 0.13629175
B67: 45839 | C67: =SUM((OFFSET(Data!$C$410,17*(ROW(Data!Y452)-434),0)):(OFFSET(Data!$C$423,17*(ROW(Data!Y452)-434),0))) -> 4045.72 | D67: =(OFFSET(Data!$P$409,17*(ROW(Data!Y452)-434),0)) -> 5308.2673 | E67: =(OFFSET(Data!$P$412,17*(ROW(Data!Y452)-434),0)) -> 312.14 | F67: =(OFFSET(Data!$P$418,17*(ROW(Data!Y452)-434),0)) -> 1063.88 | G67: =(OFFSET(Data!$P$415,17*(ROW(Data!Y452)-434),0)) -> 135 | H67: =(OFFSET(Data!$P$421,17*(ROW(Data!Y452)-434),0)) -> 3797.2473 | K67: =(OFFSET(Data!$Q$409,17*(ROW(Data!Y452)-434),0)) -> 6375.0683 | L67: =(OFFSET(Data!$Q$412,17*(ROW(Data!Y452)-434),0)) -> 815.64 | M67: =(OFFSET(Data!$Q$415,17*(ROW(Data!Y452)-434),0)) -> 130 | N67: =(OFFSET(Data!$Q$418,17*(ROW(Data!Y452)-434),0)) -> 1066.39 | O67: =(OFFSET(Data!$U$410,17*(ROW(Data!Y452)-434),0)) -> 254.37831 | P67: =(OFFSET(Data!$S$410,17*(ROW(Data!Y452)-434),0)) -> 4108.66 | Q67: =(OFFSET(Data!$Q$421,17*(ROW(Data!Y452)-434),0)) -> 4363.0383 | R67: =K66-K67+C67 -> 3820.5116 | S67: 150 | T67: 400 | U67: 0 | V67: 200 | W67: =SUM((OFFSET(Data!$F$410,17*(ROW(Data!Y452)-434),0)):(OFFSET(Data!$F$423,17*(ROW(Data!Y452)-434),0))) -> 1990.97 | X67: =SUM((OFFSET(Data!$I$410,17*(ROW(Data!Y452)-434),0)):(OFFSET(Data!$I$423,17*(ROW(Data!Y452)-434),0))) -> 2031.64 | Y67: =W67+X67 -> 4022.61 | Z67: =(OFFSET(Data!$F$412,17*(ROW(Data!Y452)-434),0)) -> 111.87 | AA67: =(OFFSET(Data!$F$411,17*(ROW(Data!Y452)-434),0)) -> 324.1 | AB67: =Data!I722 -> 210 | AC67: =AE67-AB67 -> 1821.64 | AD67: =SUM((OFFSET(Data!$F$410,17*(ROW(Data!Y452)-434),0)):(OFFSET(Data!$F$423,17*(ROW(Data!Y452)-434),0))) -> 1990.97 | AE67: =SUM((OFFSET(Data!$I$410,17*(ROW(Data!Y452)-434),0)):(OFFSET(Data!$I$423,17*(ROW(Data!Y452)-434),0))) -> 2031.64 | AF67: =AD67+AE67 -> 4022.61 | AG67: =C67-AF67 -> 23.11 | AH67: =D67-D66 -> 23.11 | AI67: =C67-R67 -> 225.20842 | AJ67: =K67-K66 -> 225.20842 | AK67: =AG67-AH67 -> 4.5474735e-13 | AL67: =AI67-AJ67 -> 0 | AM67: =AG67-AG66 -> -337.39 | AN67: =AH67-AH66 -> -337.39 | AO67: =AJ67-AJ66 -> -544.14988 | AP67: =AN67-AM67 -> -4.5474735e-13 | AQ67: =AO67-AN67 -> -206.75988 | AR67: =K67-D67 -> 1066.801 | AS67: =AI67-AG67 -> 202.09842 | AT67: =AJ67-AH67 -> 202.09842 | AU67: =ABS(AR67/K67) -> 0.16733954 | AV67: =ABS(AS67/AI67) -> 0.89738394 | AW67: =ABS(AR67/AVERAGE(K67,D67)) -> 0.18261925 | AX67: =ABS((AG67-AH67)/AVERAGE(AG67,AH67)) -> 1.9677514e-14 | AZ67: =Data!S727 -> 382.27 | BA67: =Data!T727 -> 0.15278455 | BB67: =Data!U727 -> 15.67314 | BC67: =Data!V730 -> 0 | BD67: =Data!S728 -> 610.51 | BE67: =Data!T728 -> 0.17452368 | BF67: =Data!U728 -> 289.68517 | BG67: =Data!V728 -> -8.2047842 | BH67: =Data!S729 -> 992.78 | BI67: =Data!T729 -> 0.16545865 | BJ67: =Data!U729 -> 305.35831 | BK67: =Data!V729 -> 0.26656044 | BL67: =Data!W729 -> 1298.1383 | BM67: =Data!X729 -> 0.18166655 | BP67: =ABS((AR68-AS68)/((ABS(AR68)+ABS(AS68))/2))/10 -> 0.2
B68: 45870 | C68: =SUM((OFFSET(Data!$C$410,17*(ROW(Data!Y453)-434),0)):(OFFSET(Data!$C$423,17*(ROW(Data!Y453)-434),0))) -> 4738.75 | D68: =(OFFSET(Data!$P$409,17*(ROW(Data!Y453)-434),0)) -> 7067.5773 | E68: =(OFFSET(Data!$P$412,17*(ROW(Data!Y453)-434),0)) -> 822.42 | F68: =(OFFSET(Data!$P$418,17*(ROW(Data!Y453)-434),0)) -> 1063.88 | G68: =(OFFSET(Data!$P$415,17*(ROW(Data!Y453)-434),0)) -> 535 | H68: =(OFFSET(Data!$P$421,17*(ROW(Data!Y453)-434),0)) -> 4646.2773 | K68: =(OFFSET(Data!$Q$409,17*(ROW(Data!Y453)-434),0)) -> 8117.767 | L68: =(OFFSET(Data!$Q$412,17*(ROW(Data!Y453)-434),0)) -> 1404.41 | M68: =(OFFSET(Data!$Q$415,17*(ROW(Data!Y453)-434),0)) -> 480 | N68: =(OFFSET(Data!$Q$418,17*(ROW(Data!Y453)-434),0)) -> 1066.49 | O68: =(OFFSET(Data!$U$410,17*(ROW(Data!Y453)-434),0)) -> 236.94702 | P68: =(OFFSET(Data!$S$410,17*(ROW(Data!Y453)-434),0)) -> 4929.92 | Q68: =(OFFSET(Data!$Q$421,17*(ROW(Data!Y453)-434),0)) -> 5166.867 | R68: =K67-K68+C68 -> 2996.0513 | S68: 150 | T68: 400 | U68: 0 | V68: 200 | W68: =SUM((OFFSET(Data!$F$410,17*(ROW(Data!Y453)-434),0)):(OFFSET(Data!$F$423,17*(ROW(Data!Y453)-434),0))) -> 1982.74 | X68: =SUM((OFFSET(Data!$I$410,17*(ROW(Data!Y453)-434),0)):(OFFSET(Data!$I$423,17*(ROW(Data!Y453)-434),0))) -> 996.7 | Y68: =W68+X68 -> 2979.44 | Z68: =(OFFSET(Data!$F$412,17*(ROW(Data!Y453)-434),0)) -> 111.98 | AA68: =(OFFSET(Data!$F$411,17*(ROW(Data!Y453)-434),0)) -> 273.81 | AB68: =Data!I741 -> 160 | AC68: =AE68-AB68 -> 836.7 | AD68: =SUM((OFFSET(Data!$F$410,17*(ROW(Data!Y453)-434),0)):(OFFSET(Data!$F$423,17*(ROW(Data!Y453)-434),0))) -> 1982.74 | AE68: =SUM((OFFSET(Data!$I$410,17*(ROW(Data!Y453)-434),0)):(OFFSET(Data!$I$423,17*(ROW(Data!Y453)-434),0))) -> 996.7 | AF68: =AD68+AE68 -> 2979.44 | AG68: =C68-AF68 -> 1759.31 | AH68: =D68-D67 -> 1759.31 | AI68: =C68-R68 -> 1742.6987 | AJ68: =K68-K67 -> 1742.6987 | AK68: =AG68-AH68 -> 0 | AL68: =AI68-AJ68 -> 0 | AM68: =AG68-AG67 -> 1736.2 | AN68: =AH68-AH67 -> 1736.2 | AO68: =AJ68-AJ67 -> 1517.4903 | AP68: =AN68-AM68 -> 0 | AQ68: =AO68-AN68 -> -218.7097 | AR68: =K68-D68 -> 1050.1897 | AS68: =AI68-AG68 -> -16.611285 | AT68: =AJ68-AH68 -> -16.611285 | AU68: =ABS(AR68/K68) -> 0.12936929 | AV68: =ABS(AS68/AI68) -> 0.0095319316 | AW68: =ABS(AR68/AVERAGE(K68,D68)) -> 0.13831622 | AX68: =ABS((AG68-AH68)/AVERAGE(AG68,AH68)) -> 2.5848051e-16 | AZ68: =Data!S744 -> 426.91 | BA68: =Data!T744 -> 0.15858234 | BB68: =Data!U744 -> 15.67314 | BC68: =Data!V747 -> 0 | BD68: =Data!S745 -> 587.79 | BE68: =Data!T745 -> 0.13536905 | BF68: =Data!U745 -> 272.25388 | BG68: =Data!V745 -> 7.7110761 | BH68: =Data!S746 -> 1014.7 | BI68: =Data!T746 -> 0.14425298 | BJ68: =Data!U746 -> 287.92702 | BK68: =Data!V746 -> 0.25134392 | BL68: =Data!W746 -> 1302.627 | BM68: =Data!X746 -> 0.15925081 | BP68: =ABS((AR69-AS69)/((ABS(AR69)+ABS(AS69))/2))/10 -> 0.088409984
B69: 45901 | C69: =SUM((OFFSET(Data!$C$410,17*(ROW(Data!Y454)-434),0)):(OFFSET(Data!$C$423,17*(ROW(Data!Y454)-434),0))) -> 5292.21 | D69: =(OFFSET(Data!$P$409,17*(ROW(Data!Y454)-434),0)) -> 8252.8573 | E69: =(OFFSET(Data!$P$412,17*(ROW(Data!Y454)-434),0)) -> 1221.56 | F69: =(OFFSET(Data!$P$418,17*(ROW(Data!Y454)-434),0)) -> 1063.88 | G69: =(OFFSET(Data!$P$415,17*(ROW(Data!Y454)-434),0)) -> 535 | H69: =(OFFSET(Data!$P$421,17*(ROW(Data!Y454)-434),0)) -> 5432.4173 | K69: =(OFFSET(Data!$Q$409,17*(ROW(Data!Y454)-434),0)) -> 9965.8154 | L69: =(OFFSET(Data!$Q$412,17*(ROW(Data!Y454)-434),0)) -> 1802.93 | M69: =(OFFSET(Data!$Q$415,17*(ROW(Data!Y454)-434),0)) -> 480 | N69: =(OFFSET(Data!$Q$418,17*(ROW(Data!Y454)-434),0)) -> 1066.67 | O69: =(OFFSET(Data!$U$410,17*(ROW(Data!Y454)-434),0)) -> 251.67542 | P69: =(OFFSET(Data!$S$410,17*(ROW(Data!Y454)-434),0)) -> 6364.54 | Q69: =(OFFSET(Data!$Q$421,17*(ROW(Data!Y454)-434),0)) -> 6616.2154 | R69: =K68-K69+C69 -> 3444.1616 | S69: 150 | T69: 400 | U69: 0 | V69: 200 | W69: =SUM((OFFSET(Data!$F$410,17*(ROW(Data!Y454)-434),0)):(OFFSET(Data!$F$423,17*(ROW(Data!Y454)-434),0))) -> 2680.99 | X69: =SUM((OFFSET(Data!$I$410,17*(ROW(Data!Y454)-434),0)):(OFFSET(Data!$I$423,17*(ROW(Data!Y454)-434),0))) -> 1425.94 | Y69: =W69+X69 -> 4106.93 | Z69: =(OFFSET(Data!$F$412,17*(ROW(Data!Y454)-434),0)) -> 77.73 | AA69: =(OFFSET(Data!$F$411,17*(ROW(Data!Y454)-434),0)) -> 254.92 | AB69: =Data!I759 -> 240 | AC69: =AE69-AB69 -> 1185.94 | AD69: =SUM((OFFSET(Data!$F$410,17*(ROW(Data!Y454)-434),0)):(OFFSET(Data!$F$423,17*(ROW(Data!Y454)-434),0))) -> 2680.99 | AE69: =SUM((OFFSET(Data!$I$410,17*(ROW(Data!Y454)-434),0)):(OFFSET(Data!$I$423,17*(ROW(Data!Y454)-434),0))) -> 1425.94 | AF69: =AD69+AE69 -> 4106.93 | AG69: =C69-AF69 -> 1185.28 | AH69: =D69-D68 -> 1185.28 | AI69: =C69-R69 -> 1848.0484 | AJ69: =K69-K68 -> 1848.0484 | AK69: =AG69-AH69 -> 0 | AL69: =AI69-AJ69 -> 0 | AM69: =AG69-AG68 -> -574.03 | AN69: =AH69-AH68 -> -574.03 | AO69: =AJ69-AJ68 -> 105.34968 | AP69: =AN69-AM69 -> 0 | AQ69: =AO69-AN69 -> 679.37968 | AR69: =K69-D69 -> 1712.9581 | AS69: =AI69-AG69 -> 662.7684 | AT69: =AJ69-AH69 -> 662.7684 | AU69: =ABS(AR69/K69) -> 0.17188339 | AV69: =ABS(AS69/AI69) -> 0.35863152 | AW69: =ABS(AR69/AVERAGE(K69,D69)) -> 0.18804423 | AX69: =ABS((AG69-AH69)/AVERAGE(AG69,AH69)) -> 7.6732477e-16 | AZ69: =Data!S761 -> 523.15 | BA69: =Data!T761 -> 0.18983736 | BB69: =Data!U761 -> 15.67314 | BC69: =Data!V764 -> 0 | BD69: =Data!S762 -> 1135.15 | BE69: =Data!T762 -> 0.21707121 | BF69: =Data!U762 -> 286.98228 | BG69: =Data!V762 -> 8.12823 | BH69: =Data!S763 -> 1658.3 | BI69: =Data!T763 -> 0.20767247 | BJ69: =Data!U763 -> 302.65542 | BK69: =Data!V763 -> 0.26420097 | BL69: =Data!W763 -> 1960.9554 | BM69: =Data!X763 -> 0.2147646 | BP69: =ABS((AR70-AS70)/((ABS(AR70)+ABS(AS70))/2))/10 -> 0.098462238
B70: 45931 | C70: =SUM((OFFSET(Data!$C$410,17*(ROW(Data!Y455)-434),0)):(OFFSET(Data!$C$423,17*(ROW(Data!Y455)-434),0))) -> 5290.05 | D70: =(OFFSET(Data!$P$409,17*(ROW(Data!Y455)-434),0)) -> 9248.2273 | E70: =(OFFSET(Data!$P$412,17*(ROW(Data!Y455)-434),0)) -> 1459.49 | F70: =(OFFSET(Data!$P$418,17*(ROW(Data!Y455)-434),0)) -> 363.88 | G70: =(OFFSET(Data!$P$415,17*(ROW(Data!Y455)-434),0)) -> 295 | H70: =(OFFSET(Data!$P$421,17*(ROW(Data!Y455)-434),0)) -> 7129.8573 | K70: =(OFFSET(Data!$Q$409,17*(ROW(Data!Y455)-434),0)) -> 11844.417 | L70: =(OFFSET(Data!$Q$412,17*(ROW(Data!Y455)-434),0)) -> 1931.31 | M70: =(OFFSET(Data!$Q$415,17*(ROW(Data!Y455)-434),0)) -> 240 | N70: =(OFFSET(Data!$Q$418,17*(ROW(Data!Y455)-434),0)) -> 366.85 | O70: =(OFFSET(Data!$U$410,17*(ROW(Data!Y455)-434),0)) -> 242.60709 | P70: =(OFFSET(Data!$S$410,17*(ROW(Data!Y455)-434),0)) -> 9063.65 | Q70: =(OFFSET(Data!$Q$421,17*(ROW(Data!Y455)-434),0)) -> 9306.2571 | R70: =K69-K70+C70 -> 3411.4483 | S70: 150 | T70: 400 | U70: 0 | V70: 200 | W70: =SUM((OFFSET(Data!$F$410,17*(ROW(Data!Y455)-434),0)):(OFFSET(Data!$F$423,17*(ROW(Data!Y455)-434),0))) -> 2559.99 | X70: =SUM((OFFSET(Data!$I$410,17*(ROW(Data!Y455)-434),0)):(OFFSET(Data!$I$423,17*(ROW(Data!Y455)-434),0))) -> 1734.69 | Y70: =W70+X70 -> 4294.68 | Z70: =(OFFSET(Data!$F$412,17*(ROW(Data!Y455)-434),0)) -> 77.13 | AA70: =(OFFSET(Data!$F$411,17*(ROW(Data!Y455)-434),0)) -> 234.86 | AB70: =Data!I775 -> 240 | AC70: =AE70-AB70 -> 1494.69 | AD70: =SUM((OFFSET(Data!$F$410,17*(ROW(Data!Y455)-434),0)):(OFFSET(Data!$F$423,17*(ROW(Data!Y455)-434),0))) -> 2559.99 | AE70: =SUM((OFFSET(Data!$I$410,17*(ROW(Data!Y455)-434),0)):(OFFSET(Data!$I$423,17*(ROW(Data!Y455)-434),0))) -> 1734.69 | AF70: =AD70+AE70 -> 4294.68 | AG70: =C70-AF70 -> 995.37 | AH70: =D70-D69 -> 995.37 | AI70: =C70-R70 -> 1878.6017 | AJ70: =K70-K69 -> 1878.6017 | AK70: =AG70-AH70 -> 0 | AL70: =AI70-AJ70 -> 0 | AM70: =AG70-AG69 -> -189.91 | AN70: =AH70-AH69 -> -189.91 | AO70: =AJ70-AJ69 -> 30.553277 | AP70: =AN70-AM70 -> -9.094947e-13 | AQ70: =AO70-AN70 -> 220.46328 | AR70: =K70-D70 -> 2596.1898 | AS70: =AI70-AG70 -> 883.23167 | AT70: =AJ70-AH70 -> 883.23167 | AU70: =ABS(AR70/K70) -> 0.21919101 | AV70: =ABS(AS70/AI70) -> 0.47015378 | AW70: =ABS(AR70/AVERAGE(K70,D70)) -> 0.24617016 | AX70: =ABS((AG70-AH70)/AVERAGE(AG70,AH70)) -> 0 | AZ70: =Data!S778 -> 823.07 | BA70: =Data!T778 -> 0.28325269 | BB70: =Data!U778 -> 15.67314 | BC70: =Data!V781 -> 0 | BD70: =Data!S779 -> 1834.26 | BE70: =Data!T779 -> 0.25372265 | BF70: =Data!U779 -> 277.91395 | BG70: =Data!V779 -> 7.8713868 | BH70: =Data!S780 -> 2657.33 | BI70: =Data!T780 -> 0.26218899 | BJ70: =Data!U780 -> 293.58709 | BK70: =Data!V780 -> 0.25628484 | BL70: =Data!W780 -> 2950.9171 | BM70: =Data!X780 -> 0.26158943 | BP70: =ABS((AR71-AS71)/((ABS(AR71)+ABS(AS71))/2))/10 -> 0.2
B71: 45962 | C71: =SUM((OFFSET(Data!$C$410,17*(ROW(Data!Y456)-434),0)):(OFFSET(Data!$C$423,17*(ROW(Data!Y456)-434),0))) -> 5289.95 | D71: =(OFFSET(Data!$P$409,17*(ROW(Data!Y456)-434),0)) -> 10014.807 | E71: =(OFFSET(Data!$P$412,17*(ROW(Data!Y456)-434),0)) -> 884.89 | F71: =(OFFSET(Data!$P$418,17*(ROW(Data!Y456)-434),0)) -> 508.88 | G71: =(OFFSET(Data!$P$415,17*(ROW(Data!Y456)-434),0)) -> 135 | H71: =(OFFSET(Data!$P$421,17*(ROW(Data!Y456)-434),0)) -> 8486.0373 | K71: =(OFFSET(Data!$Q$409,17*(ROW(Data!Y456)-434),0)) -> 11578.015 | L71: =(OFFSET(Data!$Q$412,17*(ROW(Data!Y456)-434),0)) -> 1727.55 | M71: =(OFFSET(Data!$Q$415,17*(ROW(Data!Y456)-434),0)) -> 80 | N71: =(OFFSET(Data!$Q$418,17*(ROW(Data!Y456)-434),0)) -> 511.9 | O71: =(OFFSET(Data!$U$410,17*(ROW(Data!Y456)-434),0)) -> 189.35494 | P71: =(OFFSET(Data!$S$410,17*(ROW(Data!Y456)-434),0)) -> 9069.21 | Q71: =(OFFSET(Data!$Q$421,17*(ROW(Data!Y456)-434),0)) -> 9258.5649 | R71: =K70-K71+C71 -> 5556.3522 | S71: 150 | T71: 400 | U71: 0 | V71: 200 | W71: =SUM((OFFSET(Data!$F$410,17*(ROW(Data!Y456)-434),0)):(OFFSET(Data!$F$423,17*(ROW(Data!Y456)-434),0))) -> 2722.08 | X71: =SUM((OFFSET(Data!$I$410,17*(ROW(Data!Y456)-434),0)):(OFFSET(Data!$I$423,17*(ROW(Data!Y456)-434),0))) -> 1801.29 | Y71: =W71+X71 -> 4523.37 | Z71: =(OFFSET(Data!$F$412,17*(ROW(Data!Y456)-434),0)) -> 37.71 | AA71: =(OFFSET(Data!$F$411,17*(ROW(Data!Y456)-434),0)) -> 209.14 | AB71: =Data!I792 -> 260 | AC71: =AE71-AB71 -> 1541.29 | AD71: =SUM((OFFSET(Data!$F$410,17*(ROW(Data!Y456)-434),0)):(OFFSET(Data!$F$423,17*(ROW(Data!Y456)-434),0))) -> 2722.08 | AE71: =SUM((OFFSET(Data!$I$410,17*(ROW(Data!Y456)-434),0)):(OFFSET(Data!$I$423,17*(ROW(Data!Y456)-434),0))) -> 1801.29 | AF71: =AD71+AE71 -> 4523.37 | AG71: =C71-AF71 -> 766.58 | AH71: =D71-D70 -> 766.58 | AI71: =C71-R71 -> -266.40215 | AJ71: =K71-K70 -> -266.40215 | AK71: =AG71-AH71 -> -1.8189894e-12 | AL71: =AI71-AJ71 -> 0 | AM71: =AG71-AG70 -> -228.79 | AN71: =AH71-AH70 -> -228.79 | AO71: =AJ71-AJ70 -> -2145.0038 | AP71: =AN71-AM71 -> 1.8189894e-12 | AQ71: =AO71-AN71 -> -1916.2138 | AR71: =K71-D71 -> 1563.2076 | AS71: =AI71-AG71 -> -1032.9822 | AT71: =AJ71-AH71 -> -1032.9822 | AU71: =ABS(AR71/K71) -> 0.13501517 | AV71: =ABS(AS71/AI71) -> 3.8775293 | AW71: =ABS(AR71/AVERAGE(K71,D71)) -> 0.14478956 | AX71: =ABS((AG71-AH71)/AVERAGE(AG71,AH71)) -> 2.3728631e-15 | AZ71: =Data!S795 -> 1070.02 | BA71: =Data!T795 -> 0.28254188 | BB71: =Data!U795 -> 15.67314 | BC71: =Data!V798 -> 0 | BD71: =Data!S796 -> 551.16 | BE71: =Data!T796 -> 0.06470495 | BF71: =Data!U796 -> 224.6618 | BG71: =Data!V796 -> 6.3631204 | BH71: =Data!S797 -> 1621.18 | BI71: =Data!T797 -> 0.13174788 | BJ71: =Data!U797 -> 240.33494 | BK71: =Data!V797 -> 0.20979874 | BL71: =Data!W797 -> 1861.5149 | BM71: =Data!X797 -> 0.13839519 | BP71: =ABS((AR72-AS72)/((ABS(AR72)+ABS(AS72))/2))/10 -> 0.17975219
B72: 45992 | C72: =SUM((OFFSET(Data!$C$410,17*(ROW(Data!Y457)-434),0)):(OFFSET(Data!$C$423,17*(ROW(Data!Y457)-434),0))) -> 5284.96 | D72: =(OFFSET(Data!$P$409,17*(ROW(Data!Y457)-434),0)) -> 10186.287 | E72: =(OFFSET(Data!$P$412,17*(ROW(Data!Y457)-434),0)) -> 387.99 | F72: =(OFFSET(Data!$P$418,17*(ROW(Data!Y457)-434),0)) -> 158.88 | G72: =(OFFSET(Data!$P$415,17*(ROW(Data!Y457)-434),0)) -> 135 | H72: =(OFFSET(Data!$P$421,17*(ROW(Data!Y457)-434),0)) -> 9504.4173 | K72: =(OFFSET(Data!$Q$409,17*(ROW(Data!Y457)-434),0)) -> 11837.537 | L72: =(OFFSET(Data!$Q$412,17*(ROW(Data!Y457)-434),0)) -> 1319.84 | M72: =(OFFSET(Data!$Q$415,17*(ROW(Data!Y457)-434),0)) -> 80 | N72: =(OFFSET(Data!$Q$418,17*(ROW(Data!Y457)-434),0)) -> 161.97 | O72: =(OFFSET(Data!$U$410,17*(ROW(Data!Y457)-434),0)) -> 192.57709 | P72: =(OFFSET(Data!$S$410,17*(ROW(Data!Y457)-434),0)) -> 10083.15 | Q72: =(OFFSET(Data!$Q$421,17*(ROW(Data!Y457)-434),0)) -> 10275.727 | R72: =K71-K72+C72 -> 5025.4379 | S72: 150 | T72: 400 | U72: 0 | V72: 200 | W72: =SUM((OFFSET(Data!$F$410,17*(ROW(Data!Y457)-434),0)):(OFFSET(Data!$F$423,17*(ROW(Data!Y457)-434),0))) -> 3070.88 | X72: =SUM((OFFSET(Data!$I$410,17*(ROW(Data!Y457)-434),0)):(OFFSET(Data!$I$423,17*(ROW(Data!Y457)-434),0))) -> 2042.6 | Y72: =W72+X72 -> 5113.48 | Z72: =(OFFSET(Data!$F$412,17*(ROW(Data!Y457)-434),0)) -> 72.79 | AA72: =(OFFSET(Data!$F$411,17*(ROW(Data!Y457)-434),0)) -> 154.29 | AB72: =Data!I810 -> 560 | AC72: =AE72-AB72 -> 1482.6 | AD72: =SUM((OFFSET(Data!$F$410,17*(ROW(Data!Y457)-434),0)):(OFFSET(Data!$F$423,17*(ROW(Data!Y457)-434),0))) -> 3070.88 | AE72: =SUM((OFFSET(Data!$I$410,17*(ROW(Data!Y457)-434),0)):(OFFSET(Data!$I$423,17*(ROW(Data!Y457)-434),0))) -> 2042.6 | AF72: =AD72+AE72 -> 5113.48 | AG72: =C72-AF72 -> 171.48 | AH72: =D72-D71 -> 171.48 | AI72: =C72-R72 -> 259.52215 | AJ72: =K72-K71 -> 259.52215 | AK72: =AG72-AH72 -> 1.8189894e-12 | AL72: =AI72-AJ72 -> 0 | AM72: =AG72-AG71 -> -595.1 | AN72: =AH72-AH71 -> -595.1 | AO72: =AJ72-AJ71 -> 525.9243 | AP72: =AN72-AM72 -> -3.6379788e-12 | AQ72: =AO72-AN72 -> 1121.0243 | AR72: =K72-D72 -> 1651.2498 | AS72: =AI72-AG72 -> 88.042148 | AT72: =AJ72-AH72 -> 88.042148 | AU72: =ABS(AR72/K72) -> 0.13949268 | AV72: =ABS(AS72/AI72) -> 0.33924715 | AW72: =ABS(AR72/AVERAGE(K72,D72)) -> 0.14995123 | AX72: =ABS((AG72-AH72)/AVERAGE(AG72,AH72)) -> 1.0607589e-14 | AZ72: =Data!S812 -> 1181.57 | BA72: =Data!T812 -> 0.27793799 | BB72: =Data!U812 -> 15.67314 | BC72: =Data!V815 -> 0 | BD72: =Data!S813 -> 499.12 | BE72: =Data!T813 -> 0.052078301 | BF72: =Data!U813 -> 227.88395 | BG72: =Data!V813 -> 6.4543817 | BH72: =Data!S814 -> 1680.69 | BI72: =Data!T814 -> 0.12147901 | BJ72: =Data!U814 -> 243.55709 | BK72: =Data!V814 -> 0.21261149 | BL72: =Data!W814 -> 1924.2471 | BM72: =Data!X814 -> 0.12844772 | BP72: =ABS((AR73-AS73)/((ABS(AR73)+ABS(AS73))/2))/10 -> 0.12866226
B73: 46023 | C73: =SUM((OFFSET(Data!$C$410,17*(ROW(Data!Y458)-434),0)):(OFFSET(Data!$C$423,17*(ROW(Data!Y458)-434),0))) -> 4949.02 | D73: =(OFFSET(Data!$P$409,17*(ROW(Data!Y458)-434),0)) -> 10659.787 | E73: =(OFFSET(Data!$P$412,17*(ROW(Data!Y458)-434),0)) -> 943.47 | F73: =(OFFSET(Data!$P$418,17*(ROW(Data!Y458)-434),0)) -> 8.88 | G73: =(OFFSET(Data!$P$415,17*(ROW(Data!Y458)-434),0)) -> 135 | H73: =(OFFSET(Data!$P$421,17*(ROW(Data!Y458)-434),0)) -> 9572.4373 | K73: =(OFFSET(Data!$Q$409,17*(ROW(Data!Y458)-434),0)) -> 12768.811 | L73: =(OFFSET(Data!$Q$412,17*(ROW(Data!Y458)-434),0)) -> 1887.53 | M73: =(OFFSET(Data!$Q$415,17*(ROW(Data!Y458)-434),0)) -> 80 | N73: =(OFFSET(Data!$Q$418,17*(ROW(Data!Y458)-434),0)) -> 12.01 | O73: =(OFFSET(Data!$U$410,17*(ROW(Data!Y458)-434),0)) -> 173.65091 | P73: =(OFFSET(Data!$S$410,17*(ROW(Data!Y458)-434),0)) -> 10615.62 | Q73: =(OFFSET(Data!$Q$421,17*(ROW(Data!Y458)-434),0)) -> 10789.271 | R73: =K72-K73+C73 -> 4017.7462 | S73: 150 | T73: 400 | U73: 0 | V73: 200 | W73: =SUM((OFFSET(Data!$F$410,17*(ROW(Data!Y458)-434),0)):(OFFSET(Data!$F$423,17*(ROW(Data!Y458)-434),0))) -> 2714.77 | X73: =SUM((OFFSET(Data!$I$410,17*(ROW(Data!Y458)-434),0)):(OFFSET(Data!$I$423,17*(ROW(Data!Y458)-434),0))) -> 1760.75 | Y73: =W73+X73 -> 4475.52 | Z73: =(OFFSET(Data!$F$412,17*(ROW(Data!Y458)-434),0)) -> 71.91 | AA73: =(OFFSET(Data!$F$411,17*(ROW(Data!Y458)-434),0)) -> 105.61 | AB73: =Data!I827 -> 485 | AC73: =AE73-AB73 -> 1275.75 | AD73: =SUM((OFFSET(Data!$F$410,17*(ROW(Data!Y458)-434),0)):(OFFSET(Data!$F$423,17*(ROW(Data!Y458)-434),0))) -> 2714.77 | AE73: =SUM((OFFSET(Data!$I$410,17*(ROW(Data!Y458)-434),0)):(OFFSET(Data!$I$423,17*(ROW(Data!Y458)-434),0))) -> 1760.75 | AF73: =AD73+AE73 -> 4475.52 | AG73: =C73-AF73 -> 473.5 | AH73: =D73-D72 -> 473.5 | AI73: =C73-R73 -> 931.27382 | AJ73: =K73-K72 -> 931.27382 | AK73: =AG73-AH73 -> -1.8189894e-12 | AL73: =AI73-AJ73 -> 0 | AM73: =AG73-AG72 -> 302.02 | AN73: =AH73-AH72 -> 302.02 | AO73: =AJ73-AJ72 -> 671.75167 | AP73: =AN73-AM73 -> 3.6379788e-12 | AQ73: =AO73-AN73 -> 369.73167 | AR73: =K73-D73 -> 2109.0236 | AS73: =AI73-AG73 -> 457.77382 | AT73: =AJ73-AH73 -> 457.77382 | AU73: =ABS(AR73/K73) -> 0.16516993 | AV73: =ABS(AS73/AI73) -> 0.49155663 | AW73: =ABS(AR73/AVERAGE(K73,D73)) -> 0.18003839 | AX73: =ABS((AG73-AH73)/AVERAGE(AG73,AH73)) -> 3.8415827e-15 | AZ73: =Data!S829 -> 1181.57 | BA73: =Data!T829 -> 0.27793799 | BB73: =Data!U829 -> 15.67314 | BC73: =Data!V832 -> 0 | BD73: =Data!S830 -> 909.42 | BE73: =Data!T830 -> 0.093694752 | BF73: =Data!U830 -> 208.95777 | BG73: =Data!V830 -> 5.9183333 | BH73: =Data!S831 -> 2090.99 | BI73: =Data!T831 -> 0.14981229 | BJ73: =Data!U831 -> 224.63091 | BK73: =Data!V831 -> 0.19609001 | BL73: =Data!W831 -> 2315.6209 | BM73: =Data!X831 -> 0.15332242 | BP73: =ABS((AR74-AS74)/((ABS(AR74)+ABS(AS74))/2))/10 -> 0.2
B74: 46054 | C74: =SUM((OFFSET(Data!$C$410,17*(ROW(Data!Y459)-434),0)):(OFFSET(Data!$C$423,17*(ROW(Data!Y459)-434),0))) -> 4830.78 | D74: =(OFFSET(Data!$P$409,17*(ROW(Data!Y459)-434),0)) -> 11074.437 | E74: =(OFFSET(Data!$P$412,17*(ROW(Data!Y459)-434),0)) -> 918.1 | F74: =(OFFSET(Data!$P$418,17*(ROW(Data!Y459)-434),0)) -> 108.88 | G74: =(OFFSET(Data!$P$415,17*(ROW(Data!Y459)-434),0)) -> 135 | H74: =(OFFSET(Data!$P$421,17*(ROW(Data!Y459)-434),0)) -> 9912.4573 | K74: =(OFFSET(Data!$Q$409,17*(ROW(Data!Y459)-434),0)) -> 11384.588 | L74: =(OFFSET(Data!$Q$412,17*(ROW(Data!Y459)-434),0)) -> 283.66 | M74: =(OFFSET(Data!$Q$415,17*(ROW(Data!Y459)-434),0)) -> 80 | N74: =(OFFSET(Data!$Q$418,17*(ROW(Data!Y459)-434),0)) -> 112.01 | O74: =(OFFSET(Data!$U$410,17*(ROW(Data!Y459)-434),0)) -> 153.56757 | P74: =(OFFSET(Data!$S$410,17*(ROW(Data!Y459)-434),0)) -> 10755.35 | Q74: =(OFFSET(Data!$Q$421,17*(ROW(Data!Y459)-434),0)) -> 10908.918 | R74: =K73-K74+C74 -> 6215.0033 | S74: 150 | T74: 400 | U74: 0 | V74: 200 | W74: =SUM((OFFSET(Data!$F$410,17*(ROW(Data!Y459)-434),0)):(OFFSET(Data!$F$423,17*(ROW(Data!Y459)-434),0))) -> 2884.17 | X74: =SUM((OFFSET(Data!$I$410,17*(ROW(Data!Y459)-434),0)):(OFFSET(Data!$I$423,17*(ROW(Data!Y459)-434),0))) -> 1531.96 | Y74: =W74+X74 -> 4416.13 | Z74: =(OFFSET(Data!$F$412,17*(ROW(Data!Y459)-434),0)) -> 0 | AA74: =(OFFSET(Data!$F$411,17*(ROW(Data!Y459)-434),0)) -> 62.83 | AB74: 0 | AC74: =AE74-AB74 -> 1531.96 | AD74: =SUM((OFFSET(Data!$F$410,17*(ROW(Data!Y459)-434),0)):(OFFSET(Data!$F$423,17*(ROW(Data!Y459)-434),0))) -> 2884.17 | AE74: =SUM((OFFSET(Data!$I$410,17*(ROW(Data!Y459)-434),0)):(OFFSET(Data!$I$423,17*(ROW(Data!Y459)-434),0))) -> 1531.96 | AF74: =AD74+AE74 -> 4416.13 | AG74: =C74-AF74 -> 414.65 | AH74: =D74-D73 -> 414.65 | AI74: =C74-R74 -> -1384.2233 | AJ74: =K74-K73 -> -1384.2233 | AK74: =AG74-AH74 -> 0 | AL74: =AI74-AJ74 -> 0 | AM74: =AG74-AG73 -> -58.85 | AN74: =AH74-AH73 -> -58.85 | AO74: =AJ74-AJ73 -> -2315.4971 | AP74: =AN74-AM74 -> -1.8189894e-12 | AQ74: =AO74-AN74 -> -2256.6471 | AR74: =K74-D74 -> 310.15027 | AS74: =AI74-AG74 -> -1798.8733 | AT74: =AJ74-AH74 -> -1798.8733 | AU74: =ABS(AR74/K74) -> 0.027242996 | AV74: =ABS(AS74/AI74) -> 1.2995543 | AW74: =ABS(AR74/AVERAGE(K74,D74)) -> 0.027619211 | AX74: =ABS((AG74-AH74)/AVERAGE(AG74,AH74)) -> 0
B75: 46082 | C75: =SUM((OFFSET(Data!$C$410,17*(ROW(Data!Y460)-434),0)):(OFFSET(Data!$C$423,17*(ROW(Data!Y460)-434),0))) -> 4775.66 | D75: =(OFFSET(Data!$P$409,17*(ROW(Data!Y460)-434),0)) -> 11136.677 | E75: =(OFFSET(Data!$P$412,17*(ROW(Data!Y460)-434),0)) -> 430.34 | F75: =(OFFSET(Data!$P$418,17*(ROW(Data!Y460)-434),0)) -> 258.88 | G75: =(OFFSET(Data!$P$415,17*(ROW(Data!Y460)-434),0)) -> 335 | H75: =(OFFSET(Data!$P$421,17*(ROW(Data!Y460)-434),0)) -> 10112.457 | R75: =K74-K75+C75 -> 16160.248 | S75: 150 | T75: 400 | U75: 0 | V75: 200 | W75: =SUM((OFFSET(Data!$F$410,17*(ROW(Data!Y460)-434),0)):(OFFSET(Data!$F$423,17*(ROW(Data!Y460)-434),0))) -> 3330.75 | X75: =SUM((OFFSET(Data!$I$410,17*(ROW(Data!Y460)-434),0)):(OFFSET(Data!$I$423,17*(ROW(Data!Y460)-434),0))) -> 1382.67 | Y75: =W75+X75 -> 4713.42 | Z75: =(OFFSET(Data!$F$412,17*(ROW(Data!Y460)-434),0)) -> 100 | AA75: =(OFFSET(Data!$F$411,17*(ROW(Data!Y460)-434),0)) -> 400 | AM75: =AG75-AG74 -> -414.65 | AN75: =AH75-AH74 -> -414.65 | AO75: =AJ75-AJ74 -> 1384.2233 | AP75: =AN75-AM75 -> 0 | AQ75: =AO75-AN75 -> 1798.8733
B76: 46113 | C76: =SUM((OFFSET(Data!$C$410,17*(ROW(Data!Y461)-434),0)):(OFFSET(Data!$C$423,17*(ROW(Data!Y461)-434),0))) -> 4775.66 | D76: =(OFFSET(Data!$P$409,17*(ROW(Data!Y461)-434),0)) -> 11825.707 | E76: =(OFFSET(Data!$P$412,17*(ROW(Data!Y461)-434),0)) -> 569.37 | F76: =(OFFSET(Data!$P$418,17*(ROW(Data!Y461)-434),0)) -> 408.88 | G76: =(OFFSET(Data!$P$415,17*(ROW(Data!Y461)-434),0)) -> 535 | H76: =(OFFSET(Data!$P$421,17*(ROW(Data!Y461)-434),0)) -> 10312.457 | R76: =K75-K76+C76 -> 4775.66 | S76: 150 | T76: 400 | U76: 0 | V76: 200 | W76: =SUM((OFFSET(Data!$F$410,17*(ROW(Data!Y461)-434),0)):(OFFSET(Data!$F$423,17*(ROW(Data!Y461)-434),0))) -> 3330.75 | X76: =SUM((OFFSET(Data!$I$410,17*(ROW(Data!Y461)-434),0)):(OFFSET(Data!$I$423,17*(ROW(Data!Y461)-434),0))) -> 755.88 | Y76: =W76+X76 -> 4086.63 | Z76: =(OFFSET(Data!$F$412,17*(ROW(Data!Y461)-434),0)) -> 100 | AA76: =(OFFSET(Data!$F$411,17*(ROW(Data!Y461)-434),0)) -> 400 | AM76: =AG76-AG75 -> 0 | AN76: =AH76-AH75 -> 0 | AO76: =AJ76-AJ75 -> 0 | AP76: =AN76-AM76 -> 0 | AQ76: =AO76-AN76 -> 0
B77: 46143 | C77: =SUM((OFFSET(Data!$C$410,17*(ROW(Data!Y462)-434),0)):(OFFSET(Data!$C$423,17*(ROW(Data!Y462)-434),0))) -> 4775.66 | D77: =(OFFSET(Data!$P$409,17*(ROW(Data!Y462)-434),0)) -> 12514.737 | E77: =(OFFSET(Data!$P$412,17*(ROW(Data!Y462)-434),0)) -> 708.4 | F77: =(OFFSET(Data!$P$418,17*(ROW(Data!Y462)-434),0)) -> 558.88 | G77: =(OFFSET(Data!$P$415,17*(ROW(Data!Y462)-434),0)) -> 735 | H77: =(OFFSET(Data!$P$421,17*(ROW(Data!Y462)-434),0)) -> 10512.457 | R77: =K76-K77+C77 -> 4775.66 | S77: 150 | T77: 400 | U77: 0 | V77: 200 | W77: =SUM((OFFSET(Data!$F$410,17*(ROW(Data!Y462)-434),0)):(OFFSET(Data!$F$423,17*(ROW(Data!Y462)-434),0))) -> 3330.75 | X77: =SUM((OFFSET(Data!$I$410,17*(ROW(Data!Y462)-434),0)):(OFFSET(Data!$I$423,17*(ROW(Data!Y462)-434),0))) -> 755.88 | Y77: =W77+X77 -> 4086.63 | Z77: =(OFFSET(Data!$F$412,17*(ROW(Data!Y462)-434),0)) -> 100 | AA77: =(OFFSET(Data!$F$411,17*(ROW(Data!Y462)-434),0)) -> 400 | AM77: =AG77-AG76 -> 0 | AN77: =AH77-AH76 -> 0 | AO77: =AJ77-AJ76 -> 0 | AP77: =AN77-AM77 -> 0 | AQ77: =AO77-AN77 -> 0
B78: 46174 | C78: =SUM((OFFSET(Data!$C$410,17*(ROW(Data!Y463)-434),0)):(OFFSET(Data!$C$423,17*(ROW(Data!Y463)-434),0))) -> 4775.66 | D78: =(OFFSET(Data!$P$409,17*(ROW(Data!Y463)-434),0)) -> 13203.767 | E78: =(OFFSET(Data!$P$412,17*(ROW(Data!Y463)-434),0)) -> 847.43 | F78: =(OFFSET(Data!$P$418,17*(ROW(Data!Y463)-434),0)) -> 708.88 | G78: =(OFFSET(Data!$P$415,17*(ROW(Data!Y463)-434),0)) -> 935 | H78: =(OFFSET(Data!$P$421,17*(ROW(Data!Y463)-434),0)) -> 10712.457 | R78: =K77-K78+C78 -> 4775.66 | S78: 150 | T78: 400 | U78: 0 | V78: 200 | W78: =SUM((OFFSET(Data!$F$410,17*(ROW(Data!Y463)-434),0)):(OFFSET(Data!$F$423,17*(ROW(Data!Y463)-434),0))) -> 3330.75 | X78: =SUM((OFFSET(Data!$I$410,17*(ROW(Data!Y463)-434),0)):(OFFSET(Data!$I$423,17*(ROW(Data!Y463)-434),0))) -> 755.88 | Y78: =W78+X78 -> 4086.63 | Z78: =(OFFSET(Data!$F$412,17*(ROW(Data!Y463)-434),0)) -> 100 | AA78: =(OFFSET(Data!$F$411,17*(ROW(Data!Y463)-434),0)) -> 400 | AM78: =AG78-AG77 -> 0 | AN78: =AH78-AH77 -> 0 | AO78: =AJ78-AJ77 -> 0 | AP78: =AN78-AM78 -> 0 | AQ78: =AO78-AN78 -> 0
B79: 46204 | C79: =SUM((OFFSET(Data!$C$410,17*(ROW(Data!Y464)-434),0)):(OFFSET(Data!$C$423,17*(ROW(Data!Y464)-434),0))) -> 4775.66 | D79: =(OFFSET(Data!$P$409,17*(ROW(Data!Y464)-434),0)) -> 13892.797 | E79: =(OFFSET(Data!$P$412,17*(ROW(Data!Y464)-434),0)) -> 986.46 | F79: =(OFFSET(Data!$P$418,17*(ROW(Data!Y464)-434),0)) -> 858.88 | G79: =(OFFSET(Data!$P$415,17*(ROW(Data!Y464)-434),0)) -> 1135 | H79: =(OFFSET(Data!$P$421,17*(ROW(Data!Y464)-434),0)) -> 10912.457 | R79: =K78-K79+C79 -> 4775.66 | S79: 150 | T79: 400 | U79: 0 | V79: 200 | W79: =SUM((OFFSET(Data!$F$410,17*(ROW(Data!Y464)-434),0)):(OFFSET(Data!$F$423,17*(ROW(Data!Y464)-434),0))) -> 3330.75 | X79: =SUM((OFFSET(Data!$I$410,17*(ROW(Data!Y464)-434),0)):(OFFSET(Data!$I$423,17*(ROW(Data!Y464)-434),0))) -> 755.88 | Y79: =W79+X79 -> 4086.63 | Z79: =(OFFSET(Data!$F$412,17*(ROW(Data!Y464)-434),0)) -> 100 | AA79: =(OFFSET(Data!$F$411,17*(ROW(Data!Y464)-434),0)) -> 400 | AM79: =AG79-AG78 -> 0 | AN79: =AH79-AH78 -> 0 | AO79: =AJ79-AJ78 -> 0 | AP79: =AN79-AM79 -> 0 | AQ79: =AO79-AN79 -> 0
B80: 46235 | C80: =SUM((OFFSET(Data!$C$410,17*(ROW(Data!Y465)-434),0)):(OFFSET(Data!$C$423,17*(ROW(Data!Y465)-434),0))) -> 4775.66 | D80: =(OFFSET(Data!$P$409,17*(ROW(Data!Y465)-434),0)) -> 14581.827 | E80: =(OFFSET(Data!$P$412,17*(ROW(Data!Y465)-434),0)) -> 1125.49 | F80: =(OFFSET(Data!$P$418,17*(ROW(Data!Y465)-434),0)) -> 1008.88 | G80: =(OFFSET(Data!$P$415,17*(ROW(Data!Y465)-434),0)) -> 1335 | H80: =(OFFSET(Data!$P$421,17*(ROW(Data!Y465)-434),0)) -> 11112.457 | R80: =K79-K80+C80 -> 4775.66 | S80: 150 | T80: 400 | U80: 0 | V80: 200 | W80: =SUM((OFFSET(Data!$F$410,17*(ROW(Data!Y465)-434),0)):(OFFSET(Data!$F$423,17*(ROW(Data!Y465)-434),0))) -> 3330.75 | X80: =SUM((OFFSET(Data!$I$410,17*(ROW(Data!Y465)-434),0)):(OFFSET(Data!$I$423,17*(ROW(Data!Y465)-434),0))) -> 755.88 | Y80: =W80+X80 -> 4086.63 | Z80: =(OFFSET(Data!$F$412,17*(ROW(Data!Y465)-434),0)) -> 100 | AA80: =(OFFSET(Data!$F$411,17*(ROW(Data!Y465)-434),0)) -> 400 | AM80: =AG80-AG79 -> 0 | AN80: =AH80-AH79 -> 0 | AO80: =AJ80-AJ79 -> 0 | AP80: =AN80-AM80 -> 0 | AQ80: =AO80-AN80 -> 0
B81: 46266 | C81: =SUM((OFFSET(Data!$C$410,17*(ROW(Data!Y466)-434),0)):(OFFSET(Data!$C$423,17*(ROW(Data!Y466)-434),0))) -> 4775.66 | D81: =(OFFSET(Data!$P$409,17*(ROW(Data!Y466)-434),0)) -> 15270.857 | E81: =(OFFSET(Data!$P$412,17*(ROW(Data!Y466)-434),0)) -> 1264.52 | F81: =(OFFSET(Data!$P$418,17*(ROW(Data!Y466)-434),0)) -> 1158.88 | G81: =(OFFSET(Data!$P$415,17*(ROW(Data!Y466)-434),0)) -> 1535 | H81: =(OFFSET(Data!$P$421,17*(ROW(Data!Y466)-434),0)) -> 11312.457 | R81: =K80-K81+C81 -> 4775.66 | S81: 150 | T81: 400 | U81: 0 | V81: 200 | W81: =SUM((OFFSET(Data!$F$410,17*(ROW(Data!Y466)-434),0)):(OFFSET(Data!$F$423,17*(ROW(Data!Y466)-434),0))) -> 3330.75 | X81: =SUM((OFFSET(Data!$I$410,17*(ROW(Data!Y466)-434),0)):(OFFSET(Data!$I$423,17*(ROW(Data!Y466)-434),0))) -> 755.88 | Y81: =W81+X81 -> 4086.63 | Z81: =(OFFSET(Data!$F$412,17*(ROW(Data!Y466)-434),0)) -> 100 | AA81: =(OFFSET(Data!$F$411,17*(ROW(Data!Y466)-434),0)) -> 400 | AM81: =AG81-AG80 -> 0 | AN81: =AH81-AH80 -> 0 | AO81: =AJ81-AJ80 -> 0 | AP81: =AN81-AM81 -> 0 | AQ81: =AO81-AN81 -> 0
B82: 46296 | C82: =SUM((OFFSET(Data!$C$410,17*(ROW(Data!Y467)-434),0)):(OFFSET(Data!$C$423,17*(ROW(Data!Y467)-434),0))) -> 4775.66 | D82: =(OFFSET(Data!$P$409,17*(ROW(Data!Y467)-434),0)) -> 15959.887 | E82: =(OFFSET(Data!$P$412,17*(ROW(Data!Y467)-434),0)) -> 1403.55 | F82: =(OFFSET(Data!$P$418,17*(ROW(Data!Y467)-434),0)) -> 1308.88 | G82: =(OFFSET(Data!$P$415,17*(ROW(Data!Y467)-434),0)) -> 1735 | H82: =(OFFSET(Data!$P$421,17*(ROW(Data!Y467)-434),0)) -> 11512.457 | R82: =K81-K82+C82 -> 4775.66 | S82: 150 | T82: 400 | U82: 0 | V82: 200 | W82: =SUM((OFFSET(Data!$F$410,17*(ROW(Data!Y467)-434),0)):(OFFSET(Data!$F$423,17*(ROW(Data!Y467)-434),0))) -> 3330.75 | X82: =SUM((OFFSET(Data!$I$410,17*(ROW(Data!Y467)-434),0)):(OFFSET(Data!$I$423,17*(ROW(Data!Y467)-434),0))) -> 755.88 | Y82: =W82+X82 -> 4086.63 | Z82: =(OFFSET(Data!$F$412,17*(ROW(Data!Y467)-434),0)) -> 100 | AA82: =(OFFSET(Data!$F$411,17*(ROW(Data!Y467)-434),0)) -> 400 | AM82: =AG82-AG81 -> 0 | AN82: =AH82-AH81 -> 0 | AO82: =AJ82-AJ81 -> 0 | AP82: =AN82-AM82 -> 0 | AQ82: =AO82-AN82 -> 0
B83: 46327 | C83: =SUM((OFFSET(Data!$C$410,17*(ROW(Data!Y468)-434),0)):(OFFSET(Data!$C$423,17*(ROW(Data!Y468)-434),0))) -> 4775.66 | D83: =(OFFSET(Data!$P$409,17*(ROW(Data!Y468)-434),0)) -> 16648.917 | E83: =(OFFSET(Data!$P$412,17*(ROW(Data!Y468)-434),0)) -> 1542.58 | F83: =(OFFSET(Data!$P$418,17*(ROW(Data!Y468)-434),0)) -> 1458.88 | G83: =(OFFSET(Data!$P$415,17*(ROW(Data!Y468)-434),0)) -> 1935 | H83: =(OFFSET(Data!$P$421,17*(ROW(Data!Y468)-434),0)) -> 11712.457 | R83: =K82-K83+C83 -> 4775.66 | S83: 150 | T83: 400 | U83: 0 | V83: 200 | W83: =SUM((OFFSET(Data!$F$410,17*(ROW(Data!Y468)-434),0)):(OFFSET(Data!$F$423,17*(ROW(Data!Y468)-434),0))) -> 3330.75 | X83: =SUM((OFFSET(Data!$I$410,17*(ROW(Data!Y468)-434),0)):(OFFSET(Data!$I$423,17*(ROW(Data!Y468)-434),0))) -> 755.88 | Y83: =W83+X83 -> 4086.63 | Z83: =(OFFSET(Data!$F$412,17*(ROW(Data!Y468)-434),0)) -> 100 | AA83: =(OFFSET(Data!$F$411,17*(ROW(Data!Y468)-434),0)) -> 400 | AM83: =AG83-AG82 -> 0 | AN83: =AH83-AH82 -> 0 | AO83: =AJ83-AJ82 -> 0 | AP83: =AN83-AM83 -> 0 | AQ83: =AO83-AN83 -> 0
B84: 46357 | C84: =SUM((OFFSET(Data!$C$410,17*(ROW(Data!Y469)-434),0)):(OFFSET(Data!$C$423,17*(ROW(Data!Y469)-434),0))) -> 4775.66 | D84: =(OFFSET(Data!$P$409,17*(ROW(Data!Y469)-434),0)) -> 17337.947 | E84: =(OFFSET(Data!$P$412,17*(ROW(Data!Y469)-434),0)) -> 1681.61 | F84: =(OFFSET(Data!$P$418,17*(ROW(Data!Y469)-434),0)) -> 1608.88 | G84: =(OFFSET(Data!$P$415,17*(ROW(Data!Y469)-434),0)) -> 2135 | H84: =(OFFSET(Data!$P$421,17*(ROW(Data!Y469)-434),0)) -> 11912.457 | R84: =K83-K84+C84 -> 4775.66 | S84: 150 | T84: 400 | U84: 0 | V84: 200 | W84: =SUM((OFFSET(Data!$F$410,17*(ROW(Data!Y469)-434),0)):(OFFSET(Data!$F$423,17*(ROW(Data!Y469)-434),0))) -> 3330.75 | X84: =SUM((OFFSET(Data!$I$410,17*(ROW(Data!Y469)-434),0)):(OFFSET(Data!$I$423,17*(ROW(Data!Y469)-434),0))) -> 755.88 | Y84: =W84+X84 -> 4086.63 | Z84: =(OFFSET(Data!$F$412,17*(ROW(Data!Y469)-434),0)) -> 100 | AA84: =(OFFSET(Data!$F$411,17*(ROW(Data!Y469)-434),0)) -> 400 | AM84: =AG84-AG83 -> 0 | AN84: =AH84-AH83 -> 0 | AO84: =AJ84-AJ83 -> 0 | AP84: =AN84-AM84 -> 0 | AQ84: =AO84-AN84 -> 0
B85: 46388 | C85: =SUM((OFFSET(Data!$C$410,17*(ROW(Data!Y470)-434),0)):(OFFSET(Data!$C$423,17*(ROW(Data!Y470)-434),0))) -> 4775.66 | D85: =(OFFSET(Data!$P$409,17*(ROW(Data!Y470)-434),0)) -> 18026.977 | E85: =(OFFSET(Data!$P$412,17*(ROW(Data!Y470)-434),0)) -> 1820.64 | F85: =(OFFSET(Data!$P$418,17*(ROW(Data!Y470)-434),0)) -> 1758.88 | G85: =(OFFSET(Data!$P$415,17*(ROW(Data!Y470)-434),0)) -> 2335 | H85: =(OFFSET(Data!$P$421,17*(ROW(Data!Y470)-434),0)) -> 12112.457 | R85: =K84-K85+C85 -> 4775.66 | S85: 150 | T85: 400 | U85: 0 | V85: 200 | W85: =SUM((OFFSET(Data!$F$410,17*(ROW(Data!Y470)-434),0)):(OFFSET(Data!$F$423,17*(ROW(Data!Y470)-434),0))) -> 3330.75 | X85: =SUM((OFFSET(Data!$I$410,17*(ROW(Data!Y470)-434),0)):(OFFSET(Data!$I$423,17*(ROW(Data!Y470)-434),0))) -> 755.88 | Y85: =W85+X85 -> 4086.63 | Z85: =(OFFSET(Data!$F$412,17*(ROW(Data!Y470)-434),0)) -> 100 | AA85: =(OFFSET(Data!$F$411,17*(ROW(Data!Y470)-434),0)) -> 400 | AM85: =AG85-AG84 -> 0 | AN85: =AH85-AH84 -> 0 | AO85: =AJ85-AJ84 -> 0 | AP85: =AN85-AM85 -> 0 | AQ85: =AO85-AN85 -> 0
B86: 46419 | C86: =SUM((OFFSET(Data!$C$410,17*(ROW(Data!Y471)-434),0)):(OFFSET(Data!$C$423,17*(ROW(Data!Y471)-434),0))) -> 4775.66 | D86: =(OFFSET(Data!$P$409,17*(ROW(Data!Y471)-434),0)) -> 18716.007 | E86: =(OFFSET(Data!$P$412,17*(ROW(Data!Y471)-434),0)) -> 1959.67 | F86: =(OFFSET(Data!$P$418,17*(ROW(Data!Y471)-434),0)) -> 1908.88 | G86: =(OFFSET(Data!$P$415,17*(ROW(Data!Y471)-434),0)) -> 2535 | H86: =(OFFSET(Data!$P$421,17*(ROW(Data!Y471)-434),0)) -> 12312.457 | R86: =K85-K86+C86 -> 4775.66 | S86: 150 | T86: 400 | U86: 0 | V86: 200 | W86: =SUM((OFFSET(Data!$F$410,17*(ROW(Data!Y471)-434),0)):(OFFSET(Data!$F$423,17*(ROW(Data!Y471)-434),0))) -> 3330.75 | X86: =SUM((OFFSET(Data!$I$410,17*(ROW(Data!Y471)-434),0)):(OFFSET(Data!$I$423,17*(ROW(Data!Y471)-434),0))) -> 755.88 | Y86: =W86+X86 -> 4086.63 | Z86: =(OFFSET(Data!$F$412,17*(ROW(Data!Y471)-434),0)) -> 100 | AA86: =(OFFSET(Data!$F$411,17*(ROW(Data!Y471)-434),0)) -> 400 | AM86: =AG86-AG85 -> 0 | AN86: =AH86-AH85 -> 0 | AO86: =AJ86-AJ85 -> 0 | AP86: =AN86-AM86 -> 0 | AQ86: =AO86-AN86 -> 0
... B132: 47818 | C132: =SUM((OFFSET(Data!$C$410,17*(ROW(Data!Y517)-434),0)):(OFFSET(Data!$C$423,17*(ROW(Data!Y517)-434),0))) -> 4775.66 | D132: =(OFFSET(Data!$P$409,17*(ROW(Data!Y517)-434),0)) -> 50411.387 | E132: =(OFFSET(Data!$P$412,17*(ROW(Data!Y517)-434),0)) -> 8355.05 | F132: =(OFFSET(Data!$P$418,17*(ROW(Data!Y517)-434),0)) -> 8808.88 | G132: =(OFFSET(Data!$P$415,17*(ROW(Data!Y517)-434),0)) -> 11735 | H132: =(OFFSET(Data!$P$421,17*(ROW(Data!Y517)-434),0)) -> 21512.457 | R132: =K131-K132+C132 -> 4775.66 | S132: 150 | T132: 400 | U132: 0 | V132: 200 | W132: =SUM((OFFSET(Data!$F$410,17*(ROW(Data!Y517)-434),0)):(OFFSET(Data!$F$423,17*(ROW(Data!Y517)-434),0))) -> 3330.75 | X132: =SUM((OFFSET(Data!$I$410,17*(ROW(Data!Y517)-434),0)):(OFFSET(Data!$I$423,17*(ROW(Data!Y517)-434),0))) -> 755.88 | Y132: =W132+X132 -> 4086.63 | Z132: =(OFFSET(Data!$F$412,17*(ROW(Data!Y517)-434),0)) -> 100 | AA132: =(OFFSET(Data!$F$411,17*(ROW(Data!Y517)-434),0)) -> 400 | AM132: =AG132-AG131 -> 0 | AN132: =AH132-AH131 -> 0 | AO132: =AJ132-AJ131 -> 0 | AP132: =AN132-AM132 -> 0 | AQ132: =AO132-AN132 -> 0

Sheet Bills
Q1: Total Due
B2: Bills | N2: =SUM(N4:N29) -> 4030.395 | O2: =SUM(O4:O29) -> 4030.4 | P2: =N2-O2 -> -0.005 | Q2: =SUM(Q4:Q29) -> -0.005 | R2: =-Q2 -> 0.005
B3: Month (of Usage) | D3: OKC | E3: Date | F3: OGE | G3: Date | H3: ONG | I3: Date | J3: Cox | K3: Date | M3: Total | N3: Owe | O3: Paid | P3: Pay Date | Q3: Due
B4: 45292 | D4: 50 | F4: 43 | H4: 61 | J4: 106.3 | M4: =SUM(D4,F4,H4,J4) -> 260.3 | N4: =M4/2 -> 130.15 | O4: =Data!F433 -> 130 | Q4: =N4-O4 -> 0.15 | R4: =O4-N4 -> -0.15
B5: 45323 | M5: =SUM(D5,F5,H5,J5) -> 0 | N5: =M5/2 -> 0 | O5: =Data!F450 -> 99 | Q5: =N5-O5 -> -99 | R5: =O5-N5 -> 99
B6: 45352 | D6: 53.5 | F6: 36.4 | H6: 72.07 | J6: 106.3 | M6: =SUM(D6,F6,H6,J6) -> 268.27 | N6: =M6/2 -> 134.135 | O6: =Data!F467 -> 10 | Q6: =N6-O6 -> 124.135 | R6: =O6-N6 -> -124.135
B7: 45383 | D7: 58.67 | F7: 37.08 | H7: 68.07 | J7: 106.3 | M7: =SUM(D7,F7,H7,J7) -> 270.12 | N7: =M7/2 -> 135.06 | O7: =Data!F484 -> 30 | Q7: =N7-O7 -> 105.06 | R7: =O7-N7 -> -105.06
B8: 45413 | D8: 67.11 | F8: 53.09 | H8: 63.42 | J8: 106.3 | M8: =SUM(D8,F8,H8,J8) -> 289.92 | N8: =M8/2 -> 144.96 | O8: =Data!F501 -> 410 | Q8: =N8-O8 -> -265.04 | R8: =O8-N8 -> 265.04
B9: 45444 | D9: 67.11 | F9: 53.09 | H9: 63.42 | J9: 106.3 | M9: =SUM(D9,F9,H9,J9) -> 289.92 | N9: =M9/2 -> 144.96 | O9: =Data!F518 -> 170 | Q9: =N9-O9 -> -25.04 | R9: =O9-N9 -> 25.04
B10: 45474 | D10: 67.11 | F10: 53.09 | H10: 63.42 | J10: 106.3 | M10: =SUM(D10,F10,H10,J10) -> 289.92 | N10: =M10/2 -> 144.96 | O10: =Data!F535 -> 170 | Q10: =N10-O10 -> -25.04 | R10: =O10-N10 -> 25.04
B11: 45505 | D11: 67.11 | F11: 53.09 | H11: 63.42 | J11: 106.3 | M11: =SUM(D11,F11,H11,J11) -> 289.92 | N11: =M11/2 -> 144.96 | O11: =Data!F552 -> 170 | Q11: =N11-O11 -> -25.04 | R11: =O11-N11 -> 25.04
B12: 45536 | D12: 67.11 | F12: 136.63 | H12: 63.42 | J12: 106.3 | M12: =SUM(D12,F12,H12,J12) -> 373.46 | N12: =M12/2 -> 186.73 | O12: =Data!F569 -> 200 | P12: 45605 | Q12: =N12-O12 -> -13.27 | R12: =O12-N12 -> 13.27
B13: 45566 | D13: 70.4 | F13: =22.5+79.29 -> 101.79 | H13: =36.12+35.29 -> 71.41 | J13: 44.11 | M13: =SUM(D13,F13,H13,J13) -> 287.71 | N13: =M13/2 -> 143.855 | O13: =Data!F586 -> 200 | P13: 45652 | Q13: =N13-O13 -> -56.145 | R13: =O13-N13 -> 56.145
B14: 45597 | D14: 75.55 | F14: 76.21 | H14: 81.11 | J14: 60 | M14: =SUM(D14,F14,H14,J14) -> 292.87 | N14: =M14/2 -> 146.435 | O14: =Data!F603 -> 200 | P14: 45652 | Q14: =N14-O14 -> -53.565 | R14: =O14-N14 -> 53.565
B15: 45627 | D15: 72.54 | F15: 58.89 | H15: 73.37 | J15: 60 | M15: =SUM(D15,F15,H15,J15) -> 264.8 | N15: =M15/2 -> 132.4 | Q15: =N15-O15 -> 132.4 | R15: =O15-N15 -> -132.4
B16: 45658 | D16: 81.87 | F16: 60.23 | H16: 79.37 | J16: 60 | M16: =SUM(D16,F16,H16,J16) -> 281.47 | N16: =M16/2 -> 140.735 | O16: 75 | P16: 45716 | Q16: =N16-O16 -> 65.735 | R16: =O16-N16 -> -65.735
B17: 45689 | D17: 72.54 | F17: 59.05 | H17: 83.37 | J17: 60 | M17: =SUM(D17,F17,H17,J17) -> 274.96 | N17: =M17/2 -> 137.48 | O17: 140 | P17: 45749 | Q17: =N17-O17 -> -2.52 | R17: =O17-N17 -> 2.52
B18: 45717 | D18: 81.87 | F18: 60.09 | H18: 87.37 | J18: 60 | M18: =SUM(D18,F18,H18,J18) -> 289.33 | N18: =M18/2 -> 144.665 | O18: 120 | P18: 45777 | Q18: =N18-O18 -> 24.665 | R18: =O18-N18 -> -24.665
B19: 45748 | D19: 81.87 | F19: 57.58 | H19: 86.3 | J19: 60 | M19: =SUM(D19,F19,H19,J19) -> 285.75 | N19: =M19/2 -> 142.875 | Q19: =N19-O19 -> 142.875 | R19: =O19-N19 -> -142.875
B20: 45778 | D20: 72.54 | F20: 70.41 | H20: 86.3 | J20: 60 | M20: =SUM(D20,F20,H20,J20) -> 289.25 | N20: =M20/2 -> 144.625 | O20: 160 | P20: 45819 | Q20: =N20-O20 -> -15.375 | R20: =O20-N20 -> 15.375
B21: 45809 | D21: 73.05 | F21: 130.51 | H21: 82.3 | J21: 60 | M21: =SUM(D21,F21,H21,J21) -> 345.86 | N21: =M21/2 -> 172.93 | O21: 140 | P21: 45838 | Q21: =N21-O21 -> 32.93 | R21: =O21-N21 -> -32.93
B22: 45839 | D22: 73.05 | F22: 172.71 | H22: 82.3 | J22: 60 | M22: =SUM(D22,F22,H22,J22) -> 388.06 | N22: =M22/2 -> 194.03 | O22: 100 | P22: 45869 | Q22: =N22-O22 -> 94.03 | R22: =O22-N22 -> -94.03
B23: 45870 | M23: =SUM(D23,F23,H23,J23) -> 0 | N23: =M23/2 -> 0 | O23: 141.95 | P23: 45874 | Q23: =N23-O23 -> -141.95 | R23: =O23-N23 -> 141.95
B24: 45901 | M24: =SUM(D24,F24,H24,J24) -> 0 | N24: =M24/2 -> 0 | Q24: =N24-O24 -> 0 | R24: =O24-N24 -> 0
B25: 45931 | J25: 98 | M25: =SUM(D25,F25,H25,J25) -> 98 | N25: =M25 -> 98 | O25: 98 | Q25: =N25-O25 -> 0 | R25: =O25-N25 -> 0
B26: 45962 | F26: =22.5+39.07+20.59 -> 82.16 | H26: 153.69 | J26: 70 | M26: =SUM(D26,F26,H26,J26) -> 305.85 | N26: =M26 -> 305.85 | O26: =70+153.69+82.16 -> 305.85 | Q26: =N26-O26 -> 0 | R26: =O26-N26 -> 0
B27: 45992 | D27: 152.74 | F27: 39.83 | H27: 134.96 | J27: 70 | M27: =SUM(D27,F27,H27,J27) -> 397.53 | N27: =M27 -> 397.53 | O27: =134.96+70+152.74+39.83 -> 397.53 | Q27: =N27-O27 -> 0 | R27: =O27-N27 -> 0
B28: 46023 | D28: 92.16 | F28: 46.52 | H28: 100.9 | J28: 70 | M28: =SUM(D28,F28,H28,J28) -> 309.58 | N28: =M28 -> 309.58 | O28: 309.58 | Q28: =N28-O28 -> 0 | R28: =O28-N28 -> 0
B29: 46054 | D29: 81.92 | H29: 101.57 | J29: 70 | M29: =SUM(D29,F29,H29,J29) -> 253.49 | N29: =M29 -> 253.49 | O29: =101.57+151.92 -> 253.49 | Q29: =N29-O29 -> 0 | R29: =O29-N29 -> 0

Sheet Bitcoin
C2: Cryptotracker_v2.0 | Q2: =H5/C8 -> 1.3319711 | S2: Liquidity = Liquid Profit when Balance = 0!
C3: USD | F3: #VALUE! | Q3: So… based on the percentage of liquidity to liquid profit, we can calculate the "realized profit".
C4: Pre | D4: Fees | E4: Post | F4: Bought/Sold
B5: Total Bought | C5: =SUM(C17:C115) -> 1145.55 | D5: =SUM(D17:D115) -> 26.55 | E5: =SUM(E17:E115) -> 1119 | F5: =SUM(F17:F115) -> 0.0211129 | G5: LIQUID PROFIT | H5: =C8-C7 -> 204.54757 | I5: =(E6+C8)/C5 -> 1.1785584 | J5: Current Market Value | L5: 69774.71 | O5: Investment Value | P5: =C5-T13 -> -35.30686 | Q5: =C8-C7 -> 204.54757 | R5: =Q5/C5 -> 0.1785584 | S5: Total Profit
B6: Total Sold | C6: =SUM(P17:P115) -> 1224.69 | D6: =SUM(Q17:Q115) -> 28.16 | E6: =SUM(R17:R115) -> 1196.53 | F6: =SUM(S17:S115) -> 0.018860196 | G6: LIQUID VALUE | H6: =C8+E6 -> 1350.0976 | I6: =H6/C5 -> 1.1785584 | J6: Minimum Market Value | L6: 0 | O6: Investment Cost | P6: =C7+Q8 -> -8153.68 | Q6: =E6-T13 -> 15.67314 | R6: =Q6/T13 -> 0.013272684 | S6: Real Profit
B7: Balance | C7: =C5-E6 -> -50.98 | D7: =D6+D5 -> 54.71 | E7: =E5-C6 -> -105.69 | F7: =F5-F6 -> 0.0022527036 | G7: TOTAL VALUE | H7: =C5+H5 -> 1350.0976 | I7: =H7/C5 -> 1.1785584 | J7: Buying Market Value | L7: 42000 | O7: Deficit | P7: =P6-P5 -> -8118.3731 | Q7: =C8-P5 -> 188.87443 | R7: =Q7/P5 -> -5.3495109 | S7: Virtual Profit
B8: Current Value | C8: =C9-(C9*E8) -> 153.56757 | D8: =D5/C5 -> 0.02317664 | E8: =D6/C6 -> 0.022993574 | F8: Overhead Fees | G8: Exchange Rate Ratio (Sell/Buy) | I8: =T12/G12 -> 1.1594914 | J8: Selling Market Value | L8: 45000 | O8: Surplus | P8: =Q7+Q8 -> -7913.8256 | Q8: ='Calculation Definitions'!L18 -> -8102.7 | R8: Return
B9: Liquidity | C9: =L5*F7 -> 157.18174 | D9: =C7+(C7*E8) -> -52.152212 | E9: Bottom Line | I9: =V12/M14 -> 0.93729927
C11: Spent | D11: Fees | E11: Bought | F11: Coin Received | G11: Exchange Rate | H11: CR Calc Check | I11: DMV for Avg Bottom Line | K11: Diff | L11: RoCMV | M11: X | P11: Sold | Q11: Fees | R11: Gained | S11: Coin Sold | T11: Exchange Rate | U11: CR Calc Check | V11: X
B12: AVERAGE | C12: =AVERAGE(C17:C115) -> 12.45163 | D12: =AVERAGE(D17:D115) -> 0.28858696 | E12: =AVERAGE(E17:E115) -> 12.163043 | F12: =AVERAGE(F17:F115) -> 0.00022948804 | G12: =SUMPRODUCT(G17:G114,E17:E114)/SUM(E17:E114) -> 62622.456 | H12: =AVERAGE(H17:H115) -> 0.00022752608 | I12: =SUMPRODUCT(I17:I114,E17:E114)/SUM(E17:E114) -> 65570.749 | J12: =AVERAGE(J17:J115) -> 12.740217 | K12: =AVERAGE(K17:K115) -> 1.4390169 | L12: =AVERAGE(L17:L115) -> 16.012462 | M12: =AVERAGE(M17:M115) -> 1.4768878 | O12: AVERAGE | P12: =AVERAGE(P17:P115) -> 25.514375 | Q12: =AVERAGE(Q17:Q115) -> 0.58666667 | R12: =AVERAGE(R17:R115) -> 24.927708 | S12: =AVERAGE(S17:S115) -> 0.00039292076 | T12: =SUMPRODUCT(T17:T114,R17:R114)/SUM(R17:R114) -> 72610.2 | U12: =AVERAGE(U17:U115) -> 0.0003929209 | V12: =AVERAGE(V17:V115) -> 0.95902272
B13: INVESTMENT | C13: =SUM(C17:C115) -> 1145.55 | D13: =SUM(D17:D115) -> 26.55 | E13: =SUM(E17:E115) -> 1119 | F13: =SUM(F17:F115) -> 0.0211129 | H13: =SUM(H17:H115) -> 0.020932399 | J13: =SUM(J17:J114) -> 1172.1 | L13: =SUM(L17:L115) -> 1473.1465 | M13: =L13/J13 -> 1.2568437 | O13: SUM | P13: =SUM(P17:P115) -> 1224.69 | Q13: =SUM(Q17:Q115) -> 28.16 | R13: =SUM(R17:R115) -> 1196.53 | S13: =SUM(S17:S115) -> 0.018860196 | T13: =SUM(S17:S114)*SUMPRODUCT(G17:G114,C17:C114)/SUM(C17:C114) -> 1180.8569 | U13: =SUM(U17:U115) -> 0.018860203
M14: =J13/C13 -> 1.0231766 | T14: VSP
B16: Date & Time | C16: Spent | D16: Fees | E16: Bought | F16: Coin Received | G16: Exchange Rate | H16: CR Calc Check | I16: DMV for Bottom Line | K16: Diff | L16: RoCMV | M16: X | O16: Date & Time | P16: Sold | Q16: Fees | R16: Gained | S16: Coin Sold | T16: Exchange Rate | U16: CR Calc Check | V16: X
B17: 44307.84 | C17: 1 | D17: 0.03 | E17: 0.97 | F17: 1.785e-05 | G17: 54341.74 | H17: =E17/G17 -> 1.7849999e-05 | I17: =G17+((J17-E17)/E17)*G17 -> 57703.085 | J17: =C17+D17 -> 1.03 | K17: =L17/J17 -> 1.2092025 | L17: =F17*$L$5 -> 1.2454786 | M17: =L17/C17 -> 1.2454786 | O17: 44311.858 | P17: 1 | Q17: 0.03 | R17: 0.97 | S17: 1.947e-05 | T17: 51361.07 | U17: =P17/T17 -> 1.9469999e-05 | V17: =R17/(S17*$I$12) -> 0.75979361
B18: 44307.844 | C18: 1 | D18: 0.03 | E18: 0.97 | F18: 1.779e-05 | G18: 54525.01 | H18: =E18/G18 -> 1.7790001e-05 | I18: =G18+((J18-E18)/E18)*G18 -> 57897.691 | J18: =C18+D18 -> 1.03 | K18: =L18/J18 -> 1.205138 | L18: =F18*$L$5 -> 1.2412921 | M18: =L18/C18 -> 1.2412921 | O18: 44316.776 | P18: 1.03 | Q18: 0.03 | R18: 1 | S18: 1.784e-05 | T18: 57735.43 | U18: =P18/T18 -> 1.7839999e-05 | V18: =R18/(S18*$I$12) -> 0.85486002
B19: 44307.853 | C19: 1 | D19: 0.03 | E19: 0.97 | F19: 1.78e-05 | G19: 54494.38 | H19: =E19/G19 -> 1.7800001e-05 | I19: =G19+((J19-E19)/E19)*G19 -> 57865.166 | J19: =C19+D19 -> 1.03 | K19: =L19/J19 -> 1.2058154 | L19: =F19*$L$5 -> 1.2419898 | M19: =L19/C19 -> 1.2419898 | O19: 44318.863 | P19: 1.03 | Q19: 0.03 | R19: 1 | S19: 1.769e-05 | T19: 58224.99 | U19: =P19/T19 -> 1.7689999e-05 | V19: =R19/(S19*$I$12) -> 0.86210869
B20: 44307.858 | C20: 1 | D20: 0.03 | E20: 0.97 | F20: 1.784e-05 | G20: 54372.2 | H20: =E20/G20 -> 1.7839999e-05 | I20: =G20+((J20-E20)/E20)*G20 -> 57735.429 | J20: =C20+D20 -> 1.03 | K20: =L20/J20 -> 1.2085251 | L20: =F20*$L$5 -> 1.2447808 | M20: =L20/C20 -> 1.2447808 | O20: 44323.974 | P20: 1.03 | Q20: 0.03 | R20: 1 | S20: 1.757e-05 | T20: 58622.65 | U20: =P20/T20 -> 1.7570001e-05 | V20: =R20/(S20*$I$12) -> 0.86799674
B21: 44307.872 | C21: 1 | D21: 0.03 | E21: 0.97 | F21: 1.79e-05 | G21: 54189.94 | H21: =E21/G21 -> 1.7900001e-05 | I21: =G21+((J21-E21)/E21)*G21 -> 57541.895 | J21: =C21+D21 -> 1.03 | K21: =L21/J21 -> 1.2125896 | L21: =F21*$L$5 -> 1.2489673 | M21: =L21/C21 -> 1.2489673 | O21: 44324.544 | P21: 1.03 | Q21: 0.03 | R21: 1 | S21: 1.742e-05 | T21: 59127.44 | U21: =P21/T21 -> 1.742e-05 | V21: =R21/(S21*$I$12) -> 0.87547088
B22: 44307.883 | C22: 1 | D22: 0.03 | E22: 0.97 | F22: 1.84e-05 | G22: 52717.39 | H22: =E22/G22 -> 1.84e-05 | I22: =G22+((J22-E22)/E22)*G22 -> 55978.259 | J22: =C22+D22 -> 1.03 | K22: =L22/J22 -> 1.2464608 | L22: =F22*$L$5 -> 1.2838547 | M22: =L22/C22 -> 1.2838547 | O22: 44324.644 | P22: 1.03 | Q22: 0.03 | R22: 1 | S22: 1.731e-05 | T22: 59503.18 | U22: =P22/T22 -> 1.7309999e-05 | V22: =R22/(S22*$I$12) -> 0.88103424
B23: 44307.892 | C23: 1 | D23: 0.03 | E23: 0.97 | F23: 1.84e-05 | G23: 52717.39 | H23: =E23/G23 -> 1.84e-05 | I23: =G23+((J23-E23)/E23)*G23 -> 55978.259 | J23: =C23+D23 -> 1.03 | K23: =L23/J23 -> 1.2464608 | L23: =F23*$L$5 -> 1.2838547 | M23: =L23/C23 -> 1.2838547 | O23: 44402.849 | P23: 4.12 | Q23: 0.12 | R23: =P23-Q23 -> 4 | S23: 0.00010909 | T23: 37766.98 | U23: =P23/T23 -> 0.00010909 | V23: =R23/(S23*$I$12) -> 0.55919709
B24: 44308.534 | C24: 1 | D24: 0.03 | E24: 0.97 | F24: 1.797e-05 | G24: 53978.85 | H24: =E24/G24 -> 1.7970001e-05 | I24: =G24+((J24-E24)/E24)*G24 -> 57317.748 | J24: =C24+D24 -> 1.03 | K24: =L24/J24 -> 1.2173316 | L24: =F24*$L$5 -> 1.2538515 | M24: =L24/C24 -> 1.2538515 | O24: 44414.466 | P24: 8.24 | Q24: 0.25 | R24: =P24-Q24 -> 7.99 | S24: =0.0001912 -> 0.0001912 | T24: 43096.23 | U24: =P24/T24 -> 0.00019120002 | V24: =R24/(S24*$I$12) -> 0.63730708
B25: 44308.535 | C25: 1 | D25: 0.03 | E25: 0.97 | F25: 1.802e-05 | G25: 53829.08 | H25: =E25/G25 -> 1.802e-05 | I25: =G25+((J25-E25)/E25)*G25 -> 57158.714 | J25: =C25+D25 -> 1.03 | K25: =L25/J25 -> 1.2207187 | L25: =F25*$L$5 -> 1.2573403 | M25: =L25/C25 -> 1.2573403 | O25: 44417.78 | P25: 4.12 | Q25: 0.12 | R25: =P25-Q25 -> 4 | S25: =0.00008914 -> 8.914e-05 | T25: 46219.43 | U25: =P25/T25 -> 8.914e-05 | V25: =R25/(S25*$I$12) -> 0.68434834
B26: 44308.556 | C26: 1 | D26: 0.03 | E26: 0.97 | F26: 1.839e-05 | G26: 52746.06 | H26: =E26/G26 -> 1.8389999e-05 | I26: =G26+((J26-E26)/E26)*G26 -> 56008.703 | J26: =C26+D26 -> 1.03 | K26: =L26/J26 -> 1.2457834 | L26: =F26*$L$5 -> 1.2831569 | M26: =L26/C26 -> 1.2831569 | O26: 44421.649 | P26: 10.3 | Q26: 0.23 | R26: =P26-Q26 -> 10.07 | S26: 0.00021709 | T26: 47445.76 | U26: =P26/T26 -> 0.00021709 | V26: =R26/(S26*$I$12) -> 0.70742354
B27: 44308.846 | C27: 2 | D27: 0.06 | E27: 1.94 | F27: 3.806e-05 | G27: 50972.15 | H27: =E27/G27 -> 3.8059999e-05 | I27: =G27+((J27-E27)/E27)*G27 -> 54125.066 | J27: =C27+D27 -> 2.06 | K27: =L27/J27 -> 1.2891386 | L27: =F27*$L$5 -> 2.6556255 | M27: =L27/C27 -> 1.3278127 | O27: 44428.871 | P27: 4.12 | Q27: 0.12 | R27: =P27-Q27 -> 4 | S27: 8.402e-05 | T27: 49035.94 | U27: =P27/T27 -> 8.4020007e-05 | V27: =R27/(S27*$I$12) -> 0.72605107
B28: 44308.889 | C28: 2 | D28: 0.06 | E28: 1.94 | F28: 3.881e-05 | G28: 49987.12 | H28: =E28/G28 -> 3.8809997e-05 | I28: =G28+((J28-E28)/E28)*G28 -> 53079.107 | J28: =C28+D28 -> 2.06 | K28: =L28/J28 -> 1.314542 | L28: =F28*$L$5 -> 2.7079565 | M28: =L28/C28 -> 1.3539782 | O28: 44429.509 | P28: 4.12 | Q28: 0.12 | R28: =P28-Q28 -> 4 | S28: 8.293e-05 | T28: 49680.45 | U28: =P28/T28 -> 8.2930006e-05 | V28: =R28/(S28*$I$12) -> 0.735594
B29: 44311.668 | C29: 1 | D29: 0.03 | E29: 0.97 | F29: 2.028e-05 | G29: 47830.37 | H29: =E29/G29 -> 2.0280002e-05 | I29: =G29+((J29-E29)/E29)*G29 -> 50788.95 | J29: =C29+D29 -> 1.03 | K29: =L29/J29 -> 1.3738166 | L29: =F29*$L$5 -> 1.4150311 | M29: =L29/C29 -> 1.4150311 | O29: 44442.362 | P29: 10.23 | Q29: 0.23 | R29: =P29-Q29 -> 10 | S29: 0.00020181 | T29: 50691.24 | U29: =P29/T29 -> 0.00020181002 | V29: =R29/(S29*$I$12) -> 0.75569609
B30: 44311.963 | C30: 1.03 | D30: 0.03 | E30: 1 | F30: 1.915e-05 | G30: 52219.32 | H30: =E30/G30 -> 1.915e-05 | I30: =G30+((J30-E30)/E30)*G30 -> 55352.479 | J30: =C30+D30 -> 1.06 | K30: =L30/J30 -> 1.2605525 | L30: =F30*$L$5 -> 1.3361857 | M30: =L30/C30 -> 1.2972677 | O30: 44445.731 | P30: 10.23 | Q30: 0.23 | R30: =P30-Q30 -> 10 | S30: 0.00019438 | T30: 52628.87 | U30: =P30/T30 -> 0.00019438 | V30: =R30/(S30*$I$12) -> 0.78458189
B31: 44314.036 | C31: 1.03 | D31: 0.03 | E31: 1 | F31: 1.831e-05 | G31: 54614.96 | H31: =E31/G31 -> 1.8310002e-05 | I31: =G31+((J31-E31)/E31)*G31 -> 57891.858 | J31: =C31+D31 -> 1.06 | K31: =L31/J31 -> 1.2052594 | L31: =F31*$L$5 -> 1.2775749 | M31: =L31/C31 -> 1.240364 | O31: 44474.199 | P31: 20.46 | Q31: 0.46 | R31: =P31-Q31 -> 20 | S31: 0.0004092 | T31: 50000 | U31: =P31/T31 -> 0.0004092 | V31: =R31/(S31*$I$12) -> 0.74539114
B32: 44314.037 | C32: 1.03 | D32: 0.03 | E32: 1 | F32: 1.832e-05 | G32: 54585.15 | H32: =E32/G32 -> 1.8320001e-05 | I32: =G32+((J32-E32)/E32)*G32 -> 57860.259 | J32: =C32+D32 -> 1.06 | K32: =L32/J32 -> 1.2059176 | L32: =F32*$L$5 -> 1.2782727 | M32: =L32/C32 -> 1.2410414 | O32: 44474.647 | P32: 20.46 | Q32: 0.46 | R32: =P32-Q32 -> 20 | S32: 0.00039856 | T32: 51334.81 | U32: =P32/T32 -> 0.00039855996 | V32: =R32/(S32*$I$12) -> 0.76529018
B33: 44314.052 | C33: 1.03 | D33: 0.03 | E33: 1 | F33: 1.845e-05 | G33: 54200.54 | H33: =E33/G33 -> 1.8450001e-05 | I33: =G33+((J33-E33)/E33)*G33 -> 57452.572 | J33: =C33+D33 -> 1.06 | K33: =L33/J33 -> 1.2144749 | L33: =F33*$L$5 -> 1.2873434 | M33: =L33/C33 -> 1.249848 | O33: 44475.341 | P33: 20.46 | Q33: 0.46 | R33: =P33-Q33 -> 20 | S33: 0.00038604 | T33: 53000 | U33: =P33/T33 -> 0.00038603774 | V33: =R33/(S33*$I$12) -> 0.79010997
B34: 44320.74 | C34: 2.06 | D34: 0.06 | E34: 2 | F34: 3.729e-05 | G34: 53633.68 | H34: =E34/G34 -> 3.7290001e-05 | I34: =G34+((J34-E34)/E34)*G34 -> 56851.701 | J34: =C34+D34 -> 2.12 | K34: =L34/J34 -> 1.2273108 | L34: =F34*$L$5 -> 2.6018989 | M34: =L34/C34 -> 1.2630577 | O34: 44475.349 | P34: 20.46 | Q34: 0.46 | R34: =P34-Q34 -> 20 | S34: 0.0003761 | T34: 54400.43 | U34: =P34/T34 -> 0.00037609997 | V34: =R34/(S34*$I$12) -> 0.8109919
B35: 44328.718 | C35: 10 | D35: 0.23 | E35: =C35-D35 -> 9.77 | F35: 0.00018669 | G35: 52332.74 | H35: =E35/G35 -> 0.00018669001 | I35: =G35+((J35-E35)/E35)*G35 -> 54796.718 | J35: =C35+D35 -> 10.23 | K35: =L35/J35 -> 1.2733373 | L35: =F35*$L$5 -> 13.026241 | M35: =L35/C35 -> 1.3026241 | O35: 44475.68 | P35: 10.23 | Q35: 0.23 | R35: =P35-Q35 -> 10 | S35: 0.00018587 | T35: 55038.47 | U35: =P35/T35 -> 0.00018586999 | V35: =R35/(S35*$I$12) -> 0.82050372
B36: 44328.775 | C36: 1.03 | D36: 0.03 | E36: =C36-D36 -> 1 | F36: 1.945e-05 | G36: 51413.88 | H36: =E36/G36 -> 1.9450001e-05 | I36: =G36+((J36-E36)/E36)*G36 -> 54498.713 | J36: =C36+D36 -> 1.06 | K36: =L36/J36 -> 1.2803001 | L36: =F36*$L$5 -> 1.3571181 | M36: =L36/C36 -> 1.3175904 | O36: 44479.975 | P36: 10.23 | Q36: 0.23 | R36: =P36-Q36 -> 10 | S36: 0.00018044 | T36: 56694.75 | U36: =P36/T36 -> 0.00018043999 | V36: =R36/(S36*$I$12) -> 0.84519523
B37: 44328.792 | C37: 1.03 | D37: 0.03 | E37: =C37-D37 -> 1 | F37: 2.037e-05 | G37: 49091.8 | H37: =E37/G37 -> 2.0370001e-05 | I37: =G37+((J37-E37)/E37)*G37 -> 52037.308 | J37: =C37+D37 -> 1.06 | K37: =L37/J37 -> 1.3408593 | L37: =F37*$L$5 -> 1.4213108 | M37: =L37/C37 -> 1.3799134 | O37: 44480.615 | P37: 10.23 | Q37: 0.23 | R37: =P37-Q37 -> 10 | S37: 0.00017714 | T37: 57750 | U37: =P37/T37 -> 0.00017714286 | V37: =R37/(S37*$I$12) -> 0.86094065
B38: 44328.794 | C38: 2.06 | D38: 0.07 | E38: =C38-D38 -> 1.99 | F38: 4.28e-05 | G38: 46495.33 | H38: =E38/G38 -> 4.2799997e-05 | I38: =G38+((J38-E38)/E38)*G38 -> 49766.358 | J38: =C38+D38 -> 2.13 | K38: =L38/J38 -> 1.4020458 | L38: =F38*$L$5 -> 2.9863576 | M38: =L38/C38 -> 1.4496881 | O38: 44482.842 | P38: 4.12 | Q38: 0.12 | R38: =P38-Q38 -> 4 | S38: 7.085e-05 | T38: 58151.02 | U38: =P38/T38 -> 7.0850004e-05 | V38: =R38/(S38*$I$12) -> 0.86101356
B39: 44331.794 | C39: 1.03 | D39: 0.03 | E39: =C39-D39 -> 1 | F39: 2.146e-05 | G39: 46598.32 | H39: =E39/G39 -> 2.1460001e-05 | I39: =G39+((J39-E39)/E39)*G39 -> 49394.219 | J39: =C39+D39 -> 1.06 | K39: =L39/J39 -> 1.4126088 | L39: =F39*$L$5 -> 1.4973653 | M39: =L39/C39 -> 1.4537527 | O39: 44484.375 | P39: 4.12 | Q39: 0.12 | R39: =P39-Q39 -> 4 | S39: 6.867e-05 | T39: 60000 | U39: =P39/T39 -> 6.8666667e-05 | V39: =R39/(S39*$I$12) -> 0.88834732
B40: 44332.584 | C40: 2.06 | D40: 0.06 | E40: =C40-D40 -> 2 | F40: 4.396e-05 | G40: 45495.91 | H40: =E40/G40 -> 4.3959996e-05 | I40: =G40+((J40-E40)/E40)*G40 -> 48225.665 | J40: =C40+D40 -> 2.12 | K40: =L40/J40 -> 1.4468379 | L40: =F40*$L$5 -> 3.0672963 | M40: =L40/C40 -> 1.4889788 | O40: 44484.64 | P40: 1.03 | Q40: 0.03 | R40: =P40-Q40 -> 1 | S40: 1.661e-05 | T40: 62000 | U40: =P40/T40 -> 1.6612903e-05 | V40: =R40/(S40*$I$12) -> 0.91816392
B41: 44332.591 | C41: 2.06 | D41: 0.06 | E41: =C41-D41 -> 2 | F41: 4.423e-05 | G41: 45218.18 | H41: =E41/G41 -> 4.4229998e-05 | I41: =G41+((J41-E41)/E41)*G41 -> 47931.271 | J41: =C41+D41 -> 2.12 | K41: =L41/J41 -> 1.4557243 | L41: =F41*$L$5 -> 3.0861354 | M41: =L41/C41 -> 1.498124 | O41: 44488.608 | P41: 1.03 | Q41: 0.03 | R41: =P41-Q41 -> 1 | S41: 1.609e-05 | T41: 64000 | U41: =P41/T41 -> 1.609375e-05 | V41: =R41/(S41*$I$12) -> 0.94783733
B42: 44332.617 | C42: 2.06 | D42: 0.06 | E42: =C42-D42 -> 2 | F42: 4.427e-05 | G42: 45177.32 | H42: =E42/G42 -> 4.4270001e-05 | I42: =G42+((J42-E42)/E42)*G42 -> 47887.959 | J42: =C42+D42 -> 2.12 | K42: =L42/J42 -> 1.4570408 | L42: =F42*$L$5 -> 3.0889264 | M42: =L42/C42 -> 1.4994788 | O42: 44489.4 | P42: 2.06 | Q42: 0.06 | R42: =P42-Q42 -> 2 | S42: 3.097e-05 | T42: 66515.98 | U42: =P42/T42 -> 3.0970001e-05 | V42: =R42/(S42*$I$12) -> 0.9848694
B43: 44332.658 | C43: 1.03 | D43: 0.03 | E43: =C43-D43 -> 1 | F43: 2.275e-05 | G43: 43956.04 | H43: =E43/G43 -> 2.2750002e-05 | I43: =G43+((J43-E43)/E43)*G43 -> 46593.402 | J43: =C43+D43 -> 1.06 | K43: =L43/J43 -> 1.4975233 | L43: =F43*$L$5 -> 1.5873747 | M43: =L43/C43 -> 1.5411404 | O43: 44508.865 | P43: 2.06 | Q43: 0.06 | R43: =P43-Q43 -> 2 | S43: 3.046e-05 | T43: 67629.68 | U43: =P43/T43 -> 3.0459999e-05 | V43: =R43/(S43*$I$12) -> 1.0013593
B44: 44334.86 | C44: 2.06 | D44: 0.06 | E44: =C44-D44 -> 2 | F44: 4.854e-05 | G44: 41203.13 | H44: =E44/G44 -> 4.8540002e-05 | I44: =G44+((J44-E44)/E44)*G44 -> 43675.318 | J44: =C44+D44 -> 2.12 | K44: =L44/J44 -> 1.5975776 | L44: =F44*$L$5 -> 3.3868644 | M44: =L44/C44 -> 1.6441089 | O44: 45292.994 | P44: 100 | Q44: 2.25 | R44: =P44-Q44 -> 97.75 | S44: 0.00221788 | T44: 45088.08 | U44: =P44/T44 -> 0.0022178811 | V44: =R44/(S44*$I$12) -> 0.67215367
B45: 44334.997 | C45: 2.06 | D45: 0.06 | E45: =C45-D45 -> 2 | F45: 5.173e-05 | G45: 38662.28 | H45: =E45/G45 -> 5.1730007e-05 | I45: =G45+((J45-E45)/E45)*G45 -> 40982.017 | J45: =C45+D45 -> 2.12 | K45: =L45/J45 -> 1.7025687 | L45: =F45*$L$5 -> 3.6094457 | M45: =L45/C45 -> 1.7521581 | O45: 45299.522 | P45: 127.68 | Q45: 2.56 | R45: =P45-Q45 -> 125.12 | S45: 0.0027636364 | T45: 46200 | U45: =P45/T45 -> 0.0027636364 | V45: =R45/(S45*$I$12) -> 0.6904555
B46: 44340.32 | C46: 2.06 | D46: 0.06 | E46: =C46-D46 -> 2 | F46: 5.186e-05 | G46: 38565.37 | H46: =E46/G46 -> 5.1859998e-05 | I46: =G46+((J46-E46)/E46)*G46 -> 40879.292 | J46: =C46+D46 -> 2.12 | K46: =L46/J46 -> 1.7068474 | L46: =F46*$L$5 -> 3.6185165 | M46: =L46/C46 -> 1.7565614 | O46: 45331.517 | P46: 100 | Q46: 2.25 | R46: =P46-Q46 -> 97.75 | S46: 0.00208333 | T46: 48000 | U46: =P46/T46 -> 0.0020833333 | V46: =R46/(S46*$I$12) -> 0.71556412
... B64: 44447.046 | C64: 10.23 | D64: 0.23 | E64: =C64-D64 -> 10 | F64: 0.00021611 | G64: 46272.73 | H64: =E64/G64 -> 0.00021611001 | I64: =G64+((J64-E64)/E64)*G64 -> 48401.276 | J64: =C64+D64 -> 10.46 | K64: =L64/J64 -> 1.4415882 | L64: =F64*$L$5 -> 15.079013 | M64: =L64/C64 -> 1.4739993 | O64: 45818.713 | P64: 50 | Q64: 1.49 | R64: =P64-Q64 -> 48.51 | S64: 0.00042992 | T64: 116300 | U64: =P64/T64 -> 0.00042992261 | V64: =R64/(S64*$I$12) -> 1.7208122
B65: 44449.784 | C65: 5.15 | D65: 0.15 | E65: =C65-D65 -> 5 | F65: 0.0001117 | G65: 44762.76 | H65: =E65/G65 -> 0.00011169999 | I65: =G65+((J65-E65)/E65)*G65 -> 47448.526 | J65: =C65+D65 -> 5.3 | K65: =L65/J65 -> 1.4705349 | L65: =F65*$L$5 -> 7.7938351 | M65: =L65/C65 -> 1.513366
B66: 44452.401 | C66: 10.23 | D66: 0.23 | E66: =C66-D66 -> 10 | F66: 0.00022758 | G66: 43940.59 | H66: =E66/G66 -> 0.00022758001 | I66: =G66+((J66-E66)/E66)*G66 -> 45961.857 | J66: =C66+D66 -> 10.46 | K66: =L66/J66 -> 1.5181002 | L66: =F66*$L$5 -> 15.879329 | M66: =L66/C66 -> 1.5522315
B67: 44459.582 | C67: 10.23 | D67: 0.23 | E67: =C67-D67 -> 10 | F67: 0.00023064 | G67: 43357.61 | H67: =E67/G67 -> 0.00023064002 | I67: =G67+((J67-E67)/E67)*G67 -> 45352.06 | J67: =C67+D67 -> 10.46 | K67: =L67/J67 -> 1.5385123 | L67: =F67*$L$5 -> 16.092839 | M67: =L67/C67 -> 1.5731026
B68: 44459.84 | C68: 10.23 | D68: 0.23 | E68: =C68-D68 -> 10 | F68: 0.00023912 | G68: 41820.01 | H68: =E68/G68 -> 0.00023911998 | I68: =G68+((J68-E68)/E68)*G68 -> 43743.73 | J68: =C68+D68 -> 10.46 | K68: =L68/J68 -> 1.5950792 | L68: =F68*$L$5 -> 16.684529 | M68: =L68/C68 -> 1.6309412
B69: 44460.753 | C69: 4.12 | D69: 0.12 | E69: =C69-D69 -> 4 | F69: 9.87e-05 | G69: 40526.85 | H69: =E69/G69 -> 9.8699998e-05 | I69: =G69+((J69-E69)/E69)*G69 -> 42958.461 | J69: =C69+D69 -> 4.24 | K69: =L69/J69 -> 1.6242368 | L69: =F69*$L$5 -> 6.8867639 | M69: =L69/C69 -> 1.6715446
B70: 44516.014 | C70: 4.2 | D70: 0.13 | E70: =C70-D70 -> 4.07 | F70: 6.692e-05 | G70: 60818.89 | H70: =E70/G70 -> 6.6919998e-05 | I70: =G70+((J70-E70)/E70)*G70 -> 64704.126 | J70: =C70+D70 -> 4.33 | K70: =L70/J70 -> 1.0783657 | L70: =F70*$L$5 -> 4.6693236 | M70: =L70/C70 -> 1.1117437
B71: 44518.708 | C71: 4.12 | D71: 0.12 | E71: =C71-D71 -> 4 | F71: 7.06e-05 | G71: 56660 | H71: =E71/G71 -> 7.0596541e-05 | I71: =G71+((J71-E71)/E71)*G71 -> 60059.6 | J71: =C71+D71 -> 4.24 | K71: =L71/J71 -> 1.1618147 | L71: =F71*$L$5 -> 4.9260945 | M71: =L71/C71 -> 1.195654
B72: 44526.12 | C72: 10.23 | D72: 0.23 | E72: =C72-D72 -> 10 | F72: 0.00018182 | G72: 55000 | H72: =E72/G72 -> 0.00018181818 | I72: =G72+((J72-E72)/E72)*G72 -> 57530 | J72: =C72+D72 -> 10.46 | K72: =L72/J72 -> 1.2128526 | L72: =F72*$L$5 -> 12.686438 | M72: =L72/C72 -> 1.240121
B73: 44526.324 | C73: 10.23 | D73: 0.23 | E73: =C73-D73 -> 10 | F73: 0.00018382 | G73: 54401.04 | H73: =E73/G73 -> 0.00018382002 | I73: =G73+((J73-E73)/E73)*G73 -> 56903.488 | J73: =C73+D73 -> 10.46 | K73: =L73/J73 -> 1.2261938 | L73: =F73*$L$5 -> 12.825987 | M73: =L73/C73 -> 1.2537622
B74: 44533.858 | C74: 10.23 | D74: 0.23 | E74: =C74-D74 -> 10 | F74: 0.00018916 | G74: 52865.3 | H74: =E74/G74 -> 0.00018916 | I74: =G74+((J74-E74)/E74)*G74 -> 55297.104 | J74: =C74+D74 -> 10.46 | K74: =L74/J74 -> 1.2618149 | L74: =F74*$L$5 -> 13.198584 | M74: =L74/C74 -> 1.2901842
B75: 44534.532 | C75: 10.23 | D75: 0.23 | E75: =C75-D75 -> 10 | F75: 0.00020515 | G75: 48744.82 | H75: =E75/G75 -> 0.00020515 | I75: =G75+((J75-E75)/E75)*G75 -> 50987.082 | J75: =C75+D75 -> 10.46 | K75: =L75/J75 -> 1.3684782 | L75: =F75*$L$5 -> 14.314282 | M75: =L75/C75 -> 1.3992455
B76: 44569.485 | C76: 10.23 | D76: 0.23 | E76: =C76-D76 -> 10 | F76: 0.00024343 | G76: 41079.57 | H76: =E76/G76 -> 0.00024343001 | I76: =G76+((J76-E76)/E76)*G76 -> 42969.23 | J76: =C76+D76 -> 10.46 | K76: =L76/J76 -> 1.6238296 | L76: =F76*$L$5 -> 16.985258 | M76: =L76/C76 -> 1.660338
... B108: 45753.522 | C108: 50 | D108: 1.12 | E108: =C108-D108 -> 48.88 | F108: 0.00059975 | G108: 81500 | H108: =E108/G108 -> 0.0005997546 | I108: =G108+((J108-E108)/E108)*G108 -> 85234.861 | J108: =C108+D108 -> 51.12 | K108: =L108/J108 -> 0.81861077 | L108: =F108*$L$5 -> 41.847382 | M108: =L108/C108 -> 0.83694765
B115: PREDICTIVE | O115: PREDICTIVE
B116: Enter your desired buying information in the line below and then copy/paste your data in the line above to calculate your results. | O116: Enter your desired buying information in the line below and then copy/paste your data in the line above to calculate your results.
B118: Enter Data Here: | C118: 1.03 | D118: =C118*D8 -> 0.023871939 | E118: =C118-D118 -> 1.0061281 | F118: 1.851e-05 | G118: =E118/F118 -> 54355.919 | H118: =E118/G118 -> 1.851e-05 | I118: =G118+((J118-E118)/E118)*G118 -> 56935.275 | J118: =C118+D118 -> 1.0538719 | K118: =L118/J118 -> 1.2255093 | L118: =F118*$L$5 -> 1.2915299 | M118: =L118/C118 -> 1.2539125 | O118: Enter Data Here: | P118: 1 | Q118: =P118*$E$8 -> 0.022993574 | R118: =P118-Q118 -> 0.97700643 | S118: 0.00029 | T118: =P118/S118 -> 3448.2759 | U118: =P118/T118 -> 0.00029 | V118: =R118/(S118*$L$6) -> #DIV/0!
B119: Enter Data Here: | C119: 82.79 | D119: =C119*D8 -> 1.918794 | E119: =C119-D119 -> 80.871206 | F119: =E119/G119 -> 0.0013478534 | G119: 60000 | H119: =E119/G119 -> 0.0013478534 | I119: =G119+((J119-E119)/E119)*G119 -> 62847.185 | J119: =C119+D119 -> 84.708794 | K119: =L119/J119 -> 1.1102281 | L119: =F119*$L$5 -> 94.046082 | M119: =L119/C119 -> 1.1359594 | O119: Enter Data Here: | P119: 20 | Q119: =P119*$E$8 -> 0.45987148 | R119: =P119-Q119 -> 19.540129 | S119: =P119/T119 -> 0.00027777778 | T119: 72000 | U119: =P119/T119 -> 0.00027777778 | V119: =R119/(S119*$L$6) -> #DIV/0!

Sheet Stocks
D2: Stock Tracker_v2.0 | O2: 2905.78 | P2: <- Before Oct 31... App no longer shows VSP so having to infer manually...
D3: USD | G3: BTC | O3: 1191.65 | P3: <- This is what I had before
D4: Pre | E4: Fees | F4: Post | G4: Bought/Sold | L4: VSP | M4: 4251.2 | O4: 1193.68 | P4: <- This is what I had on 4/11/2024, then looked at my phone and saw it was 1191.65... Not sure if there was a correction issued or if I made a mistake but making a note of it
C5: Total Bought | D5: =SUM(D17:D1000) -> 14320.56 | E5: =SUM(E17:E1000) -> 10005.71 | F5: =SUM(F17:F1000) -> 9960.35 | H5: LIQUID PROFIT | I5: =(D8-D7)+E6 -> 1869.9 | J5: =(F6+D8)/D5 -> 1.1304111 | K5: Current Market Value | M5: 10755.35
C6: Total Sold | D6: =SUM(L17:L1000) -> 5435.11 | E6: =SUM(M17:M1000) -> 2.34 | F6: =D6-E6 -> 5432.77 | H6: LIQUID VALUE | I6: =D8+F6 -> 16188.12 | J6: =I6/D5 -> 1.1304111 | K6: Minimum Market Value | P6: On 4/12/2024, noticed the Investment Cost was 550.30, rather than 552.58, and that the total investment was 1741.95, rather than 1744.03 *I had previously noted a 0.06 difference in the total investment but I let it go because it was so small..
C7: Balance | D7: =D5-F6 -> 8887.79 | E7: =E6+E5 -> 10008.05 | F7: =F5-D6 -> 4525.24 | H7: TOTAL VALUE | I7: =D5+I5 -> 16190.46 | J7: =I7/D5 -> 1.1305745 | K7: Buying Market Value | P7: The difference in the two noted above is 2.08, and if the previous error of about 0.06 is subtracted from the new error, the difference is 2.025, which describes the differences in the VSP on 4/11 and o
C8: Current Value | D8: =M5 -> 10755.35 | F8: =E6/D6 -> 0.00043053406 | G8: Overhead Fees | K8: Selling Market Value | P8: On 6/9/2024, total difference is $2.21 from CashApp to Model
C9: Liquidity | D9: =M5*G7 -> 0 | E9: =D7+(D7*F8) -> 8891.6165 | F9: Bottom Line
D11: Spent | E11: Fees | F11: Bought | G11: Shares Received | H11: Exchange Rate | I11: CR Calc Check | L11: Sold | M11: Fees | N11: Gained | O11: Shares Sold | P11: Exchange Rate | Q11: CR Calc Check
C12: AVERAGE | D12: =AVERAGE(D39:D1000) -> 40.927785 | E12: =AVERAGE(E17:E1000) -> 44.469822 | F12: =AVERAGE(F39:F1000) -> 44.123077 | G12: =AVERAGE(G17:G1000) -> #DIV/0! | H12: =AVERAGE(H17:H91) -> #DIV/0! | I12: =AVERAGE(I17:I91) -> #REF! | K12: AVERAGE | L12: =AVERAGE(L17:L1000) -> 39.384855 | M12: =AVERAGE(M17:M1000) -> 0.016956522 | N12: =AVERAGE(N17:N1000) -> 39.367899 | O12: =AVERAGE(O17:O1000) -> 2.9951907 | P12: =AVERAGE(P17:P91) -> 210.09078 | Q12: =AVERAGE(Q17:Q91) -> 15.562393
C13: INVESTMENT | D13: =SUM(D39:D1000) -> 13301.53 | E13: =SUM(E17:E1000) -> 10005.71 | F13: =SUM(F39:F91000) -> 9177.6 | G13: =SUM(G17:G91) -> 0 | I13: =SUM(I17:I91) -> #REF! | K13: SUM | L13: =SUM(L17:L1000) -> 5435.11 | M13: =COUNT(L17:L1000)*0.02 -> 2.76 | N13: =SUM(N17:N1000) -> 5432.77 | O13: =SUM(O17:O91) -> 116.26954 | Q13: =SUM(Q17:Q91) -> 1167.1795
C16: Date & Time | D16: Bought | E16: Add Cash | F16: Bank | G16: Shares Received | H16: Exchange Rate | I16: CR Calc Check | K16: Date & Time | L16: Sold | M16: Fees | N16: Gained | O16: Shares Sold | P16: Exchange Rate | Q16: CR Calc Check | S16: Cashout | T16: Fees (Insant) | U16: Dividend Total
D17: 30 | E17: =10+10+10 -> 30 | F17: 30 | I17: =#REF!/H17 -> #REF! | L17: 10.41 | M17: 0.02 | N17: =L17-M17 -> 10.39 | Q17: =P17*O17 -> 0 | S17: =98.82+50+11+65+100+60+84.75+(-10)+4+18.43+85-150+90+15+20+55+(-50)+26.3+(-20)+(-20)+(-25)+(-25)+(-13)+(-49.15)+(-50+2.23)+55+25+60+2+(-48.78)+30+115-0.32 -> 611.28 | T17: =1.73+0.25+1.48+0.32+0.46 -> 4.24 | U17: =SUM(S22:S100) -> 33.83
D18: =20+20+10+20+10+10+20+10+10+10+10 -> 150 | E18: =20+20+10+10+10+10+10+20+10+10+20 -> 150 | F18: 150 | I18: =#REF!/H18 -> #REF! | L18: 10 | M18: 0.02 | N18: =L18-M18 -> 9.98 | Q18: =P18*O18 -> 0
D19: 20 | E19: =20 -> 20 | F19: 20 | I19: =#REF!/H19 -> #REF! | L19: 15.45 | M19: 0.02 | N19: =L19-M19 -> 15.43 | Q19: =P19*O19 -> 0 | S19: =SUM(L32:L200)-SUM(D39:D300)-SUM(M32:M200)+SUM(Bitcoin!R46:R114)-SUM(Bitcoin!C87:C114)-S17+SUM(E39:E300)+SUM(S25:S105) -> 1259.13 | T19: Wallet Calculation
D20: =20+20+10+20+14.36+10 -> 94.36 | E20: =20+20+14.36+20+10+10 -> 94.36 | F20: 94.36 | I20: =#REF!/H20 -> #REF! | L20: 10 | M20: 0.02 | N20: =L20-M20 -> 9.98 | Q20: =P20*O20 -> 0
D21: =15+20+15.64 -> 50.64 | E21: =15+20+15.64 -> 50.64 | F21: 50.64 | I21: =#REF!/H21 -> #REF! | L21: 5 | M21: 0.02 | N21: =L21-M21 -> 4.98 | Q21: =P21*O21 -> 0 | S21: Dividends
D22: =20+20+15+10+10 -> 75 | E22: =20+20+5+10+20 -> 75 | F22: 75 | I22: =#REF!/H22 -> #REF! | L22: 10.83 | M22: 0.02 | N22: =L22-M22 -> 10.81 | Q22: =P22*O22 -> 0 | S22: 0.19 | T22: Broadcom
D23: 10 | I23: =#REF!/H23 -> #REF! | L23: 21.13 | M23: 0.02 | N23: =L23-M23 -> 21.11 | Q23: =P23*O23 -> 0 | S23: 0.03
D24: 10 | L24: =34.31 -> 34.31 | M24: 0.02 | N24: =L24-M24 -> 34.29 | Q24: =P24*O24 -> 0 | S24: 0.02 | T24: Dominos
D25: 10 | L25: 32.61 | M25: 0.02 | N25: =L25-M25 -> 32.59 | Q25: =P25*O25 -> 0 | S25: 0.01 | T25: General Electric
D26: 5 | L26: =39.65 -> 39.65 | M26: 0.02 | N26: =L26-M26 -> 39.63 | Q26: =P26*O26 -> 0 | S26: 0.09 | T26: Apple
D27: 10 | E27: 9.2 | F27: 9.2 | I27: =#REF!/H27 -> #REF! | L27: 22.89 | M27: 0.02 | N27: =L27-M27 -> 22.87 | Q27: =P27*O27 -> 0 | S27: 0.19 | T27: Charles Schwab
D28: =10+10 -> 20 | E28: =10+10 -> 20 | F28: =10+10 -> 20 | I28: =#REF!/H28 -> #REF! | L28: 21.46 | M28: 0.02 | N28: =L28-M28 -> 21.44 | Q28: =P28*O28 -> 0 | S28: 0.1 | T28: Conoco Phillips
D29: 5 | I29: =#REF!/H29 -> #REF! | L29: 10.25 | M29: 0.02 | N29: =L29-M29 -> 10.23 | Q29: =P29*O29 -> 0 | S29: 0.04 | T29: Conoco Phillips
D30: 20 | E30: 15.02 | F30: 15.02 | I30: =#REF!/H30 -> #REF! | L30: 10.46 | M30: 0.02 | N30: =L30-M30 -> 10.44 | Q30: =P30*O30 -> 0 | S30: 0.15 | T30: Pfizer
D31: 20 | E31: 20 | F31: 20 | I31: =#REF!/H31 -> #REF! | L31: 10.3 | M31: 0.02 | N31: =L31-M31 -> 10.28 | Q31: =P31*O31 -> 0 | S31: 0.2 | T31: Target
D32: 3.96 | I32: =#REF!/H32 -> #REF! | L32: 76.45 | M32: 0.02 | N32: =L32-M32 -> 76.43 | Q32: =P32*O32 -> 0 | S32: 0.3 | T32: Broadcom
D33: 10 | E33: 8.98 | F33: 8.98 | I33: =#REF!/H33 -> #REF! | L33: 21.45 | M33: 0.02 | N33: =L33-M33 -> 21.43 | Q33: =P33*O33 -> 0 | S33: 0.59 | T33: Medical Properties Trust
D34: =10 -> 10 | I34: =#REF!/H34 -> #REF! | L34: 10.9 | M34: 0.02 | N34: =L34-M34 -> 10.88 | Q34: =P34*O34 -> 0 | S34: 0.14 | T34: Apple
D35: =10+10+10+25+25+15.33+10+36.7+10+10+25+20+50+5+10+10+10 -> 292.03 | E35: =8.08+25+25+15.33+10+36.7+10+10+25+20 -> 185.11 | F35: =8.08+25+25+15.33+10+36.7+20+10+25+10 -> 185.11 | I35: =#REF!/H35 -> #REF! | L35: 10.8 | M35: 0.02 | N35: =L35-M35 -> 10.78 | Q35: =P35*O35 -> 0 | S35: 0.21 | T35: Broadcom
D36: 10 | E36: 49.81 | F36: 10 | I36: =#REF!/H36 -> #REF! | L36: 10.01 | M36: 0.02 | N36: =L36-M36 -> 9.99 | Q36: =P36*O36 -> 0 | S36: 0.59 | T36: Medical Properties Trust
D37: 10 | E37: 10 | F37: 10 | I37: =#REF!/H37 -> #REF! | L37: 10.45 | M37: 0.02 | N37: =L37-M37 -> 10.43 | Q37: =P37*O37 -> 0 | S37: 0.04 | T37: Apple
D38: =10.1+20+9+25.53+10+10+28.64+20+19.77 -> 153.04 | E38: =10+14.63+10+10 -> 44.63 | F38: =49.81+14.63+10+10 -> 84.44 | I38: =#REF!/H38 -> #REF! | L38: 10.05 | M38: 0.02 | N38: =L38-M38 -> 10.03 | Q38: =P38*O38 -> 0 | S38: 0.03 | T38: First Majestic Silver
D39: 20 | I39: =F39/H39 -> #DIV/0! | L39: 30.75 | M39: 0.02 | N39: =L39-M39 -> 30.73 | Q39: =P39*O39 -> 0 | S39: 0.34 | T39: Intel
D40: 20 | I40: =F40/H40 -> #DIV/0! | L40: 23.14 | M40: 0.02 | N40: =L40-M40 -> 23.12 | Q40: =P40*O40 -> 0 | S40: 0.25 | T40: Tractor Supply
D41: 15 | I41: =F41/H41 -> #DIV/0! | K41: 45317.42 | L41: 17.68 | M41: 0.02 | N41: =L41-M41 -> 17.66 | O41: 4.6153846 | P41: 3.83 | Q41: =P41*O41 -> 17.676923 | R41: Nokia | S41: 1.24 | T41: Broadcom
D42: 10 | E42: 10 | F42: 10 | I42: =F42/H42 -> #DIV/0! | K42: 45321.51 | L42: 17.39 | M42: 0.02 | N42: =L42-M42 -> 17.37 | O42: 0.12326772 | P42: 141.08 | Q42: =P42*O42 -> 17.39061 | R42: Phillips 66 | S42: 0.01 | T42: NVIDIA
D43: 25 | I43: =F43/H43 -> #DIV/0! | K43: 45324.574 | L43: 46.02 | M43: 0.02 | N43: =L43-M43 -> 46 | O43: 0.2678972 | P43: 171.78 | Q43: =P43*O43 -> 46.019381 | R43: Amazon | S43: 0.32 | T43: Medical Properties Trust
D44: 30 | I44: =F44/H44 -> #DIV/0! | K44: 45324.575 | L44: 25.6 | M44: 0.02 | N44: =L44-M44 -> 25.58 | O44: 0.52193374 | P44: 49.05 | Q44: =P44*O44 -> 25.60085 | R44: Cameco | S44: 0.06 | T44: Micron Technology
D45: 25 | I45: =F45/H45 -> #DIV/0! | K45: 45330.604 | L45: 27.78 | M45: 0.02 | N45: =L45-M45 -> 27.76 | O45: 3.1852003 | P45: 8.72 | Q45: =P45*O45 -> 27.774946 | R45: Iovance Biotheraputics | S45: 0.49 | T45: Tractor Supply
D46: 30 | I46: =F46/H46 -> #DIV/0! | K46: 45337.372 | L46: 52.74 | M46: 0.02 | N46: =L46-M46 -> 52.72 | O46: 3.0069958 | P46: 17.54 | Q46: =P46*O46 -> 52.742707 | R46: Lyft | S46: 0.28 | T46: Lockheed Martin
D47: 50 | I47: =F47/H47 -> #DIV/0! | K47: 45342.597 | L47: 50.3 | M47: 0.02 | N47: =L47-M47 -> 50.28 | O47: 49.291798 | P47: 1.02 | Q47: =P47*O47 -> 50.277634 | R47: Opko Health | S47: 0.01 | T47: NVIDIA
D48: 25 | I48: =F48/H48 -> #DIV/0! | K48: 45344.551 | L48: 10.5 | M48: 0.02 | N48: =L48-M48 -> 10.48 | O48: 0.11795401 | P48: 89.02 | Q48: =P48*O48 -> 10.500266 | R48: Logitech | S48: 1.17 | T48: Broadcom
D49: 25 | I49: =F49/H49 -> #DIV/0! | K49: 45348.617 | L49: 27.12 | M49: 0.02 | N49: =L49-M49 -> 27.1 | O49: 0.18017757 | P49: 150.52 | Q49: =P49*O49 -> 27.120328 | R49: Target | S49: 0.32 | T49: Medical Properties Trust
B50: AMD | D50: 50 | I50: =F50/H50 -> #DIV/0! | K50: 45348.623 | L50: 10.34 | M50: 0.02 | N50: =L50-M50 -> 10.32 | O50: 0.63537245 | P50: 16.27 | Q50: =P50*O50 -> 10.33751 | R50: NeoGenomics | S50: 0.13 | T50: Micron Technologies
B51: SMC | D51: 25 | E51: 1 | I51: =F51/H51 -> #DIV/0! | K51: 45349.433 | L51: 27.04 | M51: 0.02 | N51: =L51-M51 -> 27.02 | O51: 5.4599458 | P51: 4.95 | Q51: =P51*O51 -> 27.026732 | R51: Allogene Therapeutics | S51: 0.16 | T51: GE Aerospace
B52: Lending Tree | D52: 25 | I52: =F52/H52 -> #DIV/0! | K52: 45349.437 | L52: 59.6 | M52: 0.02 | N52: =L52-M52 -> 59.58 | O52: 0.04584027 | P52: 1300.17 | Q52: =P52*O52 -> 59.600144 | R52: Broadcom | S52: 0.38 | T52: Microchip Technology
B53: COMPASS Pathways | D53: 20 | I53: =F53/H53 -> #DIV/0! | K53: 45349.442 | L53: 29.22 | M53: 0.02 | N53: =L53-M53 -> 29.2 | O53: 1 | P53: 29.22 | Q53: =P53*O53 -> 29.22 | R53: Dutch Bros | S53: 0.51 | T53: Tractor Supply
B54: Opko Health | D54: 20 | I54: =F54/H54 -> #DIV/0! | K54: 45350.428 | L54: 28.8 | M54: 0.02 | N54: =L54-M54 -> 28.78 | O54: 0.79067384 | P54: 36.42 | Q54: =P54*O54 -> 28.796341 | R54: LendingTree | S54: 0.62 | T54: Lockheed Martin
B55: Broadcom | D55: 50 | I55: =F55/H55 -> #DIV/0! | K55: 45351.379 | L55: 56.68 | M55: 0.02 | N55: =L55-M55 -> 56.66 | O55: 0.30754317 | P55: 184.3 | Q55: =P55*O55 -> 56.680206 | R55: AMD | S55: 1.62 | T55: Broadcom
B56: Apple | D56: 30 | I56: =F56/H56 -> #DIV/0! | K56: 45352.455 | L56: 22.27 | M56: 0.02 | N56: =L56-M56 -> 22.25 | O56: 1.9588638 | P56: 11.37 | Q56: =P56*O56 -> 22.272282 | R56: COMPASS Pathways | S56: 0.01 | T56: NVIDIA
B57: Super Micro Computer | D57: 10 | I57: =F57/H57 -> #DIV/0! | K57: 45355.452 | L57: 65.4 | M57: 0.02 | N57: =L57-M57 -> 65.38 | O57: 0.05801659 | P57: 1127.26 | Q57: =P57*O57 -> 65.399781 | R57: Super Micro Computer | S57: 0.32 | T57: Medical Properties Trust
B58: AMD | D58: 20 | I58: =F58/H58 -> #DIV/0! | K58: 45356.395 | L58: 30.98 | M58: 0.02 | N58: =L58-M58 -> 30.96 | O58: 2.079175 | P58: 14.9 | Q58: =P58*O58 -> 30.979707 | R58: Gold Fields Limited | S58: 0.13 | T58: Micron Technology
B59: EchoStar | D59: 15 | I59: =F59/H59 -> #DIV/0! | K59: 45358.617 | L59: 20.09 | M59: 0.02 | N59: =L59-M59 -> 20.07 | O59: 0.1783803 | P59: 112.62 | Q59: =P59*O59 -> 20.089189 | R59: ConocoPhillips | S59: 0.21 | T59: GE Aerospace
B60: FuelCell Energy | D60: 20 | E60: 29.66 | I60: =F60/H60 -> #DIV/0! | K60: 45362.551 | L60: 10.4 | M60: 0.02 | N60: =L60-M60 -> 10.38 | O60: 0.8000768 | P60: 13 | Q60: =P60*O60 -> 10.400998 | R60: Rivian Automotive | S60: 0.8 | T60: Microchip Technology
